Workbook
Name nom_société: #REF!
Name LigneTitreRégion1..C7: #REF!
Name LigneTitreRégion2..G5: #REF!
Name LigneTitreRégion3..G26: #REF!

Sheet Suivi Client
B1: Prénom | C1: Nom Complet | D1: Mail | E1: Adresse | F1: Code Postale | G1: Ville | H1: Numéro de téléphone
A2: Carouge | B2: Léo | C2: ='Suivi Client'!$B2 & " " &'Suivi Client'!$A2 -> Léo Carouge | D2: leocarouge@gmail.com | E2: 144 Avenue de Flandre | F2: 75019 | G2: PARIS | H2: 645080351
A3: marrié | B3: Agnès | C3: ='Suivi Client'!$B3 & " " &'Suivi Client'!$A3 -> Agnès marrié
A4: leclézio | B4: Pierre | C4: ='Suivi Client'!$B4 & " " &'Suivi Client'!$A4 -> Pierre leclézio | F4: 75016 | G4: PARIS
A5: LAPEDAGNE | B5: GAEL | C5: ='Suivi Client'!$B5 & " " &'Suivi Client'!$A5 -> GAEL LAPEDAGNE | G5: SAINT JEAN DE LUZ
A6: MADARIAGA | B6: OIHAN | C6: ='Suivi Client'!$B6 & " " &'Suivi Client'!$A6 -> OIHAN MADARIAGA | G6: HENDAYE
A7: WOJTOWIC | B7: ACHILLE | C7: ='Suivi Client'!$B7 & " " &'Suivi Client'!$A7 -> ACHILLE WOJTOWIC | G7: SAINT JEAN DE LUZ
A8: LASSERRE | B8: BASTIEN | C8: ='Suivi Client'!$B8 & " " &'Suivi Client'!$A8 -> BASTIEN LASSERRE | G8: CIBOUR
A9: LANDRIEU | B9: HUGO | C9: ='Suivi Client'!$B9 & " " &'Suivi Client'!$A9 -> HUGO LANDRIEU | G9: SAINT JEAN DE LUZ
A10: COUDRET | B10: CHARLOTTE | C10: ='Suivi Client'!$B10 & " " &'Suivi Client'!$A10 -> CHARLOTTE COUDRET | G10: SAINT JEAN DE LUZ
A11: BILBAO | B11: XANTI | C11: ='Suivi Client'!$B11 & " " &'Suivi Client'!$A11 -> XANTI BILBAO | G11: CIBOUR
A12: POULHES | B12: CHARLES | C12: ='Suivi Client'!$B12 & " " &'Suivi Client'!$A12 -> CHARLES POULHES | F12: 75019 | G12: PARIS
A13: SIMON | B13: ALEXANDRE | C13: ='Suivi Client'!$B13 & " " &'Suivi Client'!$A13 -> ALEXANDRE SIMON | F13: 75020 | G13: PARIS
A14: ETXABE | B14: GENTZA | C14: ='Suivi Client'!$B14 & " " &'Suivi Client'!$A14 -> GENTZA ETXABE | G14: URRUGNE
A15: COTINA | B15: BIXENTE | C15: ='Suivi Client'!$B15 & " " &'Suivi Client'!$A15 -> BIXENTE COTINA | G15: URRUGNE
A16: AIZPURUA | B16: GABI | C16: ='Suivi Client'!$B16 & " " &'Suivi Client'!$A16 -> GABI AIZPURUA | G16: HENDAYE
A17: MATESANZE | B17: JAIME | C17: ='Suivi Client'!$B17 & " " &'Suivi Client'!$A17 -> JAIME MATESANZE | G17: HENDAYE
A18: DUBARBIER | B18: JOELLE | C18: ='Suivi Client'!$B18 & " " &'Suivi Client'!$A18 -> JOELLE DUBARBIER | G18: SAINT JEAN DE LUZ
A19: Cireddu | B19: Gregory | C19: ='Suivi Client'!$B19 & " " &'Suivi Client'!$A19 -> Gregory Cireddu | F19: 57 | G19: Mazeroy
A20: Gintrand | B20: Philippe | C20: ='Suivi Client'!$B20 & " " &'Suivi Client'!$A20 -> Philippe Gintrand | E20: 2 CHEMIN D OLLANET | F20: 26240 | G20: St vallier
A21: Fassaert | B21: Pascal | C21: ='Suivi Client'!$B21 & " " &'Suivi Client'!$A21 -> Pascal Fassaert | E21: ROUTE DE PLANCY | F21: 10170 | G21: Mery/Seine
A22: Soulhac | B22: Eric | C22: ='Suivi Client'!$B22 & " " &'Suivi Client'!$A22 -> Eric Soulhac | E22: 6 ALLLEE DES TERRASSES DU RHONE | F22: 26140 | G22: St vallier
A23: Bouilot | B23: Jac/dan | C23: ='Suivi Client'!$B23 & " " &'Suivi Client'!$A23 -> Jac/dan Bouilot | E23: 11 RUE LUCIE AUBRAC | F23: 26240 | G23: St vallier
A24: Gintrand | C24: ='Suivi Client'!$B24 & " " &'Suivi Client'!$A24 -> Gintrand | G24: Nimes
A25: Xantie | C25: ='Suivi Client'!$B25 & " " &'Suivi Client'!$A25 -> Xantie | G25: St jean de luz
A26: Morel | B26: Jacques | C26: ='Suivi Client'!$B26 & " " &'Suivi Client'!$A26 -> Jacques Morel | E26: 20 RUE DU 11 NOVEMBRE | F26: 10300 | G26: ST E SAVINE
A27: Jeff | B27: Fassaert | C27: ='Suivi Client'!$B27 & " " &'Suivi Client'!$A27 -> Fassaert Jeff | G27: concarneau
A28: Fassaert | B28: ZACHARIE | C28: ='Suivi Client'!$B28 & " " &'Suivi Client'!$A28 -> ZACHARIE Fassaert | G28: PARIS
A29: FISHER | B29: LEO | C29: ='Suivi Client'!$B29 & " " &'Suivi Client'!$A29 -> LEO FISHER | G29: PARIS
A30: camille | B30: cireddu | C30: ='Suivi Client'!$B30 & " " &'Suivi Client'!$A30 -> cireddu camille | G30: bordeaux
A31: Jean-Louis | B31: Dubois | C31: ='Suivi Client'!$B31 & " " &'Suivi Client'!$A31 -> Dubois Jean-Louis | D31: Jeanlouisdubois@aol.com | E31: 2 impasse le grand fin | F31: 21110 | G31: Torey en plaine
A32: Chataigner | B32: Aymeric | C32: ='Suivi Client'!$B32 & " " &'Suivi Client'!$A32 -> Aymeric Chataigner | G32: Talence
A33: Meon | B33: Benoit | C33: ='Suivi Client'!$B33 & " " &'Suivi Client'!$A33 -> Benoit Meon | D33: b.meon@acofi.com | G33: PARIS
A34: Valerie | B34: Carouge | C34: ='Suivi Client'!$B34 & " " &'Suivi Client'!$A34 -> Carouge Valerie | E34: RUE DE VERDUN | G34: EPERNAY
A35: Carouge | B35: Nino | C35: ='Suivi Client'!$B35 & " " &'Suivi Client'!$A35 -> Nino Carouge | G35: flavigny
A36: jaunet | B36: cedric | C36: ='Suivi Client'!$B36 & " " &'Suivi Client'!$A36 -> cedric jaunet | G36: emmerainville
C37: ='Suivi Client'!$B37 & " " &'Suivi Client'!$A37
A38: Ville | B38: Pascal | C38: ='Suivi Client'!$B38 & " " &'Suivi Client'!$A38 -> Pascal Ville | G38: TROYES
A39: Fassaert | B39: MICHELLE | C39: ='Suivi Client'!$B39 & " " &'Suivi Client'!$A39 -> MICHELLE Fassaert | G39: MERY SUR SEINE
A40: MARTIN | B40: JEAN | C40: ='Suivi Client'!$B40 & " " &'Suivi Client'!$A40 -> JEAN MARTIN | F40: 75019 | G40: PARIS
A41: BOUTMY | B41: Stanislas | C41: ='Suivi Client'!$B41 & " " &'Suivi Client'!$A41 -> Stanislas BOUTMY | D41: stanislas.boutmy@sienna-im.com | G41: PARIS
A42: CONSO | C42: ='Suivi Client'!$B42 & " " &'Suivi Client'!$A42 -> CONSO
A43: CADEAU | C43: ='Suivi Client'!$B43 & " " &'Suivi Client'!$A43 -> CADEAU
A44: Gautier | B44: Valerie Franck | C44: ='Suivi Client'!$B44 & " " &'Suivi Client'!$A44 -> Valerie Franck Gautier | D44: valerie-art@sfr.fr | F44: 77 | G44: Faviere
A45: Francoise | B45: amie dubarbier | C45: ='Suivi Client'!$B45 & " " &'Suivi Client'!$A45 -> amie dubarbier Francoise
A46: Sandre | B46: LOVERGNE | C46: ='Suivi Client'!$B46 & " " &'Suivi Client'!$A46 -> LOVERGNE Sandre | G46: PARIS
A47: Lucile | B47: Gauchet | C47: ='Suivi Client'!$B47 & " " &'Suivi Client'!$A47 -> Gauchet Lucile
A48: Parent | B48: Philémon | C48: ='Suivi Client'!$B48 & " " &'Suivi Client'!$A48 -> Philémon Parent | F48: 51200 | G48: Epernay
A49: Briest | B49: Paul | C49: ='Suivi Client'!$B49 & " " &'Suivi Client'!$A49 -> Paul Briest | D49: paul.briestcastaldo@gmail.com | E49: 2 RUE ST REMY | F49: 51150 | G49: Athis
A50: Carouge | B50: James | C50: ='Suivi Client'!$B50 & " " &'Suivi Client'!$A50 -> James Carouge | D50: famille-carouge@orange.fr | E50: 6rue de l eglise | F50: 51190 | G50: FLAVIGNY
A51: Paquin | B51: Regis | C51: ='Suivi Client'!$B51 & " " &'Suivi Client'!$A51 -> Regis Paquin | E51: Rue hermiere | F51: 77177 | G51: Faviere
A52: Tracol | B52: Aurelien | C52: ='Suivi Client'!$B52 & " " &'Suivi Client'!$A52 -> Aurelien Tracol | E52: 165route du suc de verre | F52: 7290 | G52: ARDOIX
A53: Fassaert | B53: Yannick | C53: ='Suivi Client'!$B53 & " " &'Suivi Client'!$A53 -> Yannick Fassaert | G53: Troyes
A54: Meon | B54: François | C54: ='Suivi Client'!$B54 & " " &'Suivi Client'!$A54 -> François Meon | E54: 38 Avenue Jean Faure | F54: 42480 | G54: Fouillouse
A55: Girard | B55: Jacques | C55: ='Suivi Client'!$B55 & " " &'Suivi Client'!$A55 -> Jacques Girard | E55: 385 rue des vignes | F55: 26240 | G55: St barthélemy de Vals
A56: Camille | B56: Zimmermann | C56: ='Suivi Client'!$B56 & " " &'Suivi Client'!$A56 -> Zimmermann Camille | G56: Paris
A57: Garval /Amaral | C57: ='Suivi Client'!$B57 & " " &'Suivi Client'!$A57 -> Garval /Amaral | G57: reims
A58: Sarha | C58: ='Suivi Client'!$B58 & " " &'Suivi Client'!$A58 -> Sarha | G58: paris
A59: Straubhaar | B59: Benjamin | C59: ='Suivi Client'!$B59 & " " &'Suivi Client'!$A59 -> Benjamin Straubhaar | G59: Bordeaux
A60: Karine GATE | C60: ='Suivi Client'!$B60 & " " &'Suivi Client'!$A60 -> Karine GATE | G60: PARIS
A61: Morvan | B61: Daphne | C61: ='Suivi Client'!$B61 & " " &'Suivi Client'!$A61 -> Daphne Morvan | E61: 425 cote de Manoubrey | F61: 33550 | G61: TABANAC
A62: Surman | B62: Fanny | C62: ='Suivi Client'!$B62 & " " &'Suivi Client'!$A62 -> Fanny Surman | F62: 31520 | G62: RAMONVILLE SAINT AGNE
A63: Dubourdieu | B63: Alice | C63: ='Suivi Client'!$B63 & " " &'Suivi Client'!$A63 -> Alice Dubourdieu | E63: 78 AV DU MARECHAL FOCH F1-104 | F63: 40130 | G63: CAP BRETON
A64: Juste Aguer | B64: Manon | C64: ='Suivi Client'!$B64 & " " &'Suivi Client'!$A64 -> Manon Juste Aguer | E64: 5 Impasse Colette | F64: 40130 | G64: CAP BRETON
A65: ISABELLE | B65: CLAVERY | C65: ='Suivi Client'!$B65 & " " &'Suivi Client'!$A65 -> CLAVERY ISABELLE | G65: BORDEAUX
A66: JULIETTE | C66: ='Suivi Client'!$B66 & " " &'Suivi Client'!$A66 -> JULIETTE | G66: CABANE CAP FERRET
A67: KAES | B67: ANNE | C67: ='Suivi Client'!$B67 & " " &'Suivi Client'!$A67 -> ANNE KAES | G67: METZ
A68: ABRY | B68: PATRICK | C68: ='Suivi Client'!$B68 & " " &'Suivi Client'!$A68 -> PATRICK ABRY | F68: 29710 | G68: LEU DIT LEZAU POULDREUZIC
A69: LE CHAT PEAN | B69: MARIE CLAIRE | C69: ='Suivi Client'!$B69 & " " &'Suivi Client'!$A69 -> MARIE CLAIRE LE CHAT PEAN | G69: CONCARNEAU
A70: SUIRE | B70: MARILYN | C70: ='Suivi Client'!$B70 & " " &'Suivi Client'!$A70 -> MARILYN SUIRE | G70: LE TREVAUX
A71: PARENTON | B71: MARIE ANGE | C71: ='Suivi Client'!$B71 & " " &'Suivi Client'!$A71 -> MARIE ANGE PARENTON | G71: CONCARNEAU
A72: LE DOZE | B72: ANNE | C72: ='Suivi Client'!$B72 & " " &'Suivi Client'!$A72 -> ANNE LE DOZE | G72: CONCARNEAU
A73: Coutant | B73: Denis | C73: ='Suivi Client'!$B73 & " " &'Suivi Client'!$A73 -> Denis Coutant | G73: CONCARNEAU
A74: Thomas | B74: Hugo | C74: ='Suivi Client'!$B74 & " " &'Suivi Client'!$A74 -> Hugo Thomas | D74: hugo.thomas@sienna-im.com | E74: RUE CAIL | G74: PARIS
A75: Vendages | B75: Cadeau | C75: ='Suivi Client'!$B75 & " " &'Suivi Client'!$A75 -> Cadeau Vendages
A76: AGENCE LAGUILLON | C76: ='Suivi Client'!$B76 & " " &'Suivi Client'!$A76 -> AGENCE LAGUILLON | D76: ville@agence-laguillon.com | E76: 14 RUE DU PORT | F76: 64700 | G76: HENDAYE
A77: Laurent | B77: Marrié | C77: ='Suivi Client'!$B77 & " " &'Suivi Client'!$A77 -> Marrié Laurent
A78: Anael | C78: ='Suivi Client'!$B78 & " " &'Suivi Client'!$A78 -> Anael
A79: Alixane | B79: Bouhours | C79: ='Suivi Client'!$B79 & " " &'Suivi Client'!$A79 -> Bouhours Alixane
A80: Guillaume | B80: Gintrand | C80: ='Suivi Client'!$B80 & " " &'Suivi Client'!$A80 -> Gintrand Guillaume | D80: guillaume.gintrand@sauvegarde51.fr | E80: 8 RUE HENRIE MARTIN | F80: 51200 | G80: EPERNAY
A81: Simon | B81: Gintrand | C81: ='Suivi Client'!$B81 & " " &'Suivi Client'!$A81 -> Gintrand Simon | G81: REIMS
A82: RESTAURANT INATTENDU | B82: Emilien Rouable | C82: ='Suivi Client'!$B82 & " " &'Suivi Client'!$A82 -> Emilien Rouable RESTAURANT INATTENDU | E82: 36 Rue du general leclerc | F82: 94440 | G82: VILLECRESNES
A83: MARYSE | B83: DELMAS | C83: ='Suivi Client'!$B83 & " " &'Suivi Client'!$A83 -> DELMAS MARYSE | G83: PARIS
A84: CEDRIC | B84: JAUNET | C84: ='Suivi Client'!$B84 & " " &'Suivi Client'!$A84 -> JAUNET CEDRIC | G84: EMMERAINVILLE
A85: MARIE ANNE | B85: BEAU | C85: ='Suivi Client'!$B85 & " " &'Suivi Client'!$A85 -> BEAU MARIE ANNE | G85: ST AVOLD
A86: JACQUELINE | B86: HALLINGER | C86: ='Suivi Client'!$B86 & " " &'Suivi Client'!$A86 -> HALLINGER JACQUELINE | G86: CARLING
A87: MAXIME | B87: BERDOU | C87: ='Suivi Client'!$B87 & " " &'Suivi Client'!$A87 -> BERDOU MAXIME | G87: ST JEAN DE LUZ
A88: JEAN CHRISTOPHE | B88: GONDRE | C88: ='Suivi Client'!$B88 & " " &'Suivi Client'!$A88 -> GONDRE JEAN CHRISTOPHE | D88: 230 MONTEE ST BARDOUX | G88: 26260
A89: FABIENNE | B89: DUFOUR | C89: ='Suivi Client'!$B89 & " " &'Suivi Client'!$A89 -> DUFOUR FABIENNE | G89: METZ
A90: LYDIA | C90: ='Suivi Client'!$B90 & " " &'Suivi Client'!$A90 -> LYDIA | G90: METZ
A91: MANFREDI | B91: docteur RENZO | C91: ='Suivi Client'!$B91 & " " &'Suivi Client'!$A91 -> docteur RENZO MANFREDI | E91: CENTRE MEDICO CHIRURGICAL GASTON METIVET 48 RUE ALSACE LORRAINE | F91: 94100 | G91: SAINT-MAUR-DES-FOSSES
A92: ZUPPINGER | B92: ANNE | C92: ='Suivi Client'!$B92 & " " &'Suivi Client'!$A92 -> ANNE ZUPPINGER | G92: SAINT JEAN DE LUZ
A93: BASTIEN | B93: SEJOURNE | C93: ='Suivi Client'!$B93 & " " &'Suivi Client'!$A93 -> SEJOURNE BASTIEN | F93: 51190 | G93: FLAVIGNY
A94: Thaîs | B94: DE MAUPEOU | C94: ='Suivi Client'!$B94 & " " &'Suivi Client'!$A94 -> DE MAUPEOU Thaîs | G94: PARIS
A95: Jeremie | B95: Locquet | C95: ='Suivi Client'!$B95 & " " &'Suivi Client'!$A95 -> Locquet Jeremie | G95: PARIS
A96: MARIE-SOPHIE | B96: DELFINI | C96: ='Suivi Client'!$B96 & " " &'Suivi Client'!$A96 -> DELFINI MARIE-SOPHIE | D96: msophie.delphini@icloud.com | E96: 2rue tournon | F96: 75006 | G96: PARIS
A97: Eleonore | B97: Besson | C97: ='Suivi Client'!$B97 & " " &'Suivi Client'!$A97 -> Besson Eleonore | G97: PARIS
A98: Benedicte | B98: Dumant | C98: ='Suivi Client'!$B98 & " " &'Suivi Client'!$A98 -> Dumant Benedicte | G98: PARIS
A99: SARAH | B99: BERTHOLON | C99: ='Suivi Client'!$B99 & " " &'Suivi Client'!$A99 -> BERTHOLON SARAH | G99: PARIS
A100: MARIE CAPUCINE | B100: GOUBE | C100: ='Suivi Client'!$B100 & " " &'Suivi Client'!$A100 -> GOUBE MARIE CAPUCINE | D100: mcapucine.goube@gmail.com | E100: Chemin Parlementia | F100: 64210 | G100: BIDART
...

Sheet Feuille 68

Sheet Suivi Facturation 2025
A1: N?8M | B1: Nom Client | C1: NB Selection | D1: NB Rosé | E1: Nb blanc de blan | F1: Nb Prestige | G1: Magnum Selection | I1: Montant TTC bouteilles | J1: Montant HT | K1: Date de facturation | L1: Etat paiement | M1: Etat Commande | N1: paiement | O1: commentaire | P1: Prix Transport TTC | R1: Statistiques | S1: Prix unitaire TTC | T1: =S2/1.2 -> 14.166667
A2: 1 | B2: Léo Carouge | C2: 0 | I2: =IF(L2="Cadeau",0,C2*$S$2+D2*$S$3+E2*$S$4+F2*$S$5+G2*$S$6) -> 0 | J2: =I2/1.2 -> 0 | R2: Sélection | S2: 17
A3: 2 | B3: James Carouge | C3: 8 | E3: 2 | F3: 4 | I3: =IF(L3="Cadeau",0,C3*$S$2+D3*$S$3+E3*$S$4+F3*$S$5+G3*$S$6) -> 0 | J3: =I3/1.2 -> 0 | K3: 45715 | L3: Cadeau | M3: Livrer | N3: CONSO | R3: Rosé | S3: 19
A4: 3 | B4: James Carouge | D4: 2 | F4: 2 | I4: =IF(L4="Cadeau",0,C4*$S$2+D4*$S$3+E4*$S$4+F4*$S$5+G4*$S$6) -> 0 | J4: =I4/1.2 -> 0 | K4: 45725 | L4: Cadeau | M4: Livrer | N4: CONSO | R4: Blanc de blanc | S4: 18.5
A5: 4 | B5: James Carouge | C5: 1 | D5: 1 | E5: 2 | F5: 1 | I5: =IF(L5="Cadeau",0,C5*$S$2+D5*$S$3+E5*$S$4+F5*$S$5+G5*$S$6) -> 0 | J5: =I5/1.2 -> 0 | K5: 45732 | L5: Cadeau | M5: Livrer | N5: CONSO SARDAIGNE | R5: Prestige | S5: 27
A6: 5 | B6: CHRISTINE ABRY | E6: 24 | I6: =IF(L6="Cadeau",0,C6*$S$2+D6*$S$3+E6*$S$4+F6*$S$5+G6*$S$6) -> 444 | J6: =I6/1.2 -> 370 | K6: 45739 | L6: Payé | M6: Livrer | N6: LIVRASON | R6: Magnum Brut Selection | S6: 36
A7: 6 | B7: Aymeric Chataigner | C7: 12 | I7: =IF(L7="Cadeau",0,C7*$S$2+D7*$S$3+E7*$S$4+F7*$S$5+G7*$S$6) -> 204 | J7: =I7/1.2 -> 170 | K7: 45748 | L7: Payé | M7: Livrer | R7: Nb bouteilles vendues | S7: =SUM(C2:D1201) -> 759
A8: 7 | B8: MARC WEBER | E8: 18 | I8: =IF(L8="Cadeau",0,C8*$S$2+D8*$S$3+E8*$S$4+F8*$S$5+G8*$S$6) -> 333 | J8: =I8/1.2 -> 277.5 | K8: 45750 | L8: Payé | M8: Livrer | N8: LIVRAISON
A9: 8 | B9: James Carouge | C9: 1 | D9: 1 | E9: 2 | F9: 3 | I9: =IF(L9="Cadeau",0,C9*$S$2+D9*$S$3+E9*$S$4+F9*$S$5+G9*$S$6) -> 0 | J9: =I9/1.2 -> 0 | K9: 45748 | L9: Cadeau | M9: Livrer | N9: ANN SILVANO ET SARDAIGNE | R9: Chiffre d'affaire | S9: =SUM(I2:I1216) -> 20674.5
A10: 9 | B10: THOMAS BANGRATZ | C10: 36 | E10: 18 | I10: =IF(L10="Cadeau",0,C10*$S$2+D10*$S$3+E10*$S$4+F10*$S$5+G10*$S$6) -> 945 | J10: =I10/1.2 -> 787.5 | K10: 45752 | L10: Payé | M10: Livrer | N10: COLLEGUE LEO VIREMENT
A11: 10 | B11: PHILIPPE NOYARD | E11: 30 | I11: =IF(L11="Cadeau",0,C11*$S$2+D11*$S$3+E11*$S$4+F11*$S$5+G11*$S$6) -> 555 | J11: =I11/1.2 -> 462.5 | K11: 45788 | L11: Payé | M11: A habiller | N11: MARIAGE CADO 1 ROSE
A12: 11 | B12: Jacques Girard | C12: 12 | E12: 12 | I12: =IF(L12="Cadeau",0,C12*$S$2+D12*$S$3+E12*$S$4+F12*$S$5+G12*$S$6) -> 426 | J12: =I12/1.2 -> 355 | K12: 45783 | L12: Payé | M12: Livrer | N12: TRANSPORTER GINTRAND
A13: 12 | I13: =IF(L13="Cadeau",0,C13*$S$2+D13*$S$3+E13*$S$4+F13*$S$5+G13*$S$6) -> 0 | J13: =I13/1.2 -> 0
A14: 35 | B14: Philippe Gintrand | E14: 12 | I14: =IF(L14="Cadeau",0,C14*$S$2+D14*$S$3+E14*$S$4+F14*$S$5+G14*$S$6) -> 222 | J14: =I14/1.2 -> 185 | K14: 45783 | L14: En attente de paiement | N14: DEPOT
A15: 14 | B15: Regis Paquin | E15: 6 | I15: =IF(L15="Cadeau",0,C15*$S$2+D15*$S$3+E15*$S$4+F15*$S$5+G15*$S$6) -> 111 | J15: =I15/1.2 -> 92.5 | K15: 45788 | L15: Payé
A16: 15 | B16: CHRISTINE ABRY | C16: 24 | I16: =IF(L16="Cadeau",0,C16*$S$2+D16*$S$3+E16*$S$4+F16*$S$5+G16*$S$6) -> 408 | J16: =I16/1.2 -> 340 | K16: 45810 | L16: Payé | N16: TRANSPORT GRATUIT
A17: 16 | B17: VICTOIRE SCHMITT | C17: 132 | I17: =IF(L17="Cadeau",0,C17*$S$2+D17*$S$3+E17*$S$4+F17*$S$5+G17*$S$6) -> 2244 | J17: =I17/1.2 -> 1870 | K17: 45820 | L17: Payé | M17: Habillé | N17: TRANPORT GRATUIT VIREMENT
A18: 17 | B18: CAMILLE BELLON | C18: 18 | G18: 3 | I18: =IF(L18="Cadeau",0,C18*$S$2+D18*$S$3+E18*$S$4+F18*$S$5+G18*$S$6) -> 414 | J18: =I18/1.2 -> 345 | K18: 6696903 | L18: Payé | M18: A habiller | N18: MARIAGE CAP FERET
A19: 18 | B19: Léo Carouge | E19: 6 | I19: =IF(L19="Cadeau",0,C19*$S$2+D19*$S$3+E19*$S$4+F19*$S$5+G19*$S$6) -> 0 | J19: =I19/1.2 -> 0 | K19: 45819 | L19: Cadeau | N19: CADEAU
A20: 19 | B20: Nino Carouge | C20: 1 | F20: 1 | I20: =IF(L20="Cadeau",0,C20*$S$2+D20*$S$3+E20*$S$4+F20*$S$5+G20*$S$6) -> 0 | J20: =I20/1.2 -> 0 | K20: 45819 | L20: Cadeau
A21: 20 | B21: James Carouge | D21: 1 | E21: 4 | F21: 1 | I21: =IF(L21="Cadeau",0,C21*$S$2+D21*$S$3+E21*$S$4+F21*$S$5+G21*$S$6) -> 0 | J21: =I21/1.2 -> 0 | K21: 45810 | L21: Cadeau | N21: MEMERE SARDAIGNE
A22: 21 | B22: Philémon Parent | C22: 6 | I22: =IF(L22="Cadeau",0,C22*$S$2+D22*$S$3+E22*$S$4+F22*$S$5+G22*$S$6) -> 102 | J22: =I22/1.2 -> 85 | K22: 45822 | L22: Payé | M22: Livrer | N22: ESPECE
A23: 22 | B23: AIRBNB | C23: 1 | I23: =IF(L23="Cadeau",0,C23*$S$2+D23*$S$3+E23*$S$4+F23*$S$5+G23*$S$6) -> 0 | J23: =I23/1.2 -> 0 | K23: 45826 | L23: Cadeau
A24: 24 | B24: DANIEL ACRES | C24: 12 | I24: =IF(L24="Cadeau",0,C24*$S$2+D24*$S$3+E24*$S$4+F24*$S$5+G24*$S$6) -> 204 | J24: =I24/1.2 -> 170 | K24: 45831 | L24: Payé | N24: ESPECE
A25: 25 | B25: AIRBNB | C25: 1 | I25: =IF(L25="Cadeau",0,C25*$S$2+D25*$S$3+E25*$S$4+F25*$S$5+G25*$S$6) -> 0 | J25: =I25/1.2 -> 0 | K25: 45845 | L25: Cadeau
A26: 26 | B26: Nino Carouge | E26: 1 | I26: =IF(L26="Cadeau",0,C26*$S$2+D26*$S$3+E26*$S$4+F26*$S$5+G26*$S$6) -> 18.5 | J26: =I26/1.2 -> 15.416667 | K26: 45845 | L26: Payé | N26: ESPECE | O26: ESPECE
A27: 27 | B27: CAMILLE BELLON | C27: 72 | G27: 15 | I27: =IF(L27="Cadeau",0,C27*$S$2+D27*$S$3+E27*$S$4+F27*$S$5+G27*$S$6) -> 1764 | J27: =I27/1.2 -> 1470 | K27: 45845 | L27: Payé | N27: BORDEAUX TRANP GRATUIT
A28: 28 | B28: CHRISTINE ABRY | C28: 12 | I28: =IF(L28="Cadeau",0,C28*$S$2+D28*$S$3+E28*$S$4+F28*$S$5+G28*$S$6) -> 204 | J28: =I28/1.2 -> 170 | K28: 45874 | L28: Payé | N28: VIREMENT
A29: 29
A30: 30 | I30: =IF(L30="Cadeau",0,C30*$S$2+D30*$S$3+E30*$S$4+F30*$S$5+G30*$S$6) -> 0 | J30: =I30/1.2 -> 0
A31: 31 | B31: Philippe Gintrand | E31: 12 | I31: =IF(L31="Cadeau",0,C31*$S$2+D31*$S$3+E31*$S$4+F31*$S$5+G31*$S$6) -> 222 | J31: =I31/1.2 -> 185 | K31: 45879 | L31: Payé
A32: 32 | B32: Jac/dan Bouilot | D32: 12 | I32: =IF(L32="Cadeau",0,C32*$S$2+D32*$S$3+E32*$S$4+F32*$S$5+G32*$S$6) -> 228 | J32: =I32/1.2 -> 190 | K32: 45879 | L32: Payé | M32: Livrer | N32: VIREMENT
A33: 33 | B33: James Carouge | C33: 18 | D33: 6 | E33: 12 | F33: 6 | G33: 2 | I33: =IF(L33="Cadeau",0,C33*$S$2+D33*$S$3+E33*$S$4+F33*$S$5+G33*$S$6) -> 0 | J33: =I33/1.2 -> 0 | K33: 45879 | L33: Cadeau | N33: DEPOT SARDAIGNE | O33: DEPOT SARDAIGNE
A34: 34 | B34: SEVERINE PAQUIN | E34: 18 | I34: =IF(L34="Cadeau",0,C34*$S$2+D34*$S$3+E34*$S$4+F34*$S$5+G34*$S$6) -> 333 | J34: =I34/1.2 -> 277.5 | K34: 45901 | L34: Payé | M34: Livrer
A35: 35 | B35: James Carouge | E35: 3 | I35: =IF(L35="Cadeau",0,C35*$S$2+D35*$S$3+E35*$S$4+F35*$S$5+G35*$S$6) -> 0 | J35: =I35/1.2 -> 0 | K35: 45901 | L35: Cadeau | N35: SEVERINE 3 BLC DE BLCS
A36: 36 | B36: James Carouge | C36: 9 | E36: 3 | F36: 2 | I36: =IF(L36="Cadeau",0,C36*$S$2+D36*$S$3+E36*$S$4+F36*$S$5+G36*$S$6) -> 0 | J36: =I36/1.2 -> 0 | K36: 45901 | L36: Cadeau | N36: VENDANGEURS
A37: 37 | B37: PAOLA ZICCA | C37: 6 | D37: 6 | E37: 24 | I37: =IF(L37="Cadeau",0,C37*$S$2+D37*$S$3+E37*$S$4+F37*$S$5+G37*$S$6) -> 660 | J37: =I37/1.2 -> 550 | K37: 45884 | L37: Payé | N37: ESPECE/ITALIE
A38: 38 | B38: SERGIO ZICCA | C38: 6 | I38: =IF(L38="Cadeau",0,C38*$S$2+D38*$S$3+E38*$S$4+F38*$S$5+G38*$S$6) -> 102 | J38: =I38/1.2 -> 85 | K38: 45894 | L38: Payé | N38: ESPECE/ ITALIE
A39: 39 | B39: THOMAS BANGRATZ | C39: 84 | I39: =IF(L39="Cadeau",0,C39*$S$2+D39*$S$3+E39*$S$4+F39*$S$5+G39*$S$6) -> 1428 | J39: =I39/1.2 -> 1190 | K39: 45905 | L39: Payé | N39: VIREMENT
A40: 40 | B40: CHRISTINE ABRY | E40: 12 | I40: =IF(L40="Cadeau",0,C40*$S$2+D40*$S$3+E40*$S$4+F40*$S$5+G40*$S$6) -> 222 | J40: =I40/1.2 -> 185 | K40: 45907 | L40: Payé | N40: VIREMENT
A41: 41 | B41: QUARD AZDINE | E41: 12 | G41: 4 | I41: =IF(L41="Cadeau",0,C41*$S$2+D41*$S$3+E41*$S$4+F41*$S$5+G41*$S$6) -> 366 | J41: =I41/1.2 -> 305 | K41: 45911 | L41: Payé | M41: Livrer | N41: 50 LIVRAISON VIREMENT
A42: 42 | B42: Léo Carouge | C42: 6 | I42: =IF(L42="Cadeau",0,C42*$S$2+D42*$S$3+E42*$S$4+F42*$S$5+G42*$S$6) -> 0 | J42: =I42/1.2 -> 0 | K42: 45917 | L42: Cadeau
A43: 43 | B43: DANIEL ACRES | C43: 24 | I43: =IF(L43="Cadeau",0,C43*$S$2+D43*$S$3+E43*$S$4+F43*$S$5+G43*$S$6) -> 408 | J43: =I43/1.2 -> 340 | K43: 45923 | L43: Payé | M43: Habillé | N43: LIVRAISON 70 ITALIE
A44: 44 | B44: FLORENCE | E44: 6 | I44: =IF(L44="Cadeau",0,C44*$S$2+D44*$S$3+E44*$S$4+F44*$S$5+G44*$S$6) -> 111 | J44: =I44/1.2 -> 92.5 | K44: 45932 | L44: Payé | M44: Livrer | N44: VIREMENT
A45: 45 | I45: =IF(L45="Cadeau",0,C45*$S$2+D45*$S$3+E45*$S$4+F45*$S$5+G45*$S$6) -> 0 | J45: =I45/1.2 -> 0
A46: 46 | B46: Regis Paquin | E46: 24 | I46: =IF(L46="Cadeau",0,C46*$S$2+D46*$S$3+E46*$S$4+F46*$S$5+G46*$S$6) -> 444 | J46: =I46/1.2 -> 370 | K46: 45944 | L46: Payé | M46: Livrer | N46: 6 JOELLE REGLE 18 PAQUIN
A47: 47 | B47: Hugo Thomas | C47: 12 | E47: 42 | I47: =IF(L47="Cadeau",0,C47*$S$2+D47*$S$3+E47*$S$4+F47*$S$5+G47*$S$6) -> 981 | J47: =I47/1.2 -> 817.5 | K47: 45947 | L47: Payé | M47: Livrer | N47: transport 63,33
A48: 48 | B48: Jacques Girard | C48: 18 | D48: 12 | E48: 30 | I48: =IF(L48="Cadeau",0,C48*$S$2+D48*$S$3+E48*$S$4+F48*$S$5+G48*$S$6) -> 1089 | J48: =I48/1.2 -> 907.5 | K48: 45960 | L48: Payé | M48: Habillé | N48: 1 BLC// 1 2010
A49: 49 | B49: Gregory Cireddu | C49: 48 | E49: 18 | I49: =IF(L49="Cadeau",0,C49*$S$2+D49*$S$3+E49*$S$4+F49*$S$5+G49*$S$6) -> 1149 | J49: =I49/1.2 -> 957.5 | K49: 45954 | L49: En attente de paiement | M49: Livrer
A50: 50 | B50: FLORENCE | C50: 6 | D50: 6 | I50: =IF(L50="Cadeau",0,C50*$S$2+D50*$S$3+E50*$S$4+F50*$S$5+G50*$S$6) -> 216 | J50: =I50/1.2 -> 180 | K50: 45963 | L50: Payé | M50: Livrer | N50: VIREMENT
A51: 51 | B51: DAMIEN | C51: 18 | D51: 1 | I51: =IF(L51="Cadeau",0,C51*$S$2+D51*$S$3+E51*$S$4+F51*$S$5+G51*$S$6) -> 325 | J51: =I51/1.2 -> 270.83333 | K51: 45970 | L51: Payé | N51: ESPECES
A52: 52 | I52: =IF(L52="Cadeau",0,C52*$S$2+D52*$S$3+E52*$S$4+F52*$S$5+G52*$S$6) -> 0 | J52: =I52/1.2 -> 0
A53: 53 | B53: DOCTEUR LEVERRIER | E53: 12 | I53: =IF(L53="Cadeau",0,C53*$S$2+D53*$S$3+E53*$S$4+F53*$S$5+G53*$S$6) -> 222 | J53: =I53/1.2 -> 185 | L53: Payé | N53: CHEQUE
A54: 54 | B54: BRASSEUR | C54: 12 | I54: =IF(L54="Cadeau",0,C54*$S$2+D54*$S$3+E54*$S$4+F54*$S$5+G54*$S$6) -> 204 | J54: =I54/1.2 -> 170 | K54: 45970 | L54: Payé | N54: VIREMENT
A55: 55 | B55: FOURCART CAROLINE | E55: 12 | I55: =IF(L55="Cadeau",0,C55*$S$2+D55*$S$3+E55*$S$4+F55*$S$5+G55*$S$6) -> 222 | J55: =I55/1.2 -> 185 | K55: 45970 | L55: Payé | N55: CHEQUE
A56: 56 | B56: SARL CHAUFFE BOIS | E56: 12 | I56: =IF(L56="Cadeau",0,C56*$S$2+D56*$S$3+E56*$S$4+F56*$S$5+G56*$S$6) -> 222 | J56: =IF(M56="Cadeau",0,D56*$S$2+E56*$S$3+F56*$S$4+G56*$S$5) -> 228 | K56: 45970 | L56: Payé | N56: VIREMENT
A57: 57 | B57: James Carouge | F57: 1 | I57: =IF(L57="Cadeau",0,C57*$S$2+D57*$S$3+E57*$S$4+F57*$S$5+G57*$S$6) -> 0 | J57: =IF(M57="Cadeau",0,D57*$S$2+E57*$S$3+F57*$S$4+G57*$S$5) -> 18.5 | K57: 45978 | L57: Cadeau
A58: 58 | B58: DANIEL ACRES | C58: 36 | I58: =IF(L58="Cadeau",0,C58*$S$2+D58*$S$3+E58*$S$4+F58*$S$5+G58*$S$6) -> 612 | J58: =IF(M58="Cadeau",0,D58*$S$2+E58*$S$3+F58*$S$4+G58*$S$5) -> 0 | K58: 45985 | L58: Payé | N58: 105 LIVRAISON
A59: 59 | B59: BASTIEN LASSER | C59: 12 | E59: 24 | F59: 6 | I59: =IF(L59="Cadeau",0,C59*$S$2+D59*$S$3+E59*$S$4+F59*$S$5+G59*$S$6) -> 810 | J59: =IF(M59="Cadeau",0,D59*$S$2+E59*$S$3+F59*$S$4+G59*$S$5) -> 567 | K59: 45994 | L59: Payé | N59: LIVRAISON 2 VIREMENTS
A60: 60 | B60: JEAN- MARC FISCHER | E60: 12 | I60: =IF(L60="Cadeau",0,C60*$S$2+D60*$S$3+E60*$S$4+F60*$S$5+G60*$S$6) -> 222 | J60: =IF(M60="Cadeau",0,D60*$S$2+E60*$S$3+F60*$S$4+G60*$S$5) -> 228 | K60: 46009 | L60: Payé | N60: LIVRAISON
A61: 61 | B61: CAROLINE ET JEAN MICHEL BLANG | E61: 6 | F61: 12 | I61: =IF(L61="Cadeau",0,C61*$S$2+D61*$S$3+E61*$S$4+F61*$S$5+G61*$S$6) -> 435 | J61: =IF(M61="Cadeau",0,D61*$S$2+E61*$S$3+F61*$S$4+G61*$S$5) -> 336 | K61: 46009 | L61: Payé | N61: LIVRAISON GRATUITE
A62: 62 | B62: James Carouge | C62: 3 | D62: 6 | E62: 19 | G62: 1 | I62: =IF(L62="Cadeau",0,C62*$S$2+D62*$S$3+E62*$S$4+F62*$S$5+G62*$S$6) -> 0 | K62: 46018 | L62: Cadeau | N62: FIN D ANNEE ET CONSO
A63: 63 | B63: Léo Carouge | C63: 6 | E63: 6 | I63: =IF(L63="Cadeau",0,C63*$S$2+D63*$S$3+E63*$S$4+F63*$S$5+G63*$S$6) -> 0 | J63: =IF(M63="Cadeau",0,D63*$S$2+E63*$S$3+F63*$S$4+G63*$S$5) -> 114 | K63: 46016 | L63: Cadeau | N63: NOEL ANNIVERSAIRE
A64: 64 | B64: SARAH BLIN | C64: 6 | I64: =IF(L64="Cadeau",0,C64*$S$2+D64*$S$3+E64*$S$4+F64*$S$5+G64*$S$6) -> 102 | J64: =IF(M64="Cadeau",0,D64*$S$2+E64*$S$3+F64*$S$4+G64*$S$5) -> 0 | K64: 45992 | L64: Payé | N64: VIREMENT
A65: 65 | B65: AIRBNB | C65: 2 | I65: =IF(L65="Cadeau",0,C65*$S$2+D65*$S$3+E65*$S$4+F65*$S$5+G65*$S$6) -> 0 | K65: 46022 | L65: Cadeau
A66: 66 | B66: Paul Briest | C66: 24 | E66: 18 | I66: =IF(L66="Cadeau",0,C66*$S$2+D66*$S$3+E66*$S$4+F66*$S$5+G66*$S$6) -> 741 | K66: 46065
A67: 67 | I67: =IF(L67="Cadeau",0,C67*$S$2+D67*$S$3+E67*$S$4+F67*$S$5+G67*$S$6) -> 0
A68: 68 | I68: =IF(L68="Cadeau",0,C68*$S$2+D68*$S$3+E68*$S$4+F68*$S$5+G68*$S$6) -> 0
A69: 69 | I69: =IF(L69="Cadeau",0,C69*$S$2+D69*$S$3+E69*$S$4+F69*$S$5+G69*$S$6) -> 0
A70: 70 | I70: =IF(L70="Cadeau",0,C70*$S$2+D70*$S$3+E70*$S$4+F70*$S$5+G70*$S$6) -> 0
A71: 71 | I71: =IF(L71="Cadeau",0,C71*$S$2+D71*$S$3+E71*$S$4+F71*$S$5+G71*$S$6) -> 0
A72: 72 | I72: =IF(L72="Cadeau",0,C72*$S$2+D72*$S$3+E72*$S$4+F72*$S$5+G72*$S$6) -> 0
A73: 73 | I73: =IF(L73="Cadeau",0,C73*$S$2+D73*$S$3+E73*$S$4+F73*$S$5+G73*$S$6) -> 0
A74: 74 | I74: =IF(L74="Cadeau",0,C74*$S$2+D74*$S$3+E74*$S$4+F74*$S$5+G74*$S$6) -> 0
A75: 75 | I75: =IF(L75="Cadeau",0,C75*$S$2+D75*$S$3+E75*$S$4+F75*$S$5+G75*$S$6) -> 0
A76: 76 | I76: =IF(L76="Cadeau",0,C76*$S$2+D76*$S$3+E76*$S$4+F76*$S$5+G76*$S$6) -> 0
A77: 77 | I77: =IF(L77="Cadeau",0,C77*$S$2+D77*$S$3+E77*$S$4+F77*$S$5+G77*$S$6) -> 0
A78: 78 | I78: =IF(L78="Cadeau",0,C78*$S$2+D78*$S$3+E78*$S$4+F78*$S$5+G78*$S$6) -> 0
... A106: 106 | I106: =IF(L106="Cadeau",0,C106*$S$2+D106*$S$3+E106*$S$4+F106*$S$5+G106*$S$6) -> 0
I107: =IF(L107="Cadeau",0,C107*$S$2+D107*$S$3+E107*$S$4+F107*$S$5+G107*$S$6) -> 0
I108: =IF(L108="Cadeau",0,C108*$S$2+D108*$S$3+E108*$S$4+F108*$S$5+G108*$S$6) -> 0
I109: =IF(L109="Cadeau",0,C109*$S$2+D109*$S$3+E109*$S$4+F109*$S$5+G109*$S$6) -> 0
I110: =IF(L110="Cadeau",0,C110*$S$2+D110*$S$3+E110*$S$4+F110*$S$5+G110*$S$6) -> 0
I111: =IF(L111="Cadeau",0,C111*$S$2+D111*$S$3+E111*$S$4+F111*$S$5+G111*$S$6) -> 0
I112: =IF(L112="Cadeau",0,C112*$S$2+D112*$S$3+E112*$S$4+F112*$S$5+G112*$S$6) -> 0
I113: =IF(L113="Cadeau",0,C113*$S$2+D113*$S$3+E113*$S$4+F113*$S$5+G113*$S$6) -> 0
I114: =IF(L114="Cadeau",0,C114*$S$2+D114*$S$3+E114*$S$4+F114*$S$5+G114*$S$6) -> 0
I115: =IF(L115="Cadeau",0,C115*$S$2+D115*$S$3+E115*$S$4+F115*$S$5+G115*$S$6) -> 0
I116: =IF(L116="Cadeau",0,C116*$S$2+D116*$S$3+E116*$S$4+F116*$S$5+G116*$S$6) -> 0
I117: =IF(L117="Cadeau",0,C117*$S$2+D117*$S$3+E117*$S$4+F117*$S$5+G117*$S$6) -> 0
I118: =IF(L118="Cadeau",0,C118*$S$2+D118*$S$3+E118*$S$4+F118*$S$5+G118*$S$6) -> 0
... I144: =IF(L144="Cadeau",0,C144*$S$2+D144*$S$3+E144*$S$4+F144*$S$5+G144*$S$6) -> 0
A419: 23

Sheet Facturation 2025
E5: CHAMPAGNE CAROUGE CIREDDU
C7: S
G8: Nom | I8: =VLOOKUP(C16,'Suivi Facturation 2025'!$A$1:$K$10002,2,FALSE) -> Paul Briest
G9: Adresse | I9: =VLOOKUP(I8,'Suivi Client'!C2:H2960,3,FALSE) -> 2 RUE ST REMY
I10: =VLOOKUP(I8,'Suivi Client'!C2:H2960,4,FALSE) -> 51150 | J10: =VLOOKUP(I8,'Suivi Client'!C2:H2960,5,FALSE) -> Athis
G12: Adresse e-mail | I12: =IF(VLOOKUP(I8,'Suivi Client'!$C$2:$H$2000,2,FALSE)=0,"",VLOOKUP(I8,'Suivi Client'!$C$2:$H$2000,2,FALSE)) -> paul.briestcastaldo@gmail.com
M14: 23
C16: 66
A17: Date de facturation | C17: 46065
A21: Contenance | B21: Designation | H21: Qté | I21: Prix unitaire TTC | K21: Montant TTC
A23: =IF(VLOOKUP($C$16,'Suivi Facturation 2025'!$A$2:$M$1096,3,FALSE)>0,"0,75","") -> 0,75 | B23: =IF(VLOOKUP($C$16,'Suivi Facturation 2025'!$A$2:$M$978,3,FALSE)>0,"Bouteille CHAMPAGNE SELECTION","") -> Bouteille CHAMPAGNE SELECTION | H23: =IF(VLOOKUP($C$16,'Suivi Facturation 2025'!$A$2:$M$1096,3,FALSE)>0,VLOOKUP($C$16,'Suivi Facturation 2025'!$A$2:$M$1096,3,FALSE),"") -> 24 | I23: =IF(VLOOKUP($C$16,'Suivi Facturation 2025'!$A$2:$M$1096,3,FALSE)>0,'Suivi Facturation 2025'!S2,"") -> 17 | K23: =IF(VLOOKUP($C$16,'Suivi Facturation 2025'!$A$2:$M$1096,3,FALSE)>0,I23*H23,"") -> 408
A24: =IF(VLOOKUP($C$16,'Suivi Facturation 2025'!$A$2:$M$1096,4,FALSE)>0,"0,75","") | B24: =IF(VLOOKUP($C$16,'Suivi Facturation 2025'!$A$2:$M$978,4,FALSE)>0,"Bouteille CHAMPAGNE ROSE","") | H24: =IF(VLOOKUP($C$16,'Suivi Facturation 2025'!$A$2:$M$1096,4,FALSE)>0,VLOOKUP($C$16,'Suivi Facturation 2025'!$A$2:$M$1096,4,FALSE),"") | I24: =IF(VLOOKUP($C$16,'Suivi Facturation 2025'!$A$2:$M$1096,4,FALSE)>0,'Suivi Facturation 2025'!S3,"") | K24: =IF(VLOOKUP($C$16,'Suivi Facturation 2025'!$A$2:$M$1096,4,FALSE)>0,I24*H24,"")
A25: =IF(VLOOKUP($C$16,'Suivi Facturation 2025'!$A$2:$M$1096,5,FALSE)>0,"0,75","") -> 0,75 | B25: =IF(VLOOKUP($C$16,'Suivi Facturation 2025'!$A$2:$M$978,5,FALSE)>0,"Bouteille CHAMPAGNE BLANC DE BLANC","") -> Bouteille CHAMPAGNE BLANC DE BLANC | H25: =IF(VLOOKUP($C$16,'Suivi Facturation 2025'!$A$2:$M$1996,5,FALSE)>0,VLOOKUP($C$16,'Suivi Facturation 2025'!$A$2:$M$1996,5,FALSE),"") -> 18 | I25: =IF(VLOOKUP($C$16,'Suivi Facturation 2025'!$A$2:$M$1096,5,FALSE)>0,'Suivi Facturation 2025'!S4,"") -> 18.5 | K25: =IF(VLOOKUP($C$16,'Suivi Facturation 2025'!$A$2:$M$1096,5,FALSE)>0,I25*H25,"") -> 333
A26: =IF(VLOOKUP($C$16,'Suivi Facturation 2025'!$A$2:$M$1096,6,FALSE)>0,"0,75","") | B26: =IF(VLOOKUP($C$16,'Suivi Facturation 2025'!$A$2:$M$1096,6,FALSE)>0,"Bouteille CHAMPAGNE PRESTIGE","") | H26: =IF(VLOOKUP($C$16,'Suivi Facturation 2025'!$A$2:$M$1096,6,FALSE)>0,VLOOKUP($C$16,'Suivi Facturation 2025'!$A$2:$M$1096,6,FALSE),"") | I26: =IF(VLOOKUP($C$16,'Suivi Facturation 2025'!$A$2:$M$1096,6,FALSE)>0,'Suivi Facturation 2025'!S5,"") | K26: =IF(VLOOKUP($C$16,'Suivi Facturation 2025'!$A$2:$M$1096,6,FALSE)>0,I26*H26,"")
A27: =IF(VLOOKUP($C$16,'Suivi Facturation 2025'!$A$2:$M$1096,7,FALSE)>0,"1,5","") | B27: =IF(VLOOKUP($C$16,'Suivi Facturation 2025'!$A$2:$M$1096,7,FALSE)>0,"MAGNUM SELECTION","") | H27: =IF(VLOOKUP($C$16,'Suivi Facturation 2025'!$A$2:$M$1096,7,FALSE)>0,VLOOKUP($C$16,'Suivi Facturation 2025'!$A$2:$M$1096,7,FALSE),"") | I27: =IF(VLOOKUP($C$16,'Suivi Facturation 2025'!$A$2:$M$1096,7,FALSE)>0,'Suivi Facturation 2025'!S6,"") | K27: =IF(VLOOKUP($C$16,'Suivi Facturation 2025'!$A$2:$M$1096,7,FALSE)>0,I27*H27,"")
B28: =IF(VLOOKUP($C$16,'Suivi Facturation 2025'!$A$2:$P$1978,16,FALSE)>0,"PRIX LIVRAISON","") | K28: =IF(VLOOKUP($C$16,'Suivi Facturation 2025'!$A$2:$P$1978,16,FALSE)>0,VLOOKUP($C$16,'Suivi Facturation 2025'!$A$2:$P$1978,16,FALSE),"")
K37: Total HT | L37: =SUM(K23:L30)-L38 -> 617.5
K38: TVA (20%) | L38: =IFERROR(SUM(K23:L29)-SUM(K23:L29)/1.2,"") -> 123.5
K40: Total TTC | L40: =SUM(K23:L30) -> 741
A42: Toute somme impayée à son échéance produira, de plein droit et sans mise en demeure, un intérêt égal à 1,5 fois le taux d'intérêt légal par mois de retard. Nos conditions de vente ne prévoient pas d'escompte pour paiement anticipé. Coordonnées bancaires Titulaire du compte : JAMES CAROUGE IBAN FR76 1020 6000 4848 3510 3712 067 BIC AGRIFRPP802
A54: CHAMPAGNE CAROUGE CIREDDU 6 rue de l'eglise 51190 FLAVIGNY Tel : 06 77 95 90 62 SIRET 843 516 642 00017 N° TVA intracommunautaire FR67 843 516 642

Sheet Facturation 2025 HT
E5: CHAMPAGNE CAROUGE CIREDDU
G8: Nom | I8: =VLOOKUP(C16,'Suivi Facturation 2025'!$A$1:$K$10002,2,FALSE) -> DANIEL ACRES
G9: Adresse | I9: =VLOOKUP(I8,'Suivi Client'!C2:H2960,3,FALSE) -> 16 VIA POGGIARDELLI
I10: =VLOOKUP(I8,'Suivi Client'!C2:H2960,4,FALSE) -> 53045 | J10: =VLOOKUP(I8,'Suivi Client'!C2:H2960,5,FALSE) -> MONTEOULCIANO
G12: Adresse e-mail | I12: =IF(VLOOKUP(I8,'Suivi Client'!$C$2:$H$2000,2,FALSE)=0,"",VLOOKUP(I8,'Suivi Client'!$C$2:$H$2000,2,FALSE)) -> dan.acres@gmail.com
A16: numéro de facturation | C16: 58
A17: Date de facturation | C17: 45985
A21: Contenance | B21: Designation | H21: Qté | I21: Prix unitaire HT | K21: Montant HT
A23: =IF(VLOOKUP($C$16,'Suivi Facturation 2025'!$A$2:$M$1096,3,FALSE)>0,"0,75","") -> 0,75 | B23: =IF(VLOOKUP($C$16,'Suivi Facturation 2025'!$A$2:$M$978,3,FALSE)>0,"Bouteille CHAMPAGNE SELECTION","") -> Bouteille CHAMPAGNE SELECTION | H23: =IF(VLOOKUP($C$16,'Suivi Facturation 2025'!$A$2:$M$1096,3,FALSE)>0,VLOOKUP($C$16,'Suivi Facturation 2025'!$A$2:$M$1096,3,FALSE),"") -> 36 | I23: =IF(VLOOKUP($C$16,'Suivi Facturation 2025'!$A$2:$M$1096,3,FALSE)>0,'Suivi Facturation 2025'!S2,"") -> 17 | K23: =IF(VLOOKUP($C$16,'Suivi Facturation 2025'!$A$2:$M$1096,3,FALSE)>0,I23*H23,"") -> 612
A24: =IF(VLOOKUP($C$16,'Suivi Facturation 2025'!$A$2:$M$1096,4,FALSE)>0,"0,75","") | B24: =IF(VLOOKUP($C$16,'Suivi Facturation 2025'!$A$2:$M$978,4,FALSE)>0,"Bouteille CHAMPAGNE ROSE","") | H24: =IF(VLOOKUP($C$16,'Suivi Facturation 2025'!$A$2:$M$1096,4,FALSE)>0,VLOOKUP($C$16,'Suivi Facturation 2025'!$A$2:$M$1096,4,FALSE),"") | I24: =IF(VLOOKUP($C$16,'Suivi Facturation 2025'!$A$2:$M$1096,4,FALSE)>0,'Suivi Facturation 2025'!S3,"") | K24: =IF(VLOOKUP($C$16,'Suivi Facturation 2025'!$A$2:$M$1096,4,FALSE)>0,I24*H24,"")
A25: =IF(VLOOKUP($C$16,'Suivi Facturation 2025'!$A$2:$M$1096,5,FALSE)>0,"0,75","") | B25: =IF(VLOOKUP($C$16,'Suivi Facturation 2025'!$A$2:$M$978,5,FALSE)>0,"Bouteille CHAMPAGNE BLANC DE BLANC","") | H25: =IF(VLOOKUP($C$16,'Suivi Facturation 2025'!$A$2:$M$1996,5,FALSE)>0,VLOOKUP($C$16,'Suivi Facturation 2025'!$A$2:$M$1996,5,FALSE),"") | I25: =IF(VLOOKUP($C$16,'Suivi Facturation 2025'!$A$2:$M$1096,5,FALSE)>0,'Suivi Facturation 2025'!S4,"") | K25: =IF(VLOOKUP($C$16,'Suivi Facturation 2025'!$A$2:$M$1096,5,FALSE)>0,I25*H25,"")
A26: =IF(VLOOKUP($C$16,'Suivi Facturation 2025'!$A$2:$M$1096,6,FALSE)>0,"0,75","") | B26: =IF(VLOOKUP($C$16,'Suivi Facturation 2025'!$A$2:$M$1096,6,FALSE)>0,"Bouteille CHAMPAGNE PRESTIGE","") | H26: =IF(VLOOKUP($C$16,'Suivi Facturation 2025'!$A$2:$M$1096,6,FALSE)>0,VLOOKUP($C$16,'Suivi Facturation 2025'!$A$2:$M$1096,6,FALSE),"") | I26: =IF(VLOOKUP($C$16,'Suivi Facturation 2025'!$A$2:$M$1096,6,FALSE)>0,'Suivi Facturation 2025'!S5,"") | K26: =IF(VLOOKUP($C$16,'Suivi Facturation 2025'!$A$2:$M$1096,6,FALSE)>0,I26*H26,"")
A27: =IF(VLOOKUP($C$16,'Suivi Facturation 2025'!$A$2:$M$1096,7,FALSE)>0,"1,5","") | B27: =IF(VLOOKUP($C$16,'Suivi Facturation 2025'!$A$2:$M$1096,7,FALSE)>0,"MAGNUM SELECTION","") | I27: =IF(VLOOKUP($C$16,'Suivi Facturation 2025'!$A$2:$M$1096,7,FALSE)>0,'Suivi Facturation 2025'!S6,"") | K27: =IF(VLOOKUP($C$16,'Suivi Facturation 2025'!$A$2:$M$1096,7,FALSE)>0,I27*H27,"")
K40: Total HT | L40: =SUM(K23:L30) -> 612
A42: Toute somme impayée à son échéance produira, de plein droit et sans mise en demeure, un intérêt égal à 1,5 fois le taux d'intérêt légal par mois de retard. Nos conditions de vente ne prévoient pas d'escompte pour paiement anticipé. Coordonnées bancaires Titulaire du compte : JAMES CAROUGE IBAN FR76 1020 6000 4848 3510 3712 067 BIC AGRIFRPP802
A54: CHAMPAGNE CAROUGE CIREDDU 6 rue de l'eglise 51190 FLAVIGNY Tel : 06 77 95 90 62 SIRET 843 516 642 00017 N° TVA intracommunautaire FR67 843 516 642

Sheet Suivi Facturation 2024
A1: 4 | B1: Nom Client | C1: NB Selection | D1: NB Rosé | E1: Nb blanc de blan | F1: Nb Prestige | G1: Magnum Selection | I1: Montant TTC bouteilles | J1: Montant HT | K1: Date de facturation | L1: Etat paiement | M1: Etat Commande | N1: paiement | O1: commentaire | P1: Prix Transport TTC | R1: Statistiques | S1: Prix unitaire TTC | T1: =S2/1.2 -> 14.166667
A2: 1 | B2: JACKIE Guillaume | C2: 6 | I2: =IF(L2="Cadeau",0,C2*$S$2+D2*$S$3+E2*$S$4+F2*$S$5) -> 102 | J2: =I2/1.2 -> 85 | K2: 45326 | L2: REGLE | M2: Payé | R2: Sélection | S2: 17
A3: 2 | B3: SEVERINE PAQUIN | C3: 12 | E3: 12 | I3: =IF(L3="Cadeau",0,C3*$S$2+D3*$S$3+E3*$S$4+F3*$S$5) -> 426 | J3: =I3/1.2 -> 355 | K3: 45347 | L3: Payé | M3: Livrer | O3: CADEAU 1 ROSE | R3: Rosé | S3: 19
A4: 3 | B4: James Carouge | C4: 5 | E4: 3 | F4: 4 | I4: =IF(L4="Cadeau",0,C4*$S$2+D4*$S$3+E4*$S$4+F4*$S$5) -> 0 | J4: =I4/1.2 -> 0 | K4: 45349 | L4: Cadeau | O4: CONSO MAISON | R4: Blanc de blanc | S4: 18.5
A5: 4 | B5: CHRISTINE ABRY | C5: 24 | I5: =IF(L5="Cadeau",0,C5*$S$2+D5*$S$3+E5*$S$4+F5*$S$5) -> 408 | J5: =I5/1.2 -> 340 | K5: 45371 | L5: Payé | M5: Livrer | N5: LIVRAISON EN SUP | R5: Prestige | S5: 27
A6: 5 | B6: SARAH BLIN | E6: 48 | I6: =IF(L6="Cadeau",0,C6*$S$2+D6*$S$3+E6*$S$4+F6*$S$5) -> 888 | J6: =I6/1.2 -> 740 | K6: 45413 | L6: Payé | N6: GILLES PITOIS | P6: 120 | R6: Magnum Brut Selection | S6: 38
A7: 6 | B7: VICTOIRE SCHMITT | C7: 120 | I7: =IF(L7="Cadeau",0,C7*$S$2+D7*$S$3+E7*$S$4+F7*$S$5) -> 2040 | J7: =I7/1.2 -> 1700 | K7: 45425 | L7: Payé | M7: Livrer | N7: livraison 120 | R7: Nb bouteilles vendues | S7: =SUM(C2:D1201) -> 635
A8: 7 | I8: =IF(L8="Cadeau",0,C8*$S$2+D8*$S$3+E8*$S$4+F8*$S$5) -> 0 | J8: =I8/1.2 -> 0 | N8: CONSO MAISON
A9: 8 | B9: Philémon Parent | C9: 6 | I9: =IF(L9="Cadeau",0,C9*$S$2+D9*$S$3+E9*$S$4+F9*$S$5) -> 102 | J9: =I9/1.2 -> 85 | K9: 45435 | L9: Payé | M9: Livrer | N9: CHEQUE | R9: Chiffre d'affaire | S9: =SUM(I2:I1216) -> 17291
A10: 9 | B10: CHRITOPHE TRILLOT | C10: 96 | I10: =IF(L10="Cadeau",0,C10*$S$2+D10*$S$3+E10*$S$4+F10*$S$5) -> 1632 | J10: =I10/1.2 -> 1360 | K10: 45458 | L10: Payé | M10: Livrer | N10: MARIAGE | O10: cheque
A11: 10 | B11: Regis Paquin | E11: 18 | I11: =IF(L11="Cadeau",0,C11*$S$2+D11*$S$3+E11*$S$4+F11*$S$5) -> 333 | J11: =I11/1.2 -> 277.5 | K11: 45437 | L11: Payé | M11: Livrer | N11: VIREMENT
A12: 11 | B12: James Carouge | C12: 7 | E12: 3 | I12: =IF(L12="Cadeau",0,C12*$S$2+D12*$S$3+E12*$S$4+F12*$S$5) -> 0 | J12: =I12/1.2 -> 0 | K12: 45428 | L12: Cadeau | M12: Livrer | N12: CONSO CADEAU
A13: 12 | B13: James Carouge | L13: Cadeau | M13: Livrer | N13: CONSO
A14: 13 | B14: Gintrand Simon | E14: 18 | I14: =IF(L14="Cadeau",0,C14*$S$2+D14*$S$3+E14*$S$4+F14*$S$5) -> 333 | J14: =I14/1.2 -> 277.5 | K14: 45475 | L14: Payé | M14: Livrer | N14: VIREMENT
A15: 14 | B15: ISABELLE PASSA | C15: 18 | I15: =IF(L15="Cadeau",0,C15*$S$2+D15*$S$3+E15*$S$4+F15*$S$5) -> 306 | J15: =I15/1.2 -> 255 | K15: 45460 | L15: Payé | M15: Livrer | N15: LIVRAISON | O15: LIVRAISON 59,20 EN CHEQUE
A16: 15 | B16: Léo Carouge | E16: 6 | I16: =IF(L16="Cadeau",0,C16*$S$2+D16*$S$3+E16*$S$4+F16*$S$5) -> 0 | J16: =I16/1.2 -> 0 | K16: 45427 | L16: Cadeau | M16: Livrer
A17: 16 | B17: SCM MEDICALE INSTITUT DU SPO OLIVIER SELVA | E17: 36 | I17: =IF(L17="Cadeau",0,C17*$S$2+D17*$S$3+E17*$S$4+F17*$S$5) -> 666 | J17: =I17/1.2 -> 555 | K17: 45475 | L17: Payé | M17: Livrer | N17: VIREMENT
A18: 17 | B18: AGENCE LAGUILLON | E18: 60 | I18: =IF(L18="Cadeau",0,C18*$S$2+D18*$S$3+E18*$S$4+F18*$S$5) -> 1110 | J18: =I18/1.2 -> 925 | K18: 45490 | L18: Payé | M18: Livrer | N18: VIREMENT | O18: TRANSPORT GRATUIT
A19: 18 | B19: NICOLA CIREDDU | C19: 48 | F19: 6 | I19: =IF(L19="Cadeau",0,C19*$S$2+D19*$S$3+E19*$S$4+F19*$S$5) -> 978 | J19: =I19/1.2 -> 815 | K19: 45503 | L19: Payé | M19: Livrer | N19: ESPECE | O19: SARDAIGNE
A20: 19 | B20: Philippe Gintrand | C20: 30 | E20: 12 | I20: =IF(L20="Cadeau",0,C20*$S$2+D20*$S$3+E20*$S$4+F20*$S$5) -> 732 | J20: =I20/1.2 -> 610 | K20: 45495 | L20: Payé | M20: Livrer | N20: VIREMENT | O20: GIRARD 528 EUROS 12 BLC 18 SELEC
A21: 20 | B21: MARC LEFORT | C21: 6 | I21: =IF(L21="Cadeau",0,C21*$S$2+D21*$S$3+E21*$S$4+F21*$S$5) -> 102 | J21: =I21/1.2 -> 85 | K21: 45495 | L21: Payé | M21: Livrer | N21: VIREMENT | O21: ST VALLIER
A22: 21 | B22: PAOLA ZICCA | C22: 6 | E22: 12 | I22: =IF(L22="Cadeau",0,C22*$S$2+D22*$S$3+E22*$S$4+F22*$S$5) -> 324 | J22: =I22/1.2 -> 270 | K22: 45503 | L22: Payé | M22: Livrer | N22: ESPECE | O22: SARDAIGNE
A23: 22 | I23: =IF(L23="Cadeau",0,C23*$S$2+D23*$S$3+E23*$S$4+F23*$S$5) -> 0 | J23: =I23/1.2 -> 0 | K23: 45503 | L23: Payé | M23: Livrer | N23: ESPECE | O23: SARDAIGNE
A24: 23 | B24: James Carouge | D24: 6 | E24: 8 | F24: 6 | I24: =IF(L24="Cadeau",0,C24*$S$2+D24*$S$3+E24*$S$4+F24*$S$5) -> 0 | J24: =I24/1.2 -> 0 | K24: 45503 | L24: Cadeau | N24: CONSO SARDAIGNE | O24: SARDAIGNE
A25: 24 | B25: AIRBNB | I25: =IF(L25="Cadeau",0,C25*$S$2+D25*$S$3+E25*$S$4+F25*$S$5) -> 0 | J25: =I25/1.2 -> 0
A26: 25 | B26: cireddu camille | C26: 5 | I26: =IF(L26="Cadeau",0,C26*$S$2+D26*$S$3+E26*$S$4+F26*$S$5) -> 85 | J26: =I26/1.2 -> 70.833333 | K26: 45557 | L26: Payé | M26: Livrer | N26: FRANCESCA 3 BTL 51 VIREMT
A27: 26 | B27: Cadeau Vendages | C27: 4 | I27: =IF(L27="Cadeau",0,C27*$S$2+D27*$S$3+E27*$S$4+F27*$S$5) -> 0 | J27: =I27/1.2 -> 0 | K27: 45557 | L27: Cadeau | M27: Livrer | N27: VENDANGEURS
A28: 27 | B28: Sarha | C28: 2 | D28: 1 | I28: =IF(L28="Cadeau",0,C28*$S$2+D28*$S$3+E28*$S$4+F28*$S$5) -> 53 | J28: =I28/1.2 -> 44.166667 | K28: 45557 | L28: Payé | M28: Livrer | N28: VIREMENT
A29: 28 | B29: CHRISTINE ABRY | C29: 12 | I29: =IF(L29="Cadeau",0,C29*$S$2+D29*$S$3+E29*$S$4+F29*$S$5) -> 204 | J29: =I29/1.2 -> 170 | K29: 45582 | L29: Payé | M29: Livrer | N29: VIREMENT | O29: LIVRAISON
A30: 29 | B30: cireddu camille | C30: 6 | I30: =IF(L30="Cadeau",0,C30*$S$2+D30*$S$3+E30*$S$4+F30*$S$5) -> 102 | J30: =I30/1.2 -> 85 | K30: 45584 | L30: Payé | M30: Livrer | N30: 6 +2BTL FACT 25 VIREMT | O30: ENJY
A31: 30 | B31: James Carouge | C31: 1 | I31: =IF(L31="Cadeau",0,C31*$S$2+D31*$S$3+E31*$S$4+F31*$S$5) -> 0 | J31: =I31/1.2 -> 0 | K31: 45578 | L31: Cadeau | N31: CONSO
A32: 31 | B32: Stanislas BOUTMY | E32: 12 | I32: =IF(L32="Cadeau",0,C32*$S$2+D32*$S$3+E32*$S$4+F32*$S$5) -> 222 | J32: =I32/1.2 -> 185 | K32: 45592 | L32: A facturer | M32: Livrer
A33: 32 | B33: Stanislas BOUTMY | D33: 6 | E33: 6 | I33: =IF(L33="Cadeau",0,C33*$S$2+D33*$S$3+E33*$S$4+F33*$S$5) -> 225 | J33: =I33/1.2 -> 187.5 | K33: 45592 | L33: Payé | M33: Livrer | N33: VIREMENT
A34: 33 | B34: Bazin Etienne | E34: 6 | I34: =IF(L34="Cadeau",0,C34*$S$2+D34*$S$3+E34*$S$4+F34*$S$5) -> 111 | J34: =I34/1.2 -> 92.5 | K34: 45592 | L34: Payé | M34: Livrer | N34: VIREMENT
A35: 34 | B35: Léo Carouge | C35: 6 | E35: 6 | I35: =IF(L35="Cadeau",0,C35*$S$2+D35*$S$3+E35*$S$4+F35*$S$5) -> 0 | J35: =I35/1.2 -> 0 | K35: 45592 | L35: Cadeau | O35: CADEAU LEO
A36: 35 | B36: ZACHARIE Fassaert | C36: 10 | I36: =IF(L36="Cadeau",0,C36*$S$2+D36*$S$3+E36*$S$4+F36*$S$5) -> 170 | J36: =I36/1.2 -> 141.66667 | K36: 45601 | L36: Payé | N36: 2 CADEAU VIREMENT | O36: ANNIV ZAK
A37: 36 | B37: Nino Carouge | D37: 1 | F37: 2 | I37: =IF(L37="Cadeau",0,C37*$S$2+D37*$S$3+E37*$S$4+F37*$S$5) -> 0 | J37: =I37/1.2 -> 0 | K37: 45601 | L37: Cadeau | N37: DEGUSTATION | O37: ST JEAN DE LUZ
A38: 37 | B38: DANIEL ACRES | C38: 24 | I38: =IF(L38="Cadeau",0,C38*$S$2+D38*$S$3+E38*$S$4+F38*$S$5) -> 408 | J38: =I38/1.2 -> 340 | K38: 45613 | L38: Payé | M38: Livrer | N38: VIREMENT | O38: ITALIE HT
A39: 38 | B39: James Carouge | C39: 1 | D39: 1 | E39: 1 | F39: 1 | I39: =IF(L39="Cadeau",0,C39*$S$2+D39*$S$3+E39*$S$4+F39*$S$5) -> 0 | J39: =I39/1.2 -> 0 | K39: 45613 | L39: Cadeau | M39: Livrer | N39: SARDAIGNE CONSO
A40: 39 | B40: AIRBNB | C40: 1 | I40: =IF(L40="Cadeau",0,C40*$S$2+D40*$S$3+E40*$S$4+F40*$S$5) -> 0 | J40: =I40/1.2 -> 0 | K40: 45597 | L40: Cadeau | M40: Livrer
A41: 40 | B41: Philippe Gintrand | C41: 12 | D41: 6 | E41: 6 | I41: =IF(L41="Cadeau",0,C41*$S$2+D41*$S$3+E41*$S$4+F41*$S$5) -> 429 | J41: =I41/1.2 -> 357.5 | K41: 45638 | L41: En attente de paiement | M41: Livrer | N41: ST VALLIER DEPOT | O41: STOCK
A42: 41 | B42: Jac/dan Bouilot | C42: 12 | D42: 12 | I42: =IF(L42="Cadeau",0,C42*$S$2+D42*$S$3+E42*$S$4+F42*$S$5) -> 432 | J42: =I42/1.2 -> 360 | K42: 45638 | L42: Payé | M42: Livrer | N42: VIREMENT
A43: 42 | B43: MICHEL LOVINE | D43: 6 | I43: =IF(L43="Cadeau",0,C43*$S$2+D43*$S$3+E43*$S$4+F43*$S$5) -> 114 | J43: =I43/1.2 -> 95 | K43: 45638 | L43: Payé | M43: Livrer | N43: CHEQUE
A44: 43 | B44: Jacques Girard | C44: 18 | D44: 12 | E44: 36 | I44: =IF(L44="Cadeau",0,C44*$S$2+D44*$S$3+E44*$S$4+F44*$S$5) -> 1200 | J44: =I44/1.2 -> 1000 | K44: 45638 | L44: Payé | M44: Livrer | N44: CHEQUE | O44: 1 PRESTIGE CADEAU
A45: 44 | B45: GONDRE JEAN CHRISTOPHE | E45: 6 | I45: =IF(L45="Cadeau",0,C45*$S$2+D45*$S$3+E45*$S$4+F45*$S$5) -> 111 | J45: =I45/1.2 -> 92.5 | K45: 45638 | L45: Payé | M45: Livrer | N45: VIREMENT
A46: 45 | B46: AVRIL SOPHIE | E46: 6 | I46: =IF(L46="Cadeau",0,C46*$S$2+D46*$S$3+E46*$S$4+F46*$S$5) -> 111 | J46: =I46/1.2 -> 92.5 | K46: 45638 | L46: Payé | M46: Livrer | N46: CHEQUE
A47: 46 | B47: James Carouge | D47: 1 | E47: 6 | F47: 2 | I47: =IF(L47="Cadeau",0,C47*$S$2+D47*$S$3+E47*$S$4+F47*$S$5) -> 0 | J47: =I47/1.2 -> 0 | K47: 45638 | L47: Cadeau | M47: Livrer | N47: ST VALLIER 6 CADEAU
A48: 47 | B48: PATRICK ABRY | E48: 12 | I48: =IF(L48="Cadeau",0,C48*$S$2+D48*$S$3+E48*$S$4+F48*$S$5) -> 222 | J48: =I48/1.2 -> 185 | K48: 45641 | L48: Payé | M48: Livrer | N48: PLUS LIVRAISON | O48: GRATUITE
A49: 48 | B49: ABRY SOLENE | E49: 18 | I49: =IF(L49="Cadeau",0,C49*$S$2+D49*$S$3+E49*$S$4+F49*$S$5) -> 333 | J49: =I49/1.2 -> 277.5 | K49: 45641 | L49: En attente de paiement | M49: Livrer | N49: PLUS LIVRAISON | O49: 38.99
A50: 49 | B50: Gregory Cireddu | C50: 60 | E50: 6 | I50: =IF(L50="Cadeau",0,C50*$S$2+D50*$S$3+E50*$S$4+F50*$S$5) -> 1131 | J50: =I50/1.2 -> 942.5 | K50: 45642 | L50: En attente de paiement | M50: Livrer
A51: 50 | B51: SEVERINE PAQUIN | E51: 6 | I51: =IF(L51="Cadeau",0,C51*$S$2+D51*$S$3+E51*$S$4+F51*$S$5) -> 111 | J51: =I51/1.2 -> 92.5 | K51: 45642 | L51: Payé | M51: Livrer | N51: VIREMENT
A52: 51 | B52: Regis Paquin | E52: 12 | I52: =IF(L52="Cadeau",0,C52*$S$2+D52*$S$3+E52*$S$4+F52*$S$5) -> 222 | J52: =I52/1.2 -> 185 | K52: 45642 | L52: Payé | M52: Livrer | N52: VIREMENT
A53: 52 | B53: XANTI BILBAO | C53: 6 | D53: 6 | E53: 6 | I53: =IF(L53="Cadeau",0,C53*$S$2+D53*$S$3+E53*$S$4+F53*$S$5) -> 327 | J53: =I53/1.2 -> 272.5 | K53: 45643 | L53: Payé | M53: Livrer | N53: Virement | O53: 1 ROSE CADEAU
A54: 53 | B54: REMY | C54: 6 | E54: 12 | F54: 6 | I54: =IF(L54="Cadeau",0,C54*$S$2+D54*$S$3+E54*$S$4+F54*$S$5) -> 486 | J54: =I54/1.2 -> 405 | K54: 45643 | L54: Payé | M54: Livrer | N54: Virement
A55: 54 | B55: James Carouge | C55: 2 | D55: 4 | E55: 3 | F55: 3 | I55: =IF(L55="Cadeau",0,C55*$S$2+D55*$S$3+E55*$S$4+F55*$S$5) -> 0 | J55: =I55/1.2 -> 0 | K55: 45645 | L55: Cadeau | M55: Livrer | N55: SARDAIGNE
A56: 55 | B56: AIRBNB | C56: 1 | I56: =IF(L56="Cadeau",0,C56*$S$2+D56*$S$3+E56*$S$4+F56*$S$5) -> 0 | J56: =I56/1.2 -> 0 | K56: 45655 | L56: Cadeau | M56: Livrer | N56: CADEAU
A57: 56 | I57: =IF(L57="Cadeau",0,C57*$S$2+D57*$S$3+E57*$S$4+F57*$S$5) -> 0 | J57: =I57/1.2 -> 0
A58: 57 | I58: =IF(L58="Cadeau",0,C58*$S$2+D58*$S$3+E58*$S$4+F58*$S$5) -> 0 | J58: =I58/1.2 -> 0
A59: 58 | I59: =IF(L59="Cadeau",0,C59*$S$2+D59*$S$3+E59*$S$4+F59*$S$5) -> 0 | J59: =I59/1.2 -> 0
A60: 59 | I60: =IF(L60="Cadeau",0,C60*$S$2+D60*$S$3+E60*$S$4+F60*$S$5) -> 0 | J60: =I60/1.2 -> 0
A61: 60 | I61: =IF(L61="Cadeau",0,C61*$S$2+D61*$S$3+E61*$S$4+F61*$S$5) -> 0 | J61: =I61/1.2 -> 0
A62: 61 | I62: =IF(L62="Cadeau",0,C62*$S$2+D62*$S$3+E62*$S$4+F62*$S$5) -> 0 | J62: =I62/1.2 -> 0
A63: 62 | I63: =IF(L63="Cadeau",0,C63*$S$2+D63*$S$3+E63*$S$4+F63*$S$5) -> 0 | J63: =I63/1.2 -> 0
A64: 63 | I64: =IF(L64="Cadeau",0,C64*$S$2+D64*$S$3+E64*$S$4+F64*$S$5) -> 0 | J64: =I64/1.2 -> 0
A65: 64 | I65: =IF(L65="Cadeau",0,C65*$S$2+D65*$S$3+E65*$S$4+F65*$S$5) -> 0 | J65: =I65/1.2 -> 0
A66: 65 | I66: =IF(L66="Cadeau",0,C66*$S$2+D66*$S$3+E66*$S$4+F66*$S$5) -> 0 | J66: =I66/1.2 -> 0
A67: 66 | I67: =IF(L67="Cadeau",0,C67*$S$2+D67*$S$3+E67*$S$4+F67*$S$5) -> 0 | J67: =I67/1.2 -> 0
A68: 67 | I68: =IF(L68="Cadeau",0,C68*$S$2+D68*$S$3+E68*$S$4+F68*$S$5) -> 0 | J68: =I68/1.2 -> 0
... A77: 76 | I77: =IF(L77="Cadeau",0,C77*$S$2+D77*$S$3+E77*$S$4+F77*$S$5) -> 0 | J77: =I77/1.2 -> 0
A78: =IF(L78="CAdeau",0,MAX($A$2:A77)+1) -> 77 | I78: =IF(L78="Cadeau",0,C78*$S$2+D78*$S$3+E78*$S$4+F78*$S$5) -> 0 | J78: =I78/1.2 -> 0
A79: =IF(L79="CAdeau",0,MAX($A$2:A78)+1) -> 78 | I79: =IF(L79="Cadeau",0,C79*$S$2+D79*$S$3+E79*$S$4+F79*$S$5) -> 0 | J79: =I79/1.2 -> 0
A80: =IF(L80="CAdeau",0,MAX($A$2:A79)+1) -> 79 | I80: =IF(L80="Cadeau",0,C80*$S$2+D80*$S$3+E80*$S$4+F80*$S$5) -> 0 | J80: =I80/1.2 -> 0
A81: =IF(L81="CAdeau",0,MAX($A$2:A80)+1) -> 80 | I81: =IF(L81="Cadeau",0,C81*$S$2+D81*$S$3+E81*$S$4+F81*$S$5) -> 0 | J81: =I81/1.2 -> 0
A82: =IF(L82="CAdeau",0,MAX($A$2:A81)+1) -> 81 | I82: =IF(L82="Cadeau",0,C82*$S$2+D82*$S$3+E82*$S$4+F82*$S$5) -> 0 | J82: =I82/1.2 -> 0
A83: =IF(L83="CAdeau",0,MAX($A$2:A82)+1) -> 82 | I83: =IF(L83="Cadeau",0,C83*$S$2+D83*$S$3+E83*$S$4+F83*$S$5) -> 0 | J83: =I83/1.2 -> 0
A84: =IF(L84="CAdeau",0,MAX($A$2:A83)+1) -> 83 | I84: =IF(L84="Cadeau",0,C84*$S$2+D84*$S$3+E84*$S$4+F84*$S$5) -> 0 | J84: =I84/1.2 -> 0
A85: =IF(L85="CAdeau",0,MAX($A$2:A84)+1) -> 84 | I85: =IF(L85="Cadeau",0,C85*$S$2+D85*$S$3+E85*$S$4+F85*$S$5) -> 0 | J85: =I85/1.2 -> 0
A86: =IF(L86="CAdeau",0,MAX($A$2:A85)+1) -> 85 | I86: =IF(L86="Cadeau",0,C86*$S$2+D86*$S$3+E86*$S$4+F86*$S$5) -> 0 | J86: =I86/1.2 -> 0
A87: =IF(L87="CAdeau",0,MAX($A$2:A86)+1) -> 86 | I87: =IF(L87="Cadeau",0,C87*$S$2+D87*$S$3+E87*$S$4+F87*$S$5) -> 0 | J87: =I87/1.2 -> 0
A88: =IF(L88="CAdeau",0,MAX($A$2:A87)+1) -> 87 | I88: =IF(L88="Cadeau",0,C88*$S$2+D88*$S$3+E88*$S$4+F88*$S$5) -> 0 | J88: =I88/1.2 -> 0
A89: =IF(L89="CAdeau",0,MAX($A$2:A88)+1) -> 88 | I89: =IF(L89="Cadeau",0,C89*$S$2+D89*$S$3+E89*$S$4+F89*$S$5) -> 0 | J89: =I89/1.2 -> 0
... A94: =IF(L94="CAdeau",0,MAX($A$2:A93)+1) -> 93 | I94: =IF(L94="Cadeau",0,C94*$S$2+D94*$S$3+E94*$S$4+F94*$S$5) -> 0 | J94: =I94/1.2 -> 0
A95: =IF(L95="CAdeau",0,MAX($A$2:A94)+1) -> 94
A96: =IF(L96="CAdeau",0,MAX($A$2:A95)+1) -> 95
A97: =IF(L97="CAdeau",0,MAX($A$2:A96)+1) -> 96
A98: =IF(L98="CAdeau",0,MAX($A$2:A97)+1) -> 97
A100: =IF(L100="CAdeau",0,MAX($A$2:A99)+1) -> 98
A101: =IF(L101="CAdeau",0,MAX($A$2:A100)+1) -> 99
A102: =IF(L102="CAdeau",0,MAX($A$2:A101)+1) -> 100
A103: =IF(L103="CAdeau",0,MAX($A$2:A102)+1) -> 101
A104: =IF(L104="CAdeau",0,MAX($A$2:A103)+1) -> 102
A105: =IF(L105="CAdeau",0,MAX($A$2:A104)+1) -> 103
A106: =IF(L106="CAdeau",0,MAX($A$2:A105)+1) -> 104
A107: =IF(L107="CAdeau",0,MAX($A$2:A106)+1) -> 105
... A161: =IF(L161="CAdeau",0,MAX($A$2:A160)+1) -> 159

Sheet Facturation 2024
E5: CHAMPAGNE CAROUGE CIREDDU
G8: Nom | I8: =VLOOKUP(C16,'Suivi Facturation 2024'!$A$1:$K$10002,2,FALSE) -> Stanislas BOUTMY
G9: Adresse | I9: =VLOOKUP(I8,'Suivi Client'!C2:H2960,3,FALSE)
I10: =VLOOKUP(I8,'Suivi Client'!C2:H2960,4,FALSE) | J10: =VLOOKUP(I8,'Suivi Client'!C2:H2960,5,FALSE) -> PARIS
G12: Adresse e-mail | I12: =IF(VLOOKUP(I8,'Suivi Client'!$C$2:$H$2000,2,FALSE)=0,"",VLOOKUP(I8,'Suivi Client'!$C$2:$H$2000,2,FALSE)) -> stanislas.boutmy@sienna-im.com
M14: 23
A16: numéro de facturation | C16: 31
A17: Date de facturation
A21: Contenance | B21: Designation | H21: Qté | I21: Prix unitaire TTC | K21: Montant TTC
A23: =IF(VLOOKUP($C$16,'Suivi Facturation 2024'!$A$2:$M$1096,3,FALSE)>0,"0,75","") | B23: =IF(VLOOKUP($C$16,'Suivi Facturation 2024'!$A$2:$M$978,3,FALSE)>0,"Bouteille CHAMPAGNE SELECTION","") | H23: =IF(VLOOKUP($C$16,'Suivi Facturation 2025'!$A$2:$M$1096,3,FALSE)>0,VLOOKUP($C$16,'Suivi Facturation 2025'!$A$2:$M$1096,3,FALSE),"") | I23: =IF(VLOOKUP($C$16,'Suivi Facturation 2025'!$A$2:$M$1096,3,FALSE)>0,'Suivi Facturation 2025'!S2,"") | K23: =IF(VLOOKUP($C$16,'Suivi Facturation 2025'!$A$2:$M$1096,3,FALSE)>0,I23*H23,"")
A24: =IF(VLOOKUP($C$16,'Suivi Facturation 2024'!$A$2:$M$1096,4,FALSE)>0,"0,75","") | B24: =IF(VLOOKUP($C$16,'Suivi Facturation 2024'!$A$2:$M$978,4,FALSE)>0,"Bouteille CHAMPAGNE ROSE","") | H24: =IF(VLOOKUP($C$16,'Suivi Facturation 2025'!$A$2:$M$1096,4,FALSE)>0,VLOOKUP($C$16,'Suivi Facturation 2025'!$A$2:$M$1096,4,FALSE),"") | I24: =IF(VLOOKUP($C$16,'Suivi Facturation 2025'!$A$2:$M$1096,4,FALSE)>0,'Suivi Facturation 2025'!S3,"") | K24: =IF(VLOOKUP($C$16,'Suivi Facturation 2025'!$A$2:$M$1096,4,FALSE)>0,I24*H24,"")
A25: =IF(VLOOKUP($C$16,'Suivi Facturation 2024'!$A$2:$M$1096,5,FALSE)>0,"0,75","") -> 0,75 | B25: =IF(VLOOKUP($C$16,'Suivi Facturation 2024'!$A$2:$M$978,5,FALSE)>0,"Bouteille CHAMPAGNE BLANC DE BLANC","") -> Bouteille CHAMPAGNE BLANC DE BLANC | H25: =IF(VLOOKUP($C$16,'Suivi Facturation 2024'!$A$2:$M$1996,5,FALSE)>0,VLOOKUP($C$16,'Suivi Facturation 2024'!$A$2:$M$1996,5,FALSE),"") -> 12 | I25: =IF(VLOOKUP($C$16,'Suivi Facturation 2024'!$A$2:$M$1096,5,FALSE)>0,'Suivi Facturation 2024'!S4,"") -> 18.5 | K25: =IF(VLOOKUP($C$16,'Suivi Facturation 2024'!$A$2:$M$1096,5,FALSE)>0,I25*H25,"") -> 222
A26: =IF(VLOOKUP($C$16,'Suivi Facturation 2025'!$A$2:$M$1096,6,FALSE)>0,"0,75","") | B26: =IF(VLOOKUP($C$16,'Suivi Facturation 2025'!$A$2:$M$1096,6,FALSE)>0,"Bouteille CHAMPAGNE PRESTIGE","") | H26: =IF(VLOOKUP($C$16,'Suivi Facturation 2025'!$A$2:$M$1096,6,FALSE)>0,VLOOKUP($C$16,'Suivi Facturation 2025'!$A$2:$M$1096,6,FALSE),"") | I26: =IF(VLOOKUP($C$16,'Suivi Facturation 2025'!$A$2:$M$1096,6,FALSE)>0,'Suivi Facturation 2025'!S5,"") | K26: =IF(VLOOKUP($C$16,'Suivi Facturation 2025'!$A$2:$M$1096,6,FALSE)>0,I26*H26,"")
A27: =IF(VLOOKUP($C$16,'Suivi Facturation 2025'!$A$2:$M$1096,7,FALSE)>0,"1,5","") | B27: =IF(VLOOKUP($C$16,'Suivi Facturation 2025'!$A$2:$M$1096,7,FALSE)>0,"MAGNUM SELECTION","") | I27: =IF(VLOOKUP($C$16,'Suivi Facturation 2025'!$A$2:$M$1096,7,FALSE)>0,'Suivi Facturation 2025'!S6,"") | K27: =IF(VLOOKUP($C$16,'Suivi Facturation 2025'!$A$2:$M$1096,7,FALSE)>0,I27*H27,"")
B28: =IF(VLOOKUP($C$16,'Suivi Facturation 2025'!$A$2:$P$1978,16,FALSE)>0,"PRIX LIVRAISON","") | K28: =IF(VLOOKUP($C$16,'Suivi Facturation 2025'!$A$2:$P$1978,16,FALSE)>0,VLOOKUP($C$16,'Suivi Facturation 2025'!$A$2:$P$1978,16,FALSE),"")
K37: Total HT | L37: =SUM(K23:L30)-L38 -> 185
K38: TVA (20%) | L38: =IFERROR(SUM(K23:L29)-SUM(K23:L29)/1.2,"") -> 37
K40: Total TTC | L40: =SUM(K23:L30) -> 222
A42: Toute somme impayée à son échéance produira, de plein droit et sans mise en demeure, un intérêt égal à 1,5 fois le taux d'intérêt légal par mois de retard. Nos conditions de vente ne prévoient pas d'escompte pour paiement anticipé. Coordonnées bancaires Titulaire du compte : JAMES CAROUGE IBAN FR76 1020 6000 4848 3510 3712 067 BIC AGRIFRPP802
A54: CHAMPAGNE CAROUGE CIREDDU 6 rue de l'eglise 51190 FLAVIGNY Tel : 06 77 95 90 62 SIRET 843 516 642 00017 N° TVA intracommunautaire FR67 843 516 642

Sheet Facturation 2020
E5: CHAMPAGNE CAROUGE CIREDDU
G8: Nom | I8: =VLOOKUP(C16,'Suivi Facturation 2020'!$A$5:$I$10004,2,FALSE) -> #N/A
G9: Adresse | I9: =VLOOKUP(I8,'Suivi Client'!$C$2:$H$2000,3,FALSE) &" " & VLOOKUP(I8,'Suivi Client'!$C$2:$H$2000,4,FALSE) &" " & VLOOKUP(I8,'Suivi Client'!$C$2:$H$2000,5,FALSE) -> #N/A
G12: Adresse e-mail | I12: =IF(VLOOKUP(I8,'Suivi Client'!$C$2:$H$2000,2,FALSE)=0,"",VLOOKUP(I8,'Suivi Client'!$C$2:$H$2000,2,FALSE)) -> #N/A
A16: numéro de facturation | C16: 45
A17: Date de facturation
A21: Contenance | B21: Designation | H21: Qté | I21: Prix unitaire TTC | K21: Montant TTC
A23: =IF(VLOOKUP($C$16,'Suivi Facturation 2020'!$A$1:$I$104,3,FALSE)>0,"0,75","") -> #N/A | B23: =IF(VLOOKUP($C$16,'Suivi Facturation 2020'!$A$1:$I$104,3,FALSE)>0,"Bouteille CHAMPAGNE SELECTION","") -> #N/A | H23: =IF(VLOOKUP($C$16,'Suivi Facturation 2020'!$A$1:$I$104,3,FALSE)>0,VLOOKUP($C$16,'Suivi Facturation 2020'!$A$1:$I$104,3,FALSE),"") -> #N/A | I23: =IF(VLOOKUP($C$16,'Suivi Facturation 2020'!$A$1:$I$104,3,FALSE)>0,16,"") -> #N/A | K23: =IF(VLOOKUP($C$16,'Suivi Facturation 2020'!$A$1:$I$104,3,FALSE)>0,I23*H23,"") -> #N/A
A24: =IF(VLOOKUP($C$16,'Suivi Facturation 2020'!$A$1:$I$104,4,FALSE)>0,"0,75","") -> #N/A | B24: =IF(VLOOKUP($C$16,'Suivi Facturation 2020'!$A$1:$I$104,4,FALSE)>0,"Bouteille CHAMPAGNE ROSE","") -> #N/A | H24: =IF(VLOOKUP($C$16,'Suivi Facturation 2020'!$A$1:$I$104,4,FALSE)>0,VLOOKUP($C$16,'Suivi Facturation 2020'!$A$1:$I$104,4,FALSE),"") -> #N/A | I24: =IF(VLOOKUP($C$16,'Suivi Facturation 2020'!$A$1:$I$104,4,FALSE)>0,18,"") -> #N/A | K24: =IF(VLOOKUP($C$16,'Suivi Facturation 2020'!$A$1:$I$104,4,FALSE)>0,I24*H24,"") -> #N/A
K35: Total HT | L35: =SUM(K23:L24)-L36 -> #N/A
K36: TVA (20%) | L36: =IFERROR(SUM(K23:L24)-SUM(K23:L24)/1.2,"")
K38: Total TTC | L38: =SUM(K23:L24) -> #N/A
A40: Toute somme impayée à son échéance produira, de plein droit et sans mise en demeure, un intérêt égal à 1,5 fois le taux d'intérêt légal par mois de retard. Nos conditions de vente ne prévoient pas d'escompte pour paiement anticipé. Coordonnées bancaires Titulaire du compte : JAMES CAROUGE IBAN FR76 1020 6000 4848 3510 3712 067 BIC AGRIFRPP802
A52: CHAMPAGNE CAROUGE CIREDDU 6 rue de l'eglise 51190 FLAVIGNY Tel : 06 77 95 90 62 SIRET 843 516 642 00017 N° TVA intracommunautaire FR67 843 516 642

Sheet Facturation 2024 HT
E5: CHAMPAGNE CAROUGE CIREDDU
G8: Nom | I8: =VLOOKUP(C16,'Suivi Facturation 2025'!$A$1:$K$10002,2,FALSE) -> PAOLA ZICCA
G9: Adresse | I9: =VLOOKUP(I8,'Suivi Client'!C2:H2960,3,FALSE) -> VIA GIALETTO
I10: =VLOOKUP(I8,'Suivi Client'!C2:H2960,4,FALSE) -> 9100 | J10: =VLOOKUP(I8,'Suivi Client'!C2:H2960,5,FALSE) -> NUORO SARDEGNA
G12: Adresse e-mail | I12: =IF(VLOOKUP(I8,'Suivi Client'!$C$2:$H$2000,2,FALSE)=0,"",VLOOKUP(I8,'Suivi Client'!$C$2:$H$2000,2,FALSE))
A16: numéro de facturation | C16: 37
A17: Date de facturation | C17: 45613
A21: Contenance | B21: Designation | H21: Qté | I21: Prix unitaire HT | K21: Montant HT
A23: =IF(VLOOKUP($C$16,'Suivi Facturation 2025'!$A$2:$M$1096,3,FALSE)>0,"0,75","") -> 0,75 | B23: =IF(VLOOKUP($C$16,'Suivi Facturation 2025'!$A$2:$M$978,3,FALSE)>0,"Bouteille CHAMPAGNE SELECTION","") -> Bouteille CHAMPAGNE SELECTION | H23: =IF(VLOOKUP($C$16,'Suivi Facturation 2025'!$A$2:$M$1096,3,FALSE)>0,VLOOKUP($C$16,'Suivi Facturation 2025'!$A$2:$M$1096,3,FALSE),"") -> 6 | I23: =IF(VLOOKUP($C$16,'Suivi Facturation 2025'!$A$2:$M$1096,3,FALSE)>0,'Suivi Facturation 2025'!S2,"") -> 17 | K23: =IF(VLOOKUP($C$16,'Suivi Facturation 2025'!$A$2:$M$1096,3,FALSE)>0,I23*H23,"") -> 102
A24: =IF(VLOOKUP($C$16,'Suivi Facturation 2025'!$A$2:$M$1096,4,FALSE)>0,"0,75","") -> 0,75 | B24: =IF(VLOOKUP($C$16,'Suivi Facturation 2025'!$A$2:$M$978,4,FALSE)>0,"Bouteille CHAMPAGNE ROSE","") -> Bouteille CHAMPAGNE ROSE | H24: =IF(VLOOKUP($C$16,'Suivi Facturation 2025'!$A$2:$M$1096,4,FALSE)>0,VLOOKUP($C$16,'Suivi Facturation 2025'!$A$2:$M$1096,4,FALSE),"") -> 6 | I24: =IF(VLOOKUP($C$16,'Suivi Facturation 2025'!$A$2:$M$1096,4,FALSE)>0,'Suivi Facturation 2025'!S3,"") -> 19 | K24: =IF(VLOOKUP($C$16,'Suivi Facturation 2025'!$A$2:$M$1096,4,FALSE)>0,I24*H24,"") -> 114
A25: =IF(VLOOKUP($C$16,'Suivi Facturation 2025'!$A$2:$M$1096,5,FALSE)>0,"0,75","") -> 0,75 | B25: =IF(VLOOKUP($C$16,'Suivi Facturation 2025'!$A$2:$M$978,5,FALSE)>0,"Bouteille CHAMPAGNE BLANC DE BLANC","") -> Bouteille CHAMPAGNE BLANC DE BLANC | H25: =IF(VLOOKUP($C$16,'Suivi Facturation 2025'!$A$2:$M$1996,5,FALSE)>0,VLOOKUP($C$16,'Suivi Facturation 2025'!$A$2:$M$1996,5,FALSE),"") -> 24 | I25: =IF(VLOOKUP($C$16,'Suivi Facturation 2025'!$A$2:$M$1096,5,FALSE)>0,'Suivi Facturation 2025'!S4,"") -> 18.5 | K25: =IF(VLOOKUP($C$16,'Suivi Facturation 2025'!$A$2:$M$1096,5,FALSE)>0,I25*H25,"") -> 444
A26: =IF(VLOOKUP($C$16,'Suivi Facturation 2025'!$A$2:$M$1096,6,FALSE)>0,"0,75","") | B26: =IF(VLOOKUP($C$16,'Suivi Facturation 2025'!$A$2:$M$1096,6,FALSE)>0,"Bouteille CHAMPAGNE PRESTIGE","") | H26: =IF(VLOOKUP($C$16,'Suivi Facturation 2025'!$A$2:$M$1096,6,FALSE)>0,VLOOKUP($C$16,'Suivi Facturation 2025'!$A$2:$M$1096,6,FALSE),"") | I26: =IF(VLOOKUP($C$16,'Suivi Facturation 2025'!$A$2:$M$1096,6,FALSE)>0,'Suivi Facturation 2025'!S5,"") | K26: =IF(VLOOKUP($C$16,'Suivi Facturation 2025'!$A$2:$M$1096,6,FALSE)>0,I26*H26,"")
A27: =IF(VLOOKUP($C$16,'Suivi Facturation 2025'!$A$2:$M$1096,7,FALSE)>0,"1,5","") | B27: =IF(VLOOKUP($C$16,'Suivi Facturation 2025'!$A$2:$M$1096,7,FALSE)>0,"MAGNUM SELECTION","") | I27: =IF(VLOOKUP($C$16,'Suivi Facturation 2025'!$A$2:$M$1096,7,FALSE)>0,'Suivi Facturation 2025'!S6,"") | K27: =IF(VLOOKUP($C$16,'Suivi Facturation 2025'!$A$2:$M$1096,7,FALSE)>0,I27*H27,"")
B28: =IF(VLOOKUP($C$16,'Suivi Facturation 2025'!$A$2:$P$1978,14,FALSE)>0,"PRIX LIVRAISON","") -> PRIX LIVRAISON | K28: =IF(VLOOKUP($C$16,'Suivi Facturation 2025'!$A$2:$P$1978,14,FALSE)>0,VLOOKUP($C$16,'Suivi Facturation 2025'!$A$2:$P$1978,14,FALSE),"") -> ESPECE/ITALIE
K40: Total HT | L40: =SUM(K23:L30) -> 660
A42: Toute somme impayée à son échéance produira, de plein droit et sans mise en demeure, un intérêt égal à 1,5 fois le taux d'intérêt légal par mois de retard. Nos conditions de vente ne prévoient pas d'escompte pour paiement anticipé. Coordonnées bancaires Titulaire du compte : JAMES CAROUGE IBAN FR76 1020 6000 4848 3510 3712 067 BIC AGRIFRPP802
A54: CHAMPAGNE CAROUGE CIREDDU 6 rue de l'eglise 51190 FLAVIGNY Tel : 06 77 95 90 62 SIRET 843 516 642 00017 N° TVA intracommunautaire FR67 843 516 642

Sheet Suivi Facturation 2023
A1: N?8M | B1: Nom Client | C1: NB Selection | D1: NB Rosé | E1: Nb blanc de blan | F1: Nb Prestige | G1: Magnum Selection | I1: Montant TTC bouteilles | J1: Montant HT | K1: Date de facturation | L1: Etat paiement | M1: Etat Commande | N1: paiement | O1: commentaire | P1: Prix Transport TTC | R1: Statistiques | S1: Prix unitaire TTC | T1: =S2/1.2 -> 14.166667
A2: 1 | B2: Karine GATE | E2: 4 | I2: =IF(L2="Cadeau",0,C2*$S$2+D2*$S$3+E2*$S$4+F2*$S$5) -> 74 | J2: =I2/1.2 -> 61.666667 | K2: 44949 | L2: ATT | M2: En attente de paiement | O2: CAve Leo | P2: SORTIE EN DRM | R2: Sélection | S2: 17
A3: 2 | B3: Léo Carouge | C3: 12 | D3: 12 | I3: =IF(L3="Cadeau",0,C3*$S$2+D3*$S$3+E3*$S$4+F3*$S$5) -> 432 | J3: =I3/1.2 -> 360 | K3: 44964 | L3: En attente de paiement | M3: Livrer | R3: Rosé | S3: 19
A4: 3 | B4: LEO FISHER | E4: 6 | I4: =IF(L4="Cadeau",0,C4*$S$2+D4*$S$3+E4*$S$4+F4*$S$5) -> 111 | J4: =I4/1.2 -> 92.5 | K4: 44981 | L4: Payé | M4: Livrer | N4: VIREMENT 14/03 | O4: DEPOSER PAR NINO | R4: Blanc de blanc | S4: 18.5
A5: 4 | B5: HUGO LANDRIEU | C5: 6 | I5: =IF(L5="Cadeau",0,C5*$S$2+D5*$S$3+E5*$S$4+F5*$S$5) -> 102 | J5: =I5/1.2 -> 85 | K5: 44981 | L5: Payé | M5: Livrer | N5: VIREMENT 1 /03 | O5: DEPOSER PAR NINO | R5: Prestige | S5: 27
A6: 5 | B6: Regis Paquin | E6: 6 | I6: =IF(L6="Cadeau",0,C6*$S$2+D6*$S$3+E6*$S$4+F6*$S$5) -> 111 | J6: =I6/1.2 -> 92.5 | K6: 44985 | L6: Payé | M6: Livrer | N6: VIREMENT 1 OCTOBRE | R6: Magnum Brut Selection | S6: 38
A7: 6 | B7: ANNE KAES | C7: 3 | D7: 1 | I7: =IF(L7="Cadeau",0,C7*$S$2+D7*$S$3+E7*$S$4+F7*$S$5) -> 70 | J7: =I7/1.2 -> 58.333333 | K7: 44989 | L7: Payé | M7: Livrer | N7: 44992 | O7: DEPOT ISA 2021 | P7: SORTIE EN DRM | R7: Nb bouteilles vendues | S7: =SUM(C2:D1201) -> 552
A8: 7 | B8: James Carouge | C8: 1 | D8: 5 | E8: 5 | I8: =IF(L8="Cadeau",0,C8*$S$2+D8*$S$3+E8*$S$4+F8*$S$5) -> 0 | J8: =I8/1.2 -> 0 | K8: 45016 | L8: Cadeau | N8: CONSO SARDAIGNE
A9: 8 | B9: MARC WEBER | C9: 102 | I9: =IF(L9="Cadeau",0,C9*$S$2+D9*$S$3+E9*$S$4+F9*$S$5) -> 1734 | J9: =I9/1.2 -> 1445 | K9: 45040 | L9: Payé | M9: Habillé | N9: livraison 195,60 A leur frais 98 | P9: 98 | R9: Chiffre d'affaire | S9: =SUM(I2:I1216) -> 16457.5
A10: 9 | B10: SEVERINE PAQUIN | C10: 12 | E10: 18 | I10: =IF(L10="Cadeau",0,C10*$S$2+D10*$S$3+E10*$S$4+F10*$S$5) -> 537 | J10: =I10/1.2 -> 447.5 | K10: 45013 | L10: Payé | M10: Livrer | O10: H TAXE ERREUR
A11: 10 | B11: PAOLA ZICCA | C11: 18 | E11: 12 | I11: =IF(L11="Cadeau",0,C11*$S$2+D11*$S$3+E11*$S$4+F11*$S$5) -> 528 | J11: =I11/1.2 -> 440 | K11: 45016 | L11: Payé | M11: Livrer | N11: ESPECE | O11: SARDAIGNE
A12: 11 | B12: NICOLA CIREDDU | C12: 19 | D12: 10 | E12: 12 | F12: 13 | I12: =IF(L12="Cadeau",0,C12*$S$2+D12*$S$3+E12*$S$4+F12*$S$5) -> 1086 | J12: =I12/1.2 -> 905 | K12: 45016 | L12: Payé | M12: Livrer | N12: ESPECE | O12: CADEAU 1 ROSE
A13: 12 | I13: =IF(L13="Cadeau",0,C13*$S$2+D13*$S$3+E13*$S$4+F13*$S$5) -> 0 | J13: =I13/1.2 -> 0
A14: 13 | B14: ROBERTO ANEDDA | F14: 2 | I14: =IF(L14="Cadeau",0,C14*$S$2+D14*$S$3+E14*$S$4+F14*$S$5) -> 54 | J14: =I14/1.2 -> 45 | K14: 45016 | L14: Payé | N14: ESPECE | O14: SARDAIGNE
A15: 14 | I15: =IF(L15="Cadeau",0,C15*$S$2+D15*$S$3+E15*$S$4+F15*$S$5) -> 0 | J15: =I15/1.2 -> 0
A16: 15 | B16: ROBERTO ANEDDA | C16: 1 | D16: 1 | E16: 1 | F16: 1 | I16: =IF(L16="Cadeau",0,C16*$S$2+D16*$S$3+E16*$S$4+F16*$S$5) -> 81.5 | J16: =I16/1.2 -> 67.916667 | K16: 45016 | L16: Payé | N16: DEGUSTATION | O16: ATELIER DEL VINO
A17: 16 | B17: Philippe Gintrand | C17: 6 | D17: 6 | I17: =IF(L17="Cadeau",0,C17*$S$2+D17*$S$3+E17*$S$4+F17*$S$5) -> 216 | J17: =I17/1.2 -> 180 | K17: 45051 | L17: Payé | O17: SUR Depot st vallier
A18: 17 | B18: Tony Bocock | C18: 36 | E18: 6 | I18: =IF(L18="Cadeau",0,C18*$S$2+D18*$S$3+E18*$S$4+F18*$S$5) -> 723 | J18: =I18/1.2 -> 602.5 | K18: 45065 | L18: Payé | M18: Livrer | N18: VIREMENT | O18: REPRISE MAISON
A19: 18 | B19: James Carouge | C19: 4 | E19: 1 | I19: =IF(L19="Cadeau",0,C19*$S$2+D19*$S$3+E19*$S$4+F19*$S$5) -> 0 | J19: =I19/1.2 -> 0 | K19: 45065 | L19: Cadeau | N19: CADEAU ET DEGUSTATION | O19: 1 SEL SANS CRD
A20: 19 | B20: CLAUDE FORGET | C20: 6 | E20: 6 | I20: =IF(L20="Cadeau",0,C20*$S$2+D20*$S$3+E20*$S$4+F20*$S$5) -> 213 | J20: =I20/1.2 -> 177.5 | K20: 45066 | L20: Payé | M20: Livrer | N20: ESPECE | O20: AIRBNB
A21: 20 | B21: MARC WEBER | C21: 6 | I21: =IF(L21="Cadeau",0,C21*$S$2+D21*$S$3+E21*$S$4+F21*$S$5) -> 102 | J21: =I21/1.2 -> 85 | K21: 45068 | L21: Payé | M21: Livrer | N21: VIREMENT | P21: 19.06
A22: 21 | B22: Philippe Gintrand | D22: 9 | E22: 9 | I22: =IF(L22="Cadeau",0,C22*$S$2+D22*$S$3+E22*$S$4+F22*$S$5) -> 337.5 | J22: =I22/1.2 -> 281.25 | K22: 45091 | L22: Payé | M22: Livrer | N22: VIRT NEMO 225 | O22: DEPOT ST VALLIER
A23: 22 | B23: Léo Carouge | C23: 6 | E23: 12 | I23: =IF(L23="Cadeau",0,C23*$S$2+D23*$S$3+E23*$S$4+F23*$S$5) -> 324 | J23: =I23/1.2 -> 270 | K23: 45105 | L23: En attente de paiement | M23: Livrer
A24: 23 | B24: MARIA TERESA MASCARELLO | C24: 3 | E24: 2 | F24: 2 | I24: =IF(L24="Cadeau",0,C24*$S$2+D24*$S$3+E24*$S$4+F24*$S$5) -> 142 | J24: =I24/1.2 -> 118.33333 | K24: 45113 | L24: Payé | M24: Livrer | N24: ESPECE
A25: 24 | B25: THIBAULT DE SAINT PRIEST | E25: 36 | I25: =IF(L25="Cadeau",0,C25*$S$2+D25*$S$3+E25*$S$4+F25*$S$5) -> 666 | J25: =I25/1.2 -> 555 | K25: 45116 | L25: Payé | M25: Livrer | N25: VIREMENT | O25: PLUS LIVRAISQON | P25: 65.61
A26: 25 | B26: SEVERINE PAQUIN | E26: 6 | I26: =IF(L26="Cadeau",0,C26*$S$2+D26*$S$3+E26*$S$4+F26*$S$5) -> 111 | J26: =I26/1.2 -> 92.5 | K26: 45116 | L26: Payé | M26: Livrer | N26: VIREMENT 27/02 | O26: 1 ROSE CADEAUX
A27: 26 | B27: Gintrand Simon | E27: 48 | I27: =IF(L27="Cadeau",0,C27*$S$2+D27*$S$3+E27*$S$4+F27*$S$5) -> 888 | J27: =I27/1.2 -> 740 | K27: 45118 | L27: Payé | M27: Habillé | N27: VIREMENT | O27: 1 ROSE CADEAU
A28: 27 | B28: REMI PATIES | C28: 12 | E28: 6 | I28: =IF(L28="Cadeau",0,C28*$S$2+D28*$S$3+E28*$S$4+F28*$S$5) -> 315 | J28: =I28/1.2 -> 262.5 | K28: 45120 | L28: Payé | M28: Habillé | N28: 102 ESPESCE | O28: VIRT 213
A29: 28 | B29: ROBERTO ANEDDA | E29: 6 | F29: 6 | I29: =IF(L29="Cadeau",0,C29*$S$2+D29*$S$3+E29*$S$4+F29*$S$5) -> 273 | J29: =I29/1.2 -> 227.5 | K29: 45122 | L29: Payé | N29: virement le 17/01 | O29: SARDAIGNE
A30: 29 | B30: James Carouge | C30: 2 | E30: 2 | I30: =IF(L30="Cadeau",0,C30*$S$2+D30*$S$3+E30*$S$4+F30*$S$5) -> 0 | J30: =I30/1.2 -> 0 | K30: 45138 | L30: Cadeau | N30: 0 | O30: DEGUST | P30: SANS CRD
A31: 30 | B31: James Carouge | C31: 3 | D31: 2 | E31: 1 | I31: =IF(L31="Cadeau",0,C31*$S$2+D31*$S$3+E31*$S$4+F31*$S$5) -> 0 | J31: =I31/1.2 -> 0 | K31: 45138 | L31: Cadeau | N31: 0 | O31: CONSO | P31: AVEC CRD
A32: 31 | B32: James Carouge | C32: 6 | D32: 6 | E32: 6 | I32: =IF(L32="Cadeau",0,C32*$S$2+D32*$S$3+E32*$S$4+F32*$S$5) -> 0 | J32: =I32/1.2 -> 0 | K32: 45139 | L32: Cadeau | N32: sardaigne | O32: CONSO | P32: avec crd
A33: 32 | B33: Léo Carouge | E33: 1 | I33: =IF(L33="Cadeau",0,C33*$S$2+D33*$S$3+E33*$S$4+F33*$S$5) -> 0 | J33: =I33/1.2 -> 0 | K33: 45144 | L33: Cadeau | N33: DEGUSTATION
A34: 33 | B34: ROBERTO ANEDDA | C34: 12 | D34: 6 | E34: 6 | F34: 12 | I34: =IF(L34="Cadeau",0,C34*$S$2+D34*$S$3+E34*$S$4+F34*$S$5) -> 753 | J34: =I34/1.2 -> 627.5 | K34: 45148 | L34: Payé | M34: Livrer | N34: VIREMENT LE 17/01
A35: 34 | B35: James Carouge | C35: 6 | E35: 6 | I35: =IF(L35="Cadeau",0,C35*$S$2+D35*$S$3+E35*$S$4+F35*$S$5) -> 0 | J35: =I35/1.2 -> 0 | K35: 45148 | L35: Cadeau | N35: NOUS MEME
A36: 35 | B36: Stanislas BOUTMY | E36: 6 | I36: =IF(L36="Cadeau",0,C36*$S$2+D36*$S$3+E36*$S$4+F36*$S$5) -> 111 | J36: =I36/1.2 -> 92.5 | K36: 45170 | L36: Payé | M36: Livrer | N36: virement | O36: DEPOT LEO
A37: 36 | B37: Philémon Parent | C37: 6 | I37: =IF(L37="Cadeau",0,C37*$S$2+D37*$S$3+E37*$S$4+F37*$S$5) -> 102 | J37: =I37/1.2 -> 85 | K37: 45188 | L37: Payé | M37: Livrer | N37: CHEQUE | O37: GERMAINE
A38: 37 | B38: Cadeau Vendages | C38: 7 | E38: 1 | I38: =IF(L38="Cadeau",0,C38*$S$2+D38*$S$3+E38*$S$4+F38*$S$5) -> 0 | J38: =I38/1.2 -> 0 | K38: 45184 | L38: Cadeau | O38: VENDANGES
A39: 38 | B39: Regis Paquin | E39: 12 | I39: =IF(L39="Cadeau",0,C39*$S$2+D39*$S$3+E39*$S$4+F39*$S$5) -> 222 | J39: =I39/1.2 -> 185 | K39: 45199 | L39: Payé | N39: VIREMENT
A40: 39 | B40: LYDIA | E40: 2 | I40: =IF(L40="Cadeau",0,C40*$S$2+D40*$S$3+E40*$S$4+F40*$S$5) -> 37 | J40: =I40/1.2 -> 30.833333 | K40: 45078 | L40: Payé | N40: VIREMENT 40
A41: 40 | B41: DEBBIE | C41: 9 | I41: =IF(L41="Cadeau",0,C41*$S$2+D41*$S$3+E41*$S$4+F41*$S$5) -> 153 | J41: =I41/1.2 -> 127.5 | K41: 45165 | L41: Payé | N41: VIREMENT | O41: AIRBNB
A42: 41 | B42: James Carouge | E42: 5 | I42: =IF(L42="Cadeau",0,C42*$S$2+D42*$S$3+E42*$S$4+F42*$S$5) -> 0 | J42: =I42/1.2 -> 0 | K42: 45199 | L42: Cadeau | N42: ANN CHLOE | O42: CADEAU
A43: 42 | B43: James Carouge | C43: 7 | I43: =IF(L43="Cadeau",0,C43*$S$2+D43*$S$3+E43*$S$4+F43*$S$5) -> 0 | J43: =I43/1.2 -> 0 | K43: 45184 | L43: Cadeau | N43: VENDANGES | O43: CONSO
A44: 43 | B44: Léo Carouge | C44: 6 | D44: 6 | E44: 6 | I44: =IF(L44="Cadeau",0,C44*$S$2+D44*$S$3+E44*$S$4+F44*$S$5) -> 0 | J44: =I44/1.2 -> 0 | K44: 45261 | L44: Cadeau | M44: Livrer | N44: 0 | O44: cadeau
A45: 44 | B45: James Carouge | E45: 2 | F45: 2 | I45: =IF(L45="Cadeau",0,C45*$S$2+D45*$S$3+E45*$S$4+F45*$S$5) -> 0 | J45: =I45/1.2 -> 0 | K45: 45248 | L45: Cadeau | N45: 0 | O45: conso Anniv
A46: 45 | I46: =IF(L46="Cadeau",0,C46*$S$2+D46*$S$3+E46*$S$4+F46*$S$5) -> 0 | J46: =I46/1.2 -> 0 | N46: 0
A47: 47 | B47: JOELLE DUBARBIER | D47: 18 | E47: 18 | I47: =IF(L47="Cadeau",0,C47*$S$2+D47*$S$3+E47*$S$4+F47*$S$5) -> 675 | J47: =I47/1.2 -> 562.5 | K47: 45260 | L47: Payé | M47: Livrer | N47: VIREMENT 12/2024 | O47: AVEC TRANSPORT | P47: 65
A48: 46 | B48: MARC WEBER | C48: 36 | I48: 612 | J48: 510 | K48: 31/11/2023 | O48: TRANSPORT 65TTC
A49: 48 | B49: AGENCE LAGUILLON | E49: 60 | I49: =IF(L49="Cadeau",0,C49*$S$2+D49*$S$3+E49*$S$4+F49*$S$5) -> 1110 | J49: =I49/1.2 -> 925 | K49: 45260 | L49: Payé | M49: Livrer | N49: Chèque 4 le 07/12 | O49: TRANSPORT GRATUIT | P49: 0
A50: 49 | B50: YOUNES CHAKROUN | C50: 12 | D50: 6 | E50: 6 | I50: =IF(L50="Cadeau",0,C50*$S$2+D50*$S$3+E50*$S$4+F50*$S$5) -> 429 | J50: =I50/1.2 -> 357.5 | K50: 45261 | L50: Payé | M50: Livrer | N50: VIREMENT LEO 09/12 | O50: CHEZ LEO
A51: 50 | B51: Stanislas BOUTMY | C51: 6 | E51: 6 | I51: =IF(L51="Cadeau",0,C51*$S$2+D51*$S$3+E51*$S$4+F51*$S$5) -> 213 | J51: =I51/1.2 -> 177.5 | K51: 45261 | L51: Payé | M51: Livrer | N51: VIREMENT LE 11/01 | O51: CHEZ LEO
A52: 51 | B52: Hugo Thomas | C52: 18 | E52: 12 | I52: =IF(L52="Cadeau",0,C52*$S$2+D52*$S$3+E52*$S$4+F52*$S$5) -> 528 | J52: =I52/1.2 -> 440 | K52: 45261 | L52: Payé | M52: Livrer | N52: 06/12 VIREMENT | O52: CHEZ LUI
A53: 52 | B53: PIERRE LEROUX | E53: 12 | I53: =IF(L53="Cadeau",0,C53*$S$2+D53*$S$3+E53*$S$4+F53*$S$5) -> 222 | J53: =I53/1.2 -> 185 | K53: 45261 | L53: Payé | M53: Livrer | O53: CHEZ LEO
A54: 53 | B54: ISABELLE ELISSALDE | C54: 18 | I54: =IF(L54="Cadeau",0,C54*$S$2+D54*$S$3+E54*$S$4+F54*$S$5) -> 306 | J54: =I54/1.2 -> 255 | K54: 45261 | L54: Payé | M54: Livrer | N54: 07/12 virement | O54: AVEC TRANSPORT | P54: 35
A55: 54 | B55: LEO FISHER | C55: 12 | I55: =IF(L55="Cadeau",0,C55*$S$2+D55*$S$3+E55*$S$4+F55*$S$5) -> 204 | J55: =I55/1.2 -> 170 | K55: 45261 | L55: Payé | M55: Livrer | O55: NOUS MEME
A56: 55 | B56: PATRICK CROCHET | D56: 27 | E56: 33 | I56: =IF(L56="Cadeau",0,C56*$S$2+D56*$S$3+E56*$S$4+F56*$S$5) -> 1123.5 | J56: =I56/1.2 -> 936.25 | K56: 45270 | L56: Payé | M56: Livrer | N56: 08/12 VIREMENT | O56: TRANPORT GRATUIT | P56: 0
A57: 56 | B57: James Carouge | C57: 4 | D57: 2 | E57: 9 | F57: 1 | I57: =IF(L57="Cadeau",0,C57*$S$2+D57*$S$3+E57*$S$4+F57*$S$5) -> 0 | J57: =I57/1.2 -> 0 | L57: Cadeau | M57: Livrer | O57: 1 SEL AIRBNB
A58: 57 | B58: JACKIE GUILLAUME | C58: 12 | I58: =IF(L58="Cadeau",0,C58*$S$2+D58*$S$3+E58*$S$4+F58*$S$5) -> 204 | J58: =I58/1.2 -> 170 | K58: 23/121/2023 | L58: Payé | M58: Livrer | N58: VIREMENT
A59: 58 | B59: Regis Paquin | E59: 12 | I59: =IF(L59="Cadeau",0,C59*$S$2+D59*$S$3+E59*$S$4+F59*$S$5) -> 222 | J59: =I59/1.2 -> 185 | K59: 45283 | L59: Payé | M59: Livrer | N59: VIREMENT
A60: 59
A61: 60 | I61: =IF(L61="Cadeau",0,C61*$S$2+D61*$S$3+E61*$S$4+F61*$S$5) -> 0 | J61: =I61/1.2 -> 0
A62: 61 | I62: =IF(L62="Cadeau",0,C62*$S$2+D62*$S$3+E62*$S$4+F62*$S$5) -> 0 | J62: =I62/1.2 -> 0
A63: 62 | I63: =IF(L63="Cadeau",0,C63*$S$2+D63*$S$3+E63*$S$4+F63*$S$5) -> 0 | J63: =I63/1.2 -> 0
A64: 63 | I64: =IF(L64="Cadeau",0,C64*$S$2+D64*$S$3+E64*$S$4+F64*$S$5) -> 0 | J64: =I64/1.2 -> 0
A65: 64 | I65: =IF(L65="Cadeau",0,C65*$S$2+D65*$S$3+E65*$S$4+F65*$S$5) -> 0 | J65: =I65/1.2 -> 0
A66: 65 | I66: =IF(L66="Cadeau",0,C66*$S$2+D66*$S$3+E66*$S$4+F66*$S$5) -> 0 | J66: =I66/1.2 -> 0
A67: 66 | I67: =IF(L67="Cadeau",0,C67*$S$2+D67*$S$3+E67*$S$4+F67*$S$5) -> 0 | J67: =I67/1.2 -> 0
A68: 67
A69: 68
A70: 69
A71: 70
A72: 71
A73: 72
A74: 73
A75: 74
A76: 75
A77: 76
A78: =IF(L78="CAdeau",0,MAX($A$2:A77)+1) -> 77
A79: =IF(L79="CAdeau",0,MAX($A$2:A78)+1) -> 78
A80: =IF(L80="CAdeau",0,MAX($A$2:A79)+1) -> 79
A81: =IF(L81="CAdeau",0,MAX($A$2:A80)+1) -> 80
A82: =IF(L82="CAdeau",0,MAX($A$2:A81)+1) -> 81
A83: =IF(L83="CAdeau",0,MAX($A$2:A82)+1) -> 82
A84: =IF(L84="CAdeau",0,MAX($A$2:A83)+1) -> 83
A85: =IF(L85="CAdeau",0,MAX($A$2:A84)+1) -> 84
A86: =IF(L86="CAdeau",0,MAX($A$2:A85)+1) -> 85
A87: =IF(L87="CAdeau",0,MAX($A$2:A86)+1) -> 86
A88: =IF(L88="CAdeau",0,MAX($A$2:A87)+1) -> 87
A89: =IF(L89="CAdeau",0,MAX($A$2:A88)+1) -> 88
... A161: =IF(L161="CAdeau",0,MAX($A$2:A160)+1) -> 159

Sheet Facturation 2023
E5: CHAMPAGNE CAROUGE CIREDDU
G8: Nom | I8: =VLOOKUP(C16,'Suivi Facturation 2023'!$A$1:$K$10002,2,FALSE) -> JOELLE DUBARBIER
G9: Adresse | I9: =VLOOKUP(I8,'Suivi Client'!C2:H2960,3,FALSE)
I10: =VLOOKUP(I8,'Suivi Client'!C2:H2960,4,FALSE) | J10: =VLOOKUP(I8,'Suivi Client'!C2:H2960,5,FALSE) -> SAINT JEAN DE LUZ
G12: Adresse e-mail | I12: =IF(VLOOKUP(I8,'Suivi Client'!$C$2:$H$2000,2,FALSE)=0,"",VLOOKUP(I8,'Suivi Client'!$C$2:$H$2000,2,FALSE))
M14: 23
A16: numéro de facturation | C16: 47
A17: Date de facturation | C17: 45260
A21: Contenance | B21: Designation | H21: Qté | I21: Prix unitaire TTC | K21: Montant TTC
A23: =IF(VLOOKUP($C$16,'Suivi Facturation 2023'!$A$2:$M$1096,3,FALSE)>0,"0,75","") | B23: =IF(VLOOKUP($C$16,'Suivi Facturation 2023'!$A$2:$M$978,3,FALSE)>0,"Bouteille CHAMPAGNE SELECTION","") | H23: =IF(VLOOKUP($C$16,'Suivi Facturation 2023'!$A$2:$M$1096,3,FALSE)>0,VLOOKUP($C$16,'Suivi Facturation 2023'!$A$2:$M$1096,3,FALSE),"") | I23: =IF(VLOOKUP($C$16,'Suivi Facturation 2023'!$A$2:$M$1096,3,FALSE)>0,'Suivi Facturation 2023'!S2,"") | K23: =IF(VLOOKUP($C$16,'Suivi Facturation 2023'!$A$2:$M$1096,3,FALSE)>0,I23*H23,"")
A24: =IF(VLOOKUP($C$16,'Suivi Facturation 2023'!$A$2:$M$1096,4,FALSE)>0,"0,75","") -> 0,75 | B24: =IF(VLOOKUP($C$16,'Suivi Facturation 2023'!$A$2:$M$978,4,FALSE)>0,"Bouteille CHAMPAGNE ROSE","") -> Bouteille CHAMPAGNE ROSE | H24: =IF(VLOOKUP($C$16,'Suivi Facturation 2023'!$A$2:$M$1096,4,FALSE)>0,VLOOKUP($C$16,'Suivi Facturation 2023'!$A$2:$M$1096,4,FALSE),"") -> 18 | I24: =IF(VLOOKUP($C$16,'Suivi Facturation 2023'!$A$2:$M$1096,4,FALSE)>0,'Suivi Facturation 2023'!S3,"") -> 19 | K24: =IF(VLOOKUP($C$16,'Suivi Facturation 2023'!$A$2:$M$1096,4,FALSE)>0,I24*H24,"") -> 342
A25: =IF(VLOOKUP($C$16,'Suivi Facturation 2023'!$A$2:$M$1096,5,FALSE)>0,"0,75","") -> 0,75 | B25: =IF(VLOOKUP($C$16,'Suivi Facturation 2023'!$A$2:$M$978,5,FALSE)>0,"Bouteille CHAMPAGNE BLANC DE BLANC","") -> Bouteille CHAMPAGNE BLANC DE BLANC | H25: =IF(VLOOKUP($C$16,'Suivi Facturation 2023'!$A$2:$M$1996,5,FALSE)>0,VLOOKUP($C$16,'Suivi Facturation 2023'!$A$2:$M$1996,5,FALSE),"") -> 18 | I25: =IF(VLOOKUP($C$16,'Suivi Facturation 2023'!$A$2:$M$1096,5,FALSE)>0,'Suivi Facturation 2023'!S4,"") -> 18.5 | K25: =IF(VLOOKUP($C$16,'Suivi Facturation 2023'!$A$2:$M$1096,5,FALSE)>0,I25*H25,"") -> 333
A26: =IF(VLOOKUP($C$16,'Suivi Facturation 2023'!$A$2:$M$1096,6,FALSE)>0,"0,75","") | B26: =IF(VLOOKUP($C$16,'Suivi Facturation 2023'!$A$2:$M$1096,6,FALSE)>0,"Bouteille CHAMPAGNE PRESTIGE","") | H26: =IF(VLOOKUP($C$16,'Suivi Facturation 2023'!$A$2:$M$1096,6,FALSE)>0,VLOOKUP($C$16,'Suivi Facturation 2023'!$A$2:$M$1096,6,FALSE),"") | I26: =IF(VLOOKUP($C$16,'Suivi Facturation 2023'!$A$2:$M$1096,6,FALSE)>0,'Suivi Facturation 2023'!S5,"") | K26: =IF(VLOOKUP($C$16,'Suivi Facturation 2023'!$A$2:$M$1096,6,FALSE)>0,I26*H26,"")
A27: =IF(VLOOKUP($C$16,'Suivi Facturation 2023'!$A$2:$M$1096,7,FALSE)>0,"1,5","") | B27: =IF(VLOOKUP($C$16,'Suivi Facturation 2023'!$A$2:$M$1096,7,FALSE)>0,"MAGNUM SELECTION","") | I27: =IF(VLOOKUP($C$16,'Suivi Facturation 2023'!$A$2:$M$1096,7,FALSE)>0,'Suivi Facturation 2023'!S6,"") | K27: =IF(VLOOKUP($C$16,'Suivi Facturation 2023'!$A$2:$M$1096,7,FALSE)>0,I27*H27,"")
B28: =IF(VLOOKUP($C$16,'Suivi Facturation 2023'!$A$2:$P$1978,16,FALSE)>0,"PRIX LIVRAISON","") -> PRIX LIVRAISON | K28: =IF(VLOOKUP($C$16,'Suivi Facturation 2023'!$A$2:$P$1978,16,FALSE)>0,VLOOKUP($C$16,'Suivi Facturation 2023'!$A$2:$P$1978,16,FALSE),"") -> 65
K37: Total HT | L37: =SUM(K23:L30)-L38 -> 616.66667
K38: TVA (20%) | L38: =IFERROR(SUM(K23:L29)-SUM(K23:L29)/1.2,"") -> 123.33333
K40: Total TTC | L40: =SUM(K23:L30) -> 740
A42: Toute somme impayée à son échéance produira, de plein droit et sans mise en demeure, un intérêt égal à 1,5 fois le taux d'intérêt légal par mois de retard. Nos conditions de vente ne prévoient pas d'escompte pour paiement anticipé. Coordonnées bancaires Titulaire du compte : JAMES CAROUGE IBAN FR76 1020 6000 4848 3510 3712 067 BIC AGRIFRPP802
A54: CHAMPAGNE CAROUGE CIREDDU 6 rue de l'eglise 51190 FLAVIGNY Tel : 06 77 95 90 62 SIRET 843 516 642 00017 N° TVA intracommunautaire FR67 843 516 642

Sheet Facturation 2023 HT
E5: CHAMPAGNE CAROUGE CIREDDU
G8: Nom | I8: =VLOOKUP(C16,'Suivi Facturation 2023'!$A$1:$K$10002,2,FALSE)
G9: Adresse | I9: =VLOOKUP(I8,'Suivi Client'!C2:H2960,3,FALSE) -> #N/A
I10: =VLOOKUP(I8,'Suivi Client'!C2:H2960,4,FALSE) -> #N/A | J10: =VLOOKUP(I8,'Suivi Client'!C2:H2960,5,FALSE) -> #N/A
G12: Adresse e-mail | I12: =IF(VLOOKUP(I8,'Suivi Client'!$C$2:$H$2000,2,FALSE)=0,"",VLOOKUP(I8,'Suivi Client'!$C$2:$H$2000,2,FALSE)) -> #N/A
A16: numéro de facturation | C16: 59
A17: Date de facturation | C17: 45613
A21: Contenance | B21: Designation | H21: Qté | I21: Prix unitaire HT | K21: Montant HT
A23: =IF(VLOOKUP($C$16,'Suivi Facturation 2023'!$A$2:$M$1096,3,FALSE)>0,"0,75","") | B23: =IF(VLOOKUP($C$16,'Suivi Facturation 2023'!$A$2:$M$978,3,FALSE)>0,"Bouteille CHAMPAGNE SELECTION","") | H23: =IF(VLOOKUP($C$16,'Suivi Facturation 2023'!$A$2:$M$1096,3,FALSE)>0,VLOOKUP($C$16,'Suivi Facturation 2023'!$A$2:$M$1096,3,FALSE),"") | I23: =IF(VLOOKUP($C$16,'Suivi Facturation 2023'!$A$2:$M$1096,3,FALSE)>0,'Suivi Facturation 2023'!S2,"") | K23: =IF(VLOOKUP($C$16,'Suivi Facturation 2023'!$A$2:$M$1096,3,FALSE)>0,I23*H23,"")
A24: =IF(VLOOKUP($C$16,'Suivi Facturation 2023'!$A$2:$M$1096,4,FALSE)>0,"0,75","") | B24: =IF(VLOOKUP($C$16,'Suivi Facturation 2023'!$A$2:$M$978,4,FALSE)>0,"Bouteille CHAMPAGNE ROSE","") | H24: =IF(VLOOKUP($C$16,'Suivi Facturation 2023'!$A$2:$M$1096,4,FALSE)>0,VLOOKUP($C$16,'Suivi Facturation 2023'!$A$2:$M$1096,4,FALSE),"") | I24: =IF(VLOOKUP($C$16,'Suivi Facturation 2023'!$A$2:$M$1096,4,FALSE)>0,'Suivi Facturation 2023'!S3,"") | K24: =IF(VLOOKUP($C$16,'Suivi Facturation 2023'!$A$2:$M$1096,4,FALSE)>0,I24*H24,"")
A25: =IF(VLOOKUP($C$16,'Suivi Facturation 2023'!$A$2:$M$1096,5,FALSE)>0,"0,75","") | B25: =IF(VLOOKUP($C$16,'Suivi Facturation 2023'!$A$2:$M$978,5,FALSE)>0,"Bouteille CHAMPAGNE BLANC DE BLANC","") | H25: =IF(VLOOKUP($C$16,'Suivi Facturation 2023'!$A$2:$M$1996,5,FALSE)>0,VLOOKUP($C$16,'Suivi Facturation 2023'!$A$2:$M$1996,5,FALSE),"") | I25: =IF(VLOOKUP($C$16,'Suivi Facturation 2023'!$A$2:$M$1096,5,FALSE)>0,'Suivi Facturation 2023'!S4,"") | K25: =IF(VLOOKUP($C$16,'Suivi Facturation 2023'!$A$2:$M$1096,5,FALSE)>0,I25*H25,"")
A26: =IF(VLOOKUP($C$16,'Suivi Facturation 2023'!$A$2:$M$1096,6,FALSE)>0,"0,75","") | B26: =IF(VLOOKUP($C$16,'Suivi Facturation 2023'!$A$2:$M$1096,6,FALSE)>0,"Bouteille CHAMPAGNE PRESTIGE","") | H26: =IF(VLOOKUP($C$16,'Suivi Facturation 2023'!$A$2:$M$1096,6,FALSE)>0,VLOOKUP($C$16,'Suivi Facturation 2023'!$A$2:$M$1096,6,FALSE),"") | I26: =IF(VLOOKUP($C$16,'Suivi Facturation 2023'!$A$2:$M$1096,6,FALSE)>0,'Suivi Facturation 2023'!S5,"") | K26: =IF(VLOOKUP($C$16,'Suivi Facturation 2023'!$A$2:$M$1096,6,FALSE)>0,I26*H26,"")
A27: =IF(VLOOKUP($C$16,'Suivi Facturation 2023'!$A$2:$M$1096,7,FALSE)>0,"1,5","") | B27: =IF(VLOOKUP($C$16,'Suivi Facturation 2023'!$A$2:$M$1096,7,FALSE)>0,"MAGNUM SELECTION","") | I27: =IF(VLOOKUP($C$16,'Suivi Facturation 2023'!$A$2:$M$1096,7,FALSE)>0,'Suivi Facturation 2023'!S6,"") | K27: =IF(VLOOKUP($C$16,'Suivi Facturation 2023'!$A$2:$M$1096,7,FALSE)>0,I27*H27,"")
B28: =IF(VLOOKUP($C$16,'Suivi Facturation 2023'!$A$2:$P$1978,14,FALSE)>0,"PRIX LIVRAISON","") | K28: =IF(VLOOKUP($C$16,'Suivi Facturation 2023'!$A$2:$P$1978,14,FALSE)>0,VLOOKUP($C$16,'Suivi Facturation 2023'!$A$2:$P$1978,14,FALSE),"")
K40: Total HT | L40: =SUM(K23:L30) -> 0
A42: Toute somme impayée à son échéance produira, de plein droit et sans mise en demeure, un intérêt égal à 1,5 fois le taux d'intérêt légal par mois de retard. Nos conditions de vente ne prévoient pas d'escompte pour paiement anticipé. Coordonnées bancaires Titulaire du compte : JAMES CAROUGE IBAN FR76 1020 6000 4848 3510 3712 067 BIC AGRIFRPP802
A54: CHAMPAGNE CAROUGE CIREDDU 6 rue de l'eglise 51190 FLAVIGNY Tel : 06 77 95 90 62 SIRET 843 516 642 00017 N° TVA intracommunautaire FR67 843 516 642

Sheet Suivi Facturation 2022
A1: 19/ | B1: Nom Client | C1: NB Selection | D1: NB Rosé | E1: Nb blanc de blan | F1: Nb Prestige | G1: Magnum Selection | I1: Montant TTC bouteilles | J1: Montant HT | K1: Date de facturation | L1: Etat paiement | M1: Etat Commande | N1: paiement | O1: commentaire | P1: Prix Transport TTC | R1: Statistiques | S1: Prix unitaire TTC | T1: =S2/1.2 -> 14.166667
A2: 1 | B2: CONSO | C2: 3 | D2: 1 | E2: 2 | F2: 3 | I2: =IF(L2="Cadeau",0,C2*$S$2+D2*$S$3+E2*$S$4+F2*$S$5) -> 0 | J2: =I2/1.2 -> 0 | K2: 44576 | L2: Cadeau | M2: Livrer | R2: Sélection | S2: 17
A3: 2 | B3: Gintrand Guillaume | E3: 18 | I3: =IF(L3="Cadeau",0,C3*$S$2+D3*$S$3+E3*$S$4+F3*$S$5) -> 333 | J3: =I3/1.2 -> 277.5 | K3: 44579 | L3: Payé | M3: Livrer | N3: VIREMENT 09/02 | O3: SAUVEGARDE EPERNAY | R3: Rosé | S3: 19
A4: 3 | B4: Philémon Parent | C4: 6 | E4: 2 | I4: =IF(L4="Cadeau",0,C4*$S$2+D4*$S$3+E4*$S$4+F4*$S$5) -> 139 | J4: =I4/1.2 -> 115.83333 | K4: 44696 | L4: Payé | M4: Habillé | N4: CHEQUE LE 05/07 | O4: LIVRE GERMAINE PAR JAMES | R4: Blanc de blanc | S4: 18.5
A5: 4 | B5: docteur RENZO MANFREDI | C5: 6 | E5: 12 | I5: =IF(L5="Cadeau",0,C5*$S$2+D5*$S$3+E5*$S$4+F5*$S$5) -> 324 | J5: =I5/1.2 -> 270 | K5: 44630 | L5: Payé | M5: Livrer | N5: CHEQUE LE 05/07 | O5: DEPOT REGIS | R5: Prestige | S5: 27
A6: 5 | B6: ZUPPING | C6: 4 | I6: =IF(L6="Cadeau",0,C6*$S$2+D6*$S$3+E6*$S$4+F6*$S$5) -> 68 | J6: =I6/1.2 -> 56.666667 | K6: 44578 | L6: Payé | M6: Livrer | N6: ZUPPING VIREMENT | O6: DEPOT DUBARBIER DEJA SORTIE EN DRM | R6: Magnum Brut Selection | S6: 38
A7: 6 | B7: SEJOURNE BASTIEN | C7: 1 | D7: 1 | E7: 3 | I7: =IF(L7="Cadeau",0,C7*$S$2+D7*$S$3+E7*$S$4+F7*$S$5) -> 91.5 | J7: =I7/1.2 -> 76.25 | K7: 44638 | L7: Payé | M7: Livrer | N7: VIREMENT | O7: REGLEE 21/11/2022 | R7: Nb bouteilles vendues | S7: =SUM(C2:D1201) -> 990
A8: =IF(L8="CAdeau",0,MAX($A$2:A7)+1) -> 7 | B8: DE MAUPEOU Thaîs | C8: 2 | I8: =IF(L8="Cadeau",0,C8*$S$2+D8*$S$3+E8*$S$4+F8*$S$5) -> 34 | J8: =I8/1.2 -> 28.333333 | K8: 44640 | L8: Payé | M8: Livrer | N8: VIREMENT | O8: SORTIE DEPOT LEO
A9: =IF(L9="CAdeau",0,MAX($A$2:A8)+1) -> 8 | B9: Locquet Jeremie | E9: 6 | I9: =IF(L9="Cadeau",0,C9*$S$2+D9*$S$3+E9*$S$4+F9*$S$5) -> 111 | J9: =I9/1.2 -> 92.5 | K9: 44639 | L9: Payé | M9: Livrer | N9: VIRE 10/2022 | O9: SORTIE DEPOT LEO | R9: Chiffre d'affaire | S9: =SUM(I2:I1216) -> 19625
A10: =IF(L10="CAdeau",0,MAX($A$2:A9)+1) -> 9 | B10: Eric Soulhac | D10: 3 | E10: 3 | I10: =IF(L10="Cadeau",0,C10*$S$2+D10*$S$3+E10*$S$4+F10*$S$5) -> 112.5 | J10: =I10/1.2 -> 93.75 | K10: 44643 | L10: Payé | M10: Livrer | N10: VIREMENT | O10: SORTIE DEPOT ST VALLIER | P10: PRIX 2021
A11: =IF(L11="CAdeau",0,MAX($A$2:A10)+1) -> 10 | B11: JAUNET CEDRIC | D11: 6 | E11: 6 | K11: 44654 | L11: Payé | M11: Livrer | N11: VIREMENT | O11: SORTIE MAISON
A12: =IF(L12="CAdeau",0,MAX($A$2:A11)+1) -> 11 | B12: Léo Carouge | C12: 12 | I12: =IF(L12="Cadeau",0,C12*$S$2+D12*$S$3+E12*$S$4+F12*$S$5) -> 204 | J12: =I12/1.2 -> 170 | K12: 44658 | L12: En attente de paiement | M12: Livrer | N12: LEO | O12: DEPOT LEO
A13: =IF(L13="CAdeau",0,MAX($A$2:A12)+1) -> 0 | B13: CONSO | C13: 2 | I13: =IF(L13="Cadeau",0,C13*$S$2+D13*$S$3+E13*$S$4+F13*$S$5) -> 0 | J13: =I13/1.2 -> 0 | K13: 44667 | L13: Cadeau | M13: Livrer | N13: 0 | O13: NINO
A14: =IF(L14="CAdeau",0,MAX($A$2:A13)+1) -> 12 | B14: DELFINI MARIE-SOPHIE | C14: 40 | I14: =IF(L14="Cadeau",0,C14*$S$2+D14*$S$3+E14*$S$4+F14*$S$5) -> 680 | J14: =I14/1.2 -> 566.66667 | K14: 44679 | L14: Payé | M14: Livrer | N14: Virement | O14: MARIAGE PARIS | P14: REMISE 1EURO BOUTEILLE
A15: =IF(L15="CAdeau",0,MAX($A$2:A14)+1) -> 13 | B15: ANNE KAES | C15: 6 | I15: =IF(L15="Cadeau",0,C15*$S$2+D15*$S$3+E15*$S$4+F15*$S$5) -> 102 | J15: =I15/1.2 -> 85 | K15: 44677 | L15: Payé | M15: Livrer | N15: VIREMENT | O15: SORTIE DEPOT ISA | P15: PRIX 2021
A16: =IF(L16="CAdeau",0,MAX($A$2:A15)+1) -> 14 | B16: Jac/dan Bouilot | C16: 18 | D16: 12 | I16: =IF(L16="Cadeau",0,C16*$S$2+D16*$S$3+E16*$S$4+F16*$S$5) -> 534 | J16: =I16/1.2 -> 445 | K16: 44698 | L16: Payé | M16: Livrer | N16: VIREMENT | O16: sortie depot st vallier | P16: prix 2021
A17: =IF(L17="CAdeau",0,MAX($A$2:A16)+1) -> 15 | B17: Besson Eleonore | C17: 1 | D17: 1 | I17: =IF(L17="Cadeau",0,C17*$S$2+D17*$S$3+E17*$S$4+F17*$S$5) -> 36 | J17: =I17/1.2 -> 30 | K17: 44701 | L17: Payé | N17: VIREMENT | O17: Sortie dépôt leo
A18: =IF(L18="CAdeau",0,MAX($A$2:A17)+1) -> 16 | B18: Dumant Benedicte | C18: 1 | D18: 1 | I18: =IF(L18="Cadeau",0,C18*$S$2+D18*$S$3+E18*$S$4+F18*$S$5) -> 36 | J18: =I18/1.2 -> 30 | K18: 44701 | L18: Payé | N18: LEO | O18: Sortie dépôt leo
A19: =IF(L19="CAdeau",0,MAX($A$2:A18)+1) -> 17 | B19: Léo Carouge | C19: 12 | I19: =IF(L19="Cadeau",0,C19*$S$2+D19*$S$3+E19*$S$4+F19*$S$5) -> 204 | J19: =I19/1.2 -> 170 | K19: 44687 | L19: En attente de paiement | M19: Livrer | N19: DEPOT | O19: depot leo
A20: =IF(L20="CAdeau",0,MAX($A$2:A19)+1) -> 18 | B20: Gintrand Simon | E20: 24 | I20: =IF(L20="Cadeau",0,C20*$S$2+D20*$S$3+E20*$S$4+F20*$S$5) -> 444 | J20: =I20/1.2 -> 370 | K20: 44722 | L20: Payé | M20: Livrer | N20: VIREMENT
A21: =IF(L21="CAdeau",0,MAX($A$2:A20)+1) -> 0 | B21: Nino Carouge | C21: 1 | D21: 1 | E21: 1 | F21: 1 | I21: =IF(L21="Cadeau",0,C21*$S$2+D21*$S$3+E21*$S$4+F21*$S$5) -> 0 | J21: =I21/1.2 -> 0 | L21: Cadeau | M21: Habillé | N21: 0 | O21: DEGUSTATION SUISSE | P21: PAR NINO
A22: =IF(L22="CAdeau",0,MAX($A$2:A21)+1) -> 19 | B22: GOUBE MARIE CAPUCINE | C22: 156 | H22: 156 | I22: =IF(L22="Cadeau",0,C22*$S$2+D22*$S$3+E22*$S$4+F22*$S$5) -> 2652 | J22: =I22/1.2 -> 2210 | K22: 44774 | L22: Payé | M22: Livrer | N22: FACTURE EN AOUT | O22: mariage avec remise | P22: nous
A23: =IF(L23="CAdeau",0,MAX($A$2:A22)+1) -> 20 | B23: Barnerias Philippine | C23: 276 | H23: 276 | I23: =IF(L23="Cadeau",0,C23*$S$2+D23*$S$3+E23*$S$4+F23*$S$5) -> 4692 | J23: =I23/1.2 -> 3910 | K23: 44774 | M23: Livrer | N23: VIREMENT | O23: mariage avec remise | P23: nous
A24: =IF(L24="CAdeau",0,MAX($A$2:A23)+1) -> 21 | B24: Aymeric Chataigner | C24: 12 | E24: 18 | I24: =IF(L24="Cadeau",0,C24*$S$2+D24*$S$3+E24*$S$4+F24*$S$5) -> 537 | J24: =I24/1.2 -> 447.5 | K24: 44725 | L24: Payé | M24: Livrer | N24: VIREMENT | P24: ActiverS
A25: =IF(L25="CAdeau",0,MAX($A$2:A24)+1) -> 22 | B25: CLAVERY ISABELLE | C25: 6 | I25: =IF(L25="Cadeau",0,C25*$S$2+D25*$S$3+E25*$S$4+F25*$S$5) -> 102 | J25: =I25/1.2 -> 85 | K25: 44727 | L25: Payé | M25: Livrer | N25: CHEQUE LE 05/07 | P25: PRIX 2021
A26: =IF(L26="CAdeau",0,MAX($A$2:A25)+1) -> 23 | B26: BERTHOLON SARAH | E26: 1 | F26: 1 | I26: =IF(L26="Cadeau",0,C26*$S$2+D26*$S$3+E26*$S$4+F26*$S$5) -> 45.5 | J26: =I26/1.2 -> 37.916667 | K26: 44725 | L26: Payé | M26: Livrer | N26: VIREMENT | P26: NINO
A27: =IF(L27="CAdeau",0,MAX($A$2:A26)+1) -> 24 | B27: Hugo Thomas | C27: 12 | I27: =IF(L27="Cadeau",0,C27*$S$2+D27*$S$3+E27*$S$4+F27*$S$5) -> 204 | J27: =I27/1.2 -> 170 | K27: 44732 | L27: Payé | N27: VIREMENT | P27: Depot LEO
A28: =IF(L28="CAdeau",0,MAX($A$2:A27)+1) -> 25 | B28: Stanislas BOUTMY | D28: 18 | I28: =IF(L28="Cadeau",0,C28*$S$2+D28*$S$3+E28*$S$4+F28*$S$5) -> 342 | J28: =I28/1.2 -> 285 | L28: Payé | N28: VIREMENT | P28: DEPOT LEO PARIS
A29: =IF(L29="CAdeau",0,MAX($A$2:A28)+1) -> 26 | B29: Pichou Louise | C29: 12 | I29: =IF(L29="Cadeau",0,C29*$S$2+D29*$S$3+E29*$S$4+F29*$S$5) -> 204 | J29: =I29/1.2 -> 170 | L29: Payé | M29: Livrer | N29: VIREMENT 12/2022 | P29: DEPOT LEO BORDEAUX
A30: =IF(L30="CAdeau",0,MAX($A$2:A29)+1) -> 27 | B30: PAOLA ZICCA | C30: 6 | E30: 6 | I30: =IF(L30="Cadeau",0,C30*$S$2+D30*$S$3+E30*$S$4+F30*$S$5) -> 213 | J30: =I30/1.2 -> 177.5 | K30: 44758 | L30: Payé | M30: Livrer | N30: ESPECE | P30: SARDAIGNE
A31: =IF(L31="CAdeau",0,MAX($A$2:A30)+1) -> 28 | I31: =IF(L31="Cadeau",0,C31*$S$2+D31*$S$3+E31*$S$4+F31*$S$5) -> 0 | J31: =I31/1.2 -> 0 | L31: Payé
A32: =IF(L32="CAdeau",0,MAX($A$2:A31)+1) -> 0 | B32: James Carouge | C32: 18 | D32: 12 | E32: 30 | I32: =IF(L32="Cadeau",0,C32*$S$2+D32*$S$3+E32*$S$4+F32*$S$5) -> 0 | J32: =I32/1.2 -> 0 | K32: 44758 | L32: Cadeau | N32: CONSO DEPOT | O32: DSA SARDAIGNE | P32: DEGUST ET CONSO SARDAIGNE
A33: =IF(L33="CAdeau",0,MAX($A$2:A32)+1) -> 29 | B33: Garval /Amaral | E33: 12 | I33: =IF(L33="Cadeau",0,C33*$S$2+D33*$S$3+E33*$S$4+F33*$S$5) -> 222 | J33: =I33/1.2 -> 185 | K33: 44764 | L33: Payé | M33: Livrer | N33: ESPECE | P33: REIMS
B34: Philippe Gintrand | C34: 12 | D34: 14 | E34: 10 | I34: =IF(L34="Cadeau",0,C34*$S$2+D34*$S$3+E34*$S$4+F34*$S$5) -> 655 | J34: =I34/1.2 -> 545.83333 | K34: 44758 | L34: En attente de paiement | M34: Livrer | N34: DEPOT | P34: DEPOT ST VALLIER
A35: =IF(L35="CAdeau",0,MAX($A$2:A34)+1) -> 30 | B35: DELFINI MARIE-SOPHIE | C35: 132 | H35: 132 | I35: =IF(L35="Cadeau",0,C35*$S$2+D35*$S$3+E35*$S$4+F35*$S$5) -> 2244 | J35: =I35/1.2 -> 1870 | K35: 44774 | L35: Payé | M35: Habillé | N35: VIREMENT | O35: MARIAGE CORSE AVEC REMISE | P35: LIVRAISON CORSE
A36: =IF(L36="CAdeau",0,MAX($A$2:A35)+1) -> 31 | B36: AGENCE LAGUILLON | E36: 24 | I36: =IF(L36="Cadeau",0,C36*$S$2+D36*$S$3+E36*$S$4+F36*$S$5) -> 444 | J36: =I36/1.2 -> 370 | K36: 44769 | L36: Payé | M36: Livrer | N36: 8/11 CHEQUE 503,69 | P36: FRAIS LIVRAISON
A37: =IF(L37="CAdeau",0,MAX($A$2:A36)+1) -> 32 | B37: Philippe Gintrand | C37: 6 | E37: 3 | I37: =IF(L37="Cadeau",0,C37*$S$2+D37*$S$3+E37*$S$4+F37*$S$5) -> 157.5 | J37: =I37/1.2 -> 131.25 | K37: 44769 | L37: Payé | M37: Livrer | N37: VIREMENT | P37: SUR DEPOT ST VALLIER
A38: =IF(L38="CAdeau",0,MAX($A$2:A37)+1) -> 0 | B38: Nino Carouge | C38: 4 | I38: =IF(L38="Cadeau",0,C38*$S$2+D38*$S$3+E38*$S$4+F38*$S$5) -> 0 | J38: =I38/1.2 -> 0 | K38: 44837 | L38: Cadeau | O38: VENDANGEURS | P38: CONSO DEGUST
A39: =IF(L39="CAdeau",0,MAX($A$2:A38)+1) -> 0 | B39: CADEAU | C39: 6 | I39: =IF(L39="Cadeau",0,C39*$S$2+D39*$S$3+E39*$S$4+F39*$S$5) -> 0 | J39: =I39/1.2 -> 0 | K39: 44814 | L39: Cadeau
A40: =IF(L40="CAdeau",0,MAX($A$2:A39)+1) -> 33 | B40: CLAVERY ISABELLE | D40: 12 | I40: =IF(L40="Cadeau",0,C40*$S$2+D40*$S$3+E40*$S$4+F40*$S$5) -> 228 | J40: =I40/1.2 -> 190 | K40: 44838 | L40: Payé | N40: ESPECE | O40: SUR DEPOT BORDEAUX 2021
A41: K | B41: NICOLA CIREDDU | C41: 5 | D41: 4 | E41: 11 | F41: 8 | I41: =IF(L41="Cadeau",0,C41*$S$2+D41*$S$3+E41*$S$4+F41*$S$5) -> 580.5 | J41: =I41/1.2 -> 483.75 | K41: 44845 | L41: Payé | N41: Espèce | O41: LIVRAISON SARDAIGNE | P41: 2SEL 2BLC 2PRES 2ROSE
A42: =IF(L42="CAdeau",0,MAX($A$2:A41)+1) -> 34 | B42: VITTORIA | E42: 2 | I42: =IF(L42="Cadeau",0,C42*$S$2+D42*$S$3+E42*$S$4+F42*$S$5) -> 37 | J42: =I42/1.2 -> 30.833333 | K42: 44845 | L42: Payé | N42: Espèce | O42: LIVRAISON SARDAIGNE
A43: =IF(L43="CAdeau",0,MAX($A$2:A42)+1) -> 0 | B43: James Carouge | C43: 7 | D43: 2 | E43: 4 | I43: =IF(L43="Cadeau",0,C43*$S$2+D43*$S$3+E43*$S$4+F43*$S$5) -> 0 | J43: =I43/1.2 -> 0 | K43: 44858 | L43: Cadeau | O43: SARDAIGNE | P43: CONSO
A44: =IF(L44="CAdeau",0,MAX($A$2:A43)+1) -> 35 | B44: PAOLA ZICCA | C44: 6 | E44: 12 | I44: =IF(L44="Cadeau",0,C44*$S$2+D44*$S$3+E44*$S$4+F44*$S$5) -> 324 | J44: =I44/1.2 -> 270 | K44: 44857 | L44: Payé | N44: Espèce | O44: SARDAIGNE
A45: 5 | B45: DEBORA CIREDDU | D45: 2 | E45: 2 | F45: 2 | I45: =IF(L45="Cadeau",0,C45*$S$2+D45*$S$3+E45*$S$4+F45*$S$5) -> 129 | J45: =I45/1.2 -> 107.5 | K45: 44864 | L45: Payé | N45: ESPECE | O45: SARDAIGNE
I46: =IF(L46="Cadeau",0,C46*$S$2+D46*$S$3+E46*$S$4+F46*$S$5) -> 0 | J46: =I46/1.2 -> 0
A47: =IF(L47="CAdeau",0,MAX($A$2:A45)+1) -> 36 | B47: SERGIO ZICCA | C47: 2 | D47: 2 | E47: 5 | I47: =IF(L47="Cadeau",0,C47*$S$2+D47*$S$3+E47*$S$4+F47*$S$5) -> 164.5 | J47: =I47/1.2 -> 137.08333 | K47: 44865 | N47: ESPECE | O47: SARDAIGNE
A48: =IF(L48="CAdeau",0,MAX($A$2:A47)+1) -> 0 | B48: James Carouge | C48: 24 | D48: 24 | E48: 36 | F48: 12 | I48: =IF(L48="Cadeau",0,C48*$S$2+D48*$S$3+E48*$S$4+F48*$S$5) -> 0 | J48: =I48/1.2 -> 0 | K48: 44845 | L48: Cadeau | N48: DSA DEPOT DEGUST | O48: SARDAIGNE
A49: =IF(L49="CAdeau",0,MAX($A$2:A48)+1) -> 0 | B49: LAURA PICCONI | C49: 6 | D49: 12 | G49: 15 | I49: =IF(L49="Cadeau",0,C49*$S$2+D49*$S$3+E49*$S$4+F49*$S$5) -> 0 | J49: =I49/1.2 -> 0 | K49: 44849 | L49: Cadeau | N49: CADEAU | O49: 15 MAG 6 SEL 12 ROSE | P49: Mariage
A50: =IF(L50="CAdeau",0,MAX($A$2:A49)+1) -> 37 | B50: cedric jaunet | E50: 12 | I50: =IF(L50="Cadeau",0,C50*$S$2+D50*$S$3+E50*$S$4+F50*$S$5) -> 222 | J50: =I50/1.2 -> 185 | K50: 44885 | M50: Livrer | N50: VIREMENT 12/2022
A51: =IF(L51="CAdeau",0,MAX($A$2:A50)+1) -> 38 | B51: Regis Paquin | C51: 12 | E51: 6 | I51: =IF(L51="Cadeau",0,C51*$S$2+D51*$S$3+E51*$S$4+F51*$S$5) -> 315 | J51: =I51/1.2 -> 262.5 | K51: 44885 | M51: Livrer | N51: VIREMEN T | O51: SUR DEPOT 2021
A52: =IF(L52="CAdeau",0,MAX($A$2:A51)+1) -> 39 | B52: Léo Carouge | E52: 0 | I52: =IF(L52="Cadeau",0,C52*$S$2+D52*$S$3+E52*$S$4+F52*$S$5) -> 0 | J52: =I52/1.2 -> 0 | K52: 44886 | M52: Livrer
A53: =IF(L53="CAdeau",0,MAX($A$2:A52)+1) -> 0 | B53: Nino Carouge | C53: 2 | I53: =IF(L53="Cadeau",0,C53*$S$2+D53*$S$3+E53*$S$4+F53*$S$5) -> 0 | J53: =I53/1.2 -> 0 | K53: 44889 | L53: Cadeau | O53: DEGUSTATION
A54: =IF(L54="CAdeau",0,MAX($A$2:A53)+1) -> 40 | B54: Regis Paquin | E54: 12 | I54: =IF(L54="Cadeau",0,C54*$S$2+D54*$S$3+E54*$S$4+F54*$S$5) -> 222 | J54: =I54/1.2 -> 185 | K54: 44889 | M54: Livrer | N54: VIREMENT LE 27/02
A55: =IF(L55="CAdeau",0,MAX($A$2:A54)+1) -> 41 | B55: Stanislas BOUTMY | C55: 6 | I55: =IF(L55="Cadeau",0,C55*$S$2+D55*$S$3+E55*$S$4+F55*$S$5) -> 102 | J55: =I55/1.2 -> 85 | K55: 44891 | M55: Livrer | O55: CAve LEo A Regler
A56: =IF(L56="CAdeau",0,MAX($A$2:A55)+1) -> 42 | B56: Léo Carouge | G56: 0 | I56: =IF(L56="Cadeau",0,C56*$S$2+D56*$S$3+E56*$S$4+F56*$S$5+G56*$S$6) -> 0 | J56: =I56/1.2 -> 0
A57: =IF(L57="CAdeau",0,MAX($A$2:A56)+1) -> 43 | B57: Emilien Rouable RESTAURANT INATTENDU | E57: 30 | F57: 12 | I57: =IF(L57="Cadeau",0,C57*$S$2+D57*$S$3+E57*$S$4+F57*$S$5) -> 879 | J57: =I57/1.2 -> 732.5 | K57: 44897 | M57: Livrer | N57: VIREMENT 28/02/
A58: =IF(L58="CAdeau",0,MAX($A$2:A57)+1) -> 44 | B58: ZUPPING | C58: 7 | I58: =IF(L58="Cadeau",0,C58*$S$2+D58*$S$3+E58*$S$4+F58*$S$5) -> 119 | J58: =I58/1.2 -> 99.166667 | K58: 44900 | L58: Payé | M58: Livrer | N58: VIREMENT 112 | O58: DEPOT DUBARBIER
A59: =IF(L59="CAdeau",0,MAX($A$2:A58)+1) -> 45 | B59: Agnès marrié | C59: 6 | I59: =IF(L59="Cadeau",0,C59*$S$2+D59*$S$3+E59*$S$4+F59*$S$5) -> 102 | J59: =I59/1.2 -> 85 | K59: 44919 | L59: Payé | N59: VIREMENT | O59: DEPOT LEO PARIS
A60: =IF(L60="CAdeau",0,MAX($A$2:A59)+1) -> 46 | B60: cireddu camille | C60: 2 | I60: =IF(L60="Cadeau",0,C60*$S$2+D60*$S$3+E60*$S$4+F60*$S$5) -> 34 | J60: =I60/1.2 -> 28.333333 | K60: 44923 | L60: Payé | M60: Livrer | N60: ESPECE | O60: MAISON
B61: JACKIE Guillaume | C61: 2 | I61: 0 | J61: 0 | K61: 22/121/2022 | L61: Cadeau | N61: CADEAU | O61: MAISON
A62: =IF(L62="CAdeau",0,MAX($A$2:A61)+1) -> 0 | B62: Nino Carouge | C62: 1 | D62: 1 | E62: 1 | K62: 45291 | L62: Cadeau | N62: CADEAU | O62: KALINUR 1 SEL 1 ROSE
A63: =IF(L63="CAdeau",0,MAX($A$2:A62)+1) -> 47
A64: =IF(L64="CAdeau",0,MAX($A$2:A63)+1) -> 48
A65: =IF(L65="CAdeau",0,MAX($A$2:A64)+1) -> 49
A66: =IF(L66="CAdeau",0,MAX($A$2:A65)+1) -> 50
A67: =IF(L67="CAdeau",0,MAX($A$2:A66)+1) -> 51
A68: =IF(L68="CAdeau",0,MAX($A$2:A67)+1) -> 52
A69: =IF(L69="CAdeau",0,MAX($A$2:A68)+1) -> 53
A70: =IF(L70="CAdeau",0,MAX($A$2:A69)+1) -> 54
A71: =IF(L71="CAdeau",0,MAX($A$2:A70)+1) -> 55
A72: =IF(L72="CAdeau",0,MAX($A$2:A71)+1) -> 56
A73: =IF(L73="CAdeau",0,MAX($A$2:A72)+1) -> 57
A74: =IF(L74="CAdeau",0,MAX($A$2:A73)+1) -> 58
... A141: =IF(L141="CAdeau",0,MAX($A$2:A140)+1) -> 124
A142: =IF(L142="CAdeau",0,MAX($A$2:A141)+1) -> 125 | I142: =IF(L142="Cadeau",0,C142*$S$2+D142*$S$3+E142*$S$4+F142*$S$5) -> 0
A143: =IF(L143="CAdeau",0,MAX($A$2:A142)+1) -> 126 | I143: =IF(L143="Cadeau",0,C143*$S$2+D143*$S$3+E143*$S$4+F143*$S$5) -> 0
A144: =IF(L144="CAdeau",0,MAX($A$2:A143)+1) -> 127 | I144: =IF(L144="Cadeau",0,C144*$S$2+D144*$S$3+E144*$S$4+F144*$S$5) -> 0
A145: =IF(L145="CAdeau",0,MAX($A$2:A144)+1) -> 128 | I145: =IF(L145="Cadeau",0,C145*$S$2+D145*$S$3+E145*$S$4+F145*$S$5) -> 0
A146: =IF(L146="CAdeau",0,MAX($A$2:A145)+1) -> 129 | I146: =IF(L146="Cadeau",0,C146*$S$2+D146*$S$3+E146*$S$4+F146*$S$5) -> 0
A147: =IF(L147="CAdeau",0,MAX($A$2:A146)+1) -> 130 | I147: =IF(L147="Cadeau",0,C147*$S$2+D147*$S$3+E147*$S$4+F147*$S$5) -> 0
A148: =IF(L148="CAdeau",0,MAX($A$2:A147)+1) -> 131 | I148: =IF(L148="Cadeau",0,C148*$S$2+D148*$S$3+E148*$S$4+F148*$S$5) -> 0
A149: =IF(L149="CAdeau",0,MAX($A$2:A148)+1) -> 132 | I149: =IF(L149="Cadeau",0,C149*$S$2+D149*$S$3+E149*$S$4+F149*$S$5) -> 0
A150: =IF(L150="CAdeau",0,MAX($A$2:A149)+1) -> 133 | I150: =IF(L150="Cadeau",0,C150*$S$2+D150*$S$3+E150*$S$4+F150*$S$5) -> 0
A151: =IF(L151="CAdeau",0,MAX($A$2:A150)+1) -> 134
A152: =IF(L152="CAdeau",0,MAX($A$2:A151)+1) -> 135
A153: =IF(L153="CAdeau",0,MAX($A$2:A152)+1) -> 136
A154: =IF(L154="CAdeau",0,MAX($A$2:A153)+1) -> 137
A155: =IF(L155="CAdeau",0,MAX($A$2:A154)+1) -> 138
A156: =IF(L156="CAdeau",0,MAX($A$2:A155)+1) -> 139
A157: =IF(L157="CAdeau",0,MAX($A$2:A156)+1) -> 140
A158: =IF(L158="CAdeau",0,MAX($A$2:A157)+1) -> 141
A159: =IF(L159="CAdeau",0,MAX($A$2:A158)+1) -> 142
A160: =IF(L160="CAdeau",0,MAX($A$2:A159)+1) -> 143
A161: =IF(L161="CAdeau",0,MAX($A$2:A160)+1) -> 144

Sheet Facturation 2021
E5: CHAMPAGNE CAROUGE CIREDDU
G8: Nom | I8: =VLOOKUP(C16,'Suivi Facturation 2021'!$A$5:$J$10004,2,FALSE) -> Léo Carouge
G9: Adresse | I9: =VLOOKUP(I8,'Suivi Client'!$C$3:$H$2000,3,FALSE) &" " & VLOOKUP(I8,'Suivi Client'!$C$2:$H$2000,4,FALSE) &" " & VLOOKUP(I8,'Suivi Client'!$C$2:$H$2000,5,FALSE) -> #N/A
G12: Adresse e-mail | I12: =IF(VLOOKUP(I8,'Suivi Client'!$C$2:$H$2000,2,FALSE)=0,"",VLOOKUP(I8,'Suivi Client'!$C$2:$H$2000,2,FALSE)) -> leocarouge@gmail.com
A16: numéro de facturation | C16: 39
A17: Date de facturation | C17: =VLOOKUP(C16,'Suivi Facturation 2021'!$A$5:$J$10004,10,FALSE) -> 44329
A21: Contenance | B21: Designation | H21: Qté | I21: Prix unitaire TTC | K21: Montant TTC
A23: =IF(VLOOKUP($C$16,'Suivi Facturation 2021'!$A$4:$L$1098,3,FALSE)>0,"0,75","") -> 0,75 | B23: =IF(VLOOKUP($C$16,'Suivi Facturation 2021'!$A$4:$L$980,3,FALSE)>0,"Bouteille CHAMPAGNE SELECTION","") -> Bouteille CHAMPAGNE SELECTION | H23: =IF(VLOOKUP($C$16,'Suivi Facturation 2021'!$A$4:$L$1098,3,FALSE)>0,VLOOKUP($C$16,'Suivi Facturation 2021'!$A$4:$L$1098,3,FALSE),"") -> 6 | I23: =IF(VLOOKUP($C$16,'Suivi Facturation 2021'!$A$4:$L$1098,3,FALSE)>0,'Suivi Facturation 2021'!R4,"") -> 16 | K23: =IF(VLOOKUP($C$16,'Suivi Facturation 2021'!$A$4:$L$1098,3,FALSE)>0,I23*H23,"") -> 96
A24: =IF(VLOOKUP($C$16,'Suivi Facturation 2021'!$A$4:$L$1098,4,FALSE)>0,"0,75","") -> 0,75 | B24: =IF(VLOOKUP($C$16,'Suivi Facturation 2021'!$A$4:$L$980,4,FALSE)>0,"Bouteille CHAMPAGNE ROSE","") -> Bouteille CHAMPAGNE ROSE | H24: =IF(VLOOKUP($C$16,'Suivi Facturation 2021'!$A$4:$L$1098,4,FALSE)>0,VLOOKUP($C$16,'Suivi Facturation 2021'!$A$4:$L$1098,4,FALSE),"") -> 2 | I24: =IF(VLOOKUP($C$16,'Suivi Facturation 2021'!$A$4:$L$1098,4,FALSE)>0,'Suivi Facturation 2021'!R5,"") -> 18 | K24: =IF(VLOOKUP($C$16,'Suivi Facturation 2021'!$A$4:$L$1098,4,FALSE)>0,I24*H24,"") -> 36
A25: =IF(VLOOKUP($C$16,'Suivi Facturation 2021'!$A$4:$L$1098,5,FALSE)>0,"0,75","") -> 0,75 | B25: =IF(VLOOKUP($C$16,'Suivi Facturation 2021'!$A$4:$L$980,5,FALSE)>0,"Bouteille CHAMPAGNE BLANC DE BLANC","") -> Bouteille CHAMPAGNE BLANC DE BLANC | H25: =IF(VLOOKUP($C$16,'Suivi Facturation 2021'!$A$4:$L$1998,5,FALSE)>0,VLOOKUP($C$16,'Suivi Facturation 2021'!$A$4:$L$1998,5,FALSE),"") -> 6 | I25: =IF(VLOOKUP($C$16,'Suivi Facturation 2021'!$A$4:$L$1098,5,FALSE)>0,'Suivi Facturation 2021'!R6,"") -> 17.5 | K25: =IF(VLOOKUP($C$16,'Suivi Facturation 2021'!$A$4:$L$1098,5,FALSE)>0,I25*H25,"") -> 105
A26: =IF(VLOOKUP($C$16,'Suivi Facturation 2021'!$A$4:$L$1098,6,FALSE)>0,"0,75","") | B26: =IF(VLOOKUP($C$16,'Suivi Facturation 2021'!$A$4:$L$1098,6,FALSE)>0,"Bouteille CHAMPAGNE PRESTIGE","") | H26: =IF(VLOOKUP($C$16,'Suivi Facturation 2021'!$A$4:$L$1098,6,FALSE)>0,VLOOKUP($C$16,'Suivi Facturation 2021'!$A$4:$L$1098,4,FALSE),"") | I26: =IF(VLOOKUP($C$16,'Suivi Facturation 2021'!$A$4:$L$1098,6,FALSE)>0,'Suivi Facturation 2021'!R7,"") | K26: =IF(VLOOKUP($C$16,'Suivi Facturation 2021'!$A$4:$L$1098,6,FALSE)>0,I26*H26,"")
B27: =IF(VLOOKUP($C$16,'Suivi Facturation 2021'!$A$4:$O$1980,14,FALSE)>0,"PRIX LIVRAISON","") -> PRIX LIVRAISON | I27: =IF(VLOOKUP($C$16,'Suivi Facturation 2021'!$A$4:$L$1098,6,FALSE)>0,'Suivi Facturation 2021'!R8,"") | K27: =IF(VLOOKUP($C$16,'Suivi Facturation 2021'!$A$4:$O$1980,14,FALSE)>0,VLOOKUP($C$16,'Suivi Facturation 2021'!$A$4:$O$1980,14,FALSE),"") -> depot// plus 1 Conso
K36: Total HT | L36: =SUM(K23:L27)-L37 -> 197.5
K37: TVA (20%) | L37: =IFERROR(SUM(K23:L28)-SUM(K23:L28)/1.2,"") -> 39.5
K39: Total TTC | L39: =SUM(K23:L26) -> 237
A41: Toute somme impayée à son échéance produira, de plein droit et sans mise en demeure, un intérêt égal à 1,5 fois le taux d'intérêt légal par mois de retard. Nos conditions de vente ne prévoient pas d'escompte pour paiement anticipé. Coordonnées bancaires Titulaire du compte : JAMES CAROUGE IBAN FR76 1020 6000 4848 3510 3712 067 BIC AGRIFRPP802
A53: CHAMPAGNE CAROUGE CIREDDU 6 rue de l'eglise 51190 FLAVIGNY Tel : 06 77 95 90 62 SIRET 843 516 642 00017 N° TVA intracommunautaire FR67 843 516 642

Sheet Facturation 2022
E5: CHAMPAGNE CAROUGE CIREDDU
G8: Nom | I8: =VLOOKUP(C16,'Suivi Facturation 2022'!$A$5:$J$10004,2,FALSE) -> Philippe Gintrand
G9: Adresse | I9: =VLOOKUP(I8,'Suivi Client'!$C$3:$H$2000,3,FALSE) &" " & VLOOKUP(I8,'Suivi Client'!$C$2:$H$2000,4,FALSE) &" " & VLOOKUP(I8,'Suivi Client'!$C$2:$H$2000,5,FALSE) -> 2 CHEMIN D OLLANET 26240 St vallier
G12: Adresse e-mail | I12: =IF(VLOOKUP(I8,'Suivi Client'!$C$2:$H$2000,2,FALSE)=0,"",VLOOKUP(I8,'Suivi Client'!$C$2:$H$2000,2,FALSE))
A16: numéro de facturation | C16: 32
A17: Date de facturation
A21: Contenance | B21: Designation | H21: Qté | I21: Prix unitaire TTC | K21: Montant TTC
A23: =IF(VLOOKUP($C$16,'Suivi Facturation 2021'!$A$4:$L$1098,3,FALSE)>0,"0,75","") -> 0,75 | B23: =IF(VLOOKUP($C$16,'Suivi Facturation 2021'!$A$4:$L$980,3,FALSE)>0,"Bouteille CHAMPAGNE SELECTION","") -> Bouteille CHAMPAGNE SELECTION | H23: =IF(VLOOKUP($C$16,'Suivi Facturation 2022'!$A$4:$L$1098,3,FALSE)>0,VLOOKUP($C$16,'Suivi Facturation 2021'!$A$4:$L$1098,3,FALSE),"") -> 4 | I23: =IF(VLOOKUP($C$16,'Suivi Facturation 2021'!$A$4:$L$1098,3,FALSE)>0,'Suivi Facturation 2021'!R4,"") -> 16 | K23: =IF(VLOOKUP($C$16,'Suivi Facturation 2021'!$A$4:$L$1098,3,FALSE)>0,I23*H23,"") -> 64
A24: =IF(VLOOKUP($C$16,'Suivi Facturation 2022'!$A$4:$L$1098,4,FALSE)>0,"0,75","") | B24: =IF(VLOOKUP($C$16,'Suivi Facturation 2022'!$A$4:$L$980,4,FALSE)>0,"Bouteille CHAMPAGNE ROSE","") | H24: =IF(VLOOKUP($C$16,'Suivi Facturation 2022'!$A$4:$L$1098,4,FALSE)>0,VLOOKUP($C$16,'Suivi Facturation 2021'!$A$4:$L$1098,4,FALSE),"") | I24: =IF(VLOOKUP($C$16,'Suivi Facturation 2022'!$A$4:$L$1098,4,FALSE)>0,'Suivi Facturation 2021'!R5,"") | K24: =IF(VLOOKUP($C$16,'Suivi Facturation 2022'!$A$4:$L$1098,4,FALSE)>0,I24*H24,"")
A25: =IF(VLOOKUP($C$16,'Suivi Facturation 2021'!$A$4:$L$1098,5,FALSE)>0,"0,75","") | B25: =IF(VLOOKUP($C$16,'Suivi Facturation 2021'!$A$4:$L$980,5,FALSE)>0,"Bouteille CHAMPAGNE BLANC DE BLANC","") | H25: =IF(VLOOKUP($C$16,'Suivi Facturation 2021'!$A$4:$L$1998,5,FALSE)>0,VLOOKUP($C$16,'Suivi Facturation 2021'!$A$4:$L$1998,5,FALSE),"") | I25: =IF(VLOOKUP($C$16,'Suivi Facturation 2021'!$A$4:$L$1098,5,FALSE)>0,'Suivi Facturation 2021'!R6,"") | K25: =IF(VLOOKUP($C$16,'Suivi Facturation 2021'!$A$4:$L$1098,5,FALSE)>0,I25*H25,"")
A26: =IF(VLOOKUP($C$16,'Suivi Facturation 2021'!$A$4:$L$1098,6,FALSE)>0,"0,75","") | B26: =IF(VLOOKUP($C$16,'Suivi Facturation 2021'!$A$4:$L$1098,6,FALSE)>0,"Bouteille CHAMPAGNE PRESTIGE","") | H26: =IF(VLOOKUP($C$16,'Suivi Facturation 2021'!$A$4:$L$1098,6,FALSE)>0,VLOOKUP($C$16,'Suivi Facturation 2021'!$A$4:$L$1098,4,FALSE),"") | I26: =IF(VLOOKUP($C$16,'Suivi Facturation 2021'!$A$4:$L$1098,6,FALSE)>0,'Suivi Facturation 2021'!R7,"") | K26: =IF(VLOOKUP($C$16,'Suivi Facturation 2021'!$A$4:$L$1098,6,FALSE)>0,I26*H26,"")
B27: =IF(VLOOKUP($C$16,'Suivi Facturation 2022'!$A$4:$O$1980,14,FALSE)>0,"PRIX LIVRAISON","") -> PRIX LIVRAISON | I27: =IF(VLOOKUP($C$16,'Suivi Facturation 2021'!$A$4:$L$1098,6,FALSE)>0,'Suivi Facturation 2021'!R8,"") | K27: =IF(VLOOKUP($C$16,'Suivi Facturation 2022'!$A$4:$O$1980,14,FALSE)>0,VLOOKUP($C$16,'Suivi Facturation 2021'!$A$4:$O$1980,14,FALSE),"") -> DEPOT LEO
K36: Total HT | L36: =SUM(K23:L27)-L37 -> 53.333333
K37: TVA (20%) | L37: =IFERROR(SUM(K23:L28)-SUM(K23:L28)/1.2,"") -> 10.666667
K39: Total TTC | L39: =SUM(K23:L26) -> 64
A41: Toute somme impayée à son échéance produira, de plein droit et sans mise en demeure, un intérêt égal à 1,5 fois le taux d'intérêt légal par mois de retard. Nos conditions de vente ne prévoient pas d'escompte pour paiement anticipé. Coordonnées bancaires Titulaire du compte : JAMES CAROUGE IBAN FR76 1020 6000 4848 3510 3712 067 BIC AGRIFRPP802
A53: CHAMPAGNE CAROUGE CIREDDU 6 rue de l'eglise 51190 FLAVIGNY Tel : 06 77 95 90 62 SIRET 843 516 642 00017 N° TVA intracommunautaire FR67 843 516 642

Sheet Suivi Facturation 2020
A5: Numero Facuration | B5: Nom Client | C5: NB Selection | D5: NB Rosé | E5: Montant TTC | F5: Date de facturation | G5: Etat paiement | H5: Etat Commande | I5: paiement | J5: commentaire | K5: Statistiques | M5: 339
A6: 1 | B6: Pierre leclézio | C6: 6 | D6: 0 | E6: =IF(G6="Cadeau",0,C6*$L$6+D6*$L$7) -> 96 | F6: 44184 | G6: Facturé | H6: Livrée | I6: Virement | K6: Sélection | L6: 16 | M6: =SUM(C6:D50) -> 363
A7: 2 | B7: GAEL LAPEDAGNE | C7: 6 | D7: 0 | E7: =IF(G7="Cadeau",0,C7*$L$6+D7*$L$7) -> 96 | F7: 44184 | G7: Payé | H7: Livrée | I7: espece | J7: 44185 | K7: Rosé | L7: 18
A8: 3 | B8: Agnès Marrié | C8: 4 | D8: 2 | E8: =IF(G8="Cadeau",0,C8*$L$6+D8*$L$7) -> 0 | F8: 44178 | G8: Cadeau | H8: Livrée | I8: Cxxxxcxx | J8: 44179 | K8: Nb bouteilles vendues
A9: 4 | B9: OIHAN MADARIAGA | C9: 6 | D9: 0 | E9: =IF(G9="Cadeau",0,C9*$L$6+D9*$L$7) -> 96 | F9: 44184 | G9: Payé | H9: Livrée | I9: espece | J9: 44185
A10: 5 | B10: ACHILLE WOJTOWIC | C10: 6 | D10: 0 | E10: =IF(G10="Cadeau",0,C10*$L$6+D10*$L$7) -> 96 | F10: 44184 | G10: Facturé | H10: Livrée | I10: Virement | J10: 44185 | K10: Chiffre d'affaire | L10: =SUM(E6:E50) -> 5582
A11: 6 | B11: BASTIEN LASSER | C11: 6 | D11: 0 | E11: =IF(G11="Cadeau",0,C11*$L$6+D11*$L$7) -> 96 | F11: 44184 | G11: Payé | H11: Livrée | I11: Virement | J11: 44185
A12: 7 | B12: HUGO LANDRIEU | C12: 2 | D12: 0 | E12: =IF(G12="Cadeau",0,C12*$L$6+D12*$L$7) -> 32 | F12: 44184 | G12: Facturé | H12: Livrée | I12: Virement | J12: 44185
A13: =MIN(A10:A12) -> 5 | B13: CHARLOTTE | C13: 4 | D13: 4 | E13: =IF(G13="Cadeau",0,C13*$L$6+D13*$L$7) -> 136 | F13: 44184 | G13: Facturé | H13: Livrée | I13: Virement | J13: 44185
A14: 9 | B14: XANTI BILBAO | C14: 6 | D14: 0 | E14: =IF(G14="Cadeau",0,C14*$L$6+D14*$L$7) -> 96 | F14: 44184 | G14: Facturé | H14: Livrée | I14: espece
A15: 10 | B15: CHARLES POULHES | C15: 10 | D15: 0 | E15: =IF(G15="Cadeau",0,C15*$L$6+D15*$L$7) -> 160 | F15: 44184 | G15: Payé | H15: Livrée | I15: virement
A16: 11 | B16: ALEXANDRE SIMON | C16: 4 | D16: 0 | E16: =IF(G16="Cadeau",0,C16*$L$6+D16*$L$7) -> 64 | F16: 44184 | G16: Payé | H16: Livrée | I16: Virement
A17: 12 | B17: GENTZA ETXABE | C17: 12 | D17: 0 | E17: =IF(G17="Cadeau",0,C17*$L$6+D17*$L$7) -> 192 | F17: 44184 | G17: Payé | H17: Livrée | I17: Virement 128
A18: 13 | B18: BIXENTE COTINA | C18: 2 | D18: 0 | E18: =IF(G18="Cadeau",0,C18*$L$6+D18*$L$7) -> 32 | F18: 44184 | G18: Facturé | H18: Livrée | I18: Règle ohian
A19: 14 | B19: GABI AIZPURUA | C19: 6 | D19: 6 | E19: =IF(G19="Cadeau",0,C19*$L$6+D19*$L$7) -> 204 | F19: 44184 | G19: Facturé | H19: Livrée | I19: Virement | J19: LAGUILLON CHRISTINE VIR
A20: 15 | B20: JAIME MATESANZE | C20: 2 | D20: 0 | E20: =IF(G20="Cadeau",0,C20*$L$6+D20*$L$7) -> 32 | F20: 44184 | G20: Facturé | H20: Livrée | I20: Virement
A21: 16 | B21: Philippe Gintrand | C21: 6 | E21: =IF(G21="Cadeau",0,C21*$L$6+D21*$L$7) -> 96 | F21: 44191 | G21: Payé | H21: Livrée | I21: cheque
A22: 17 | B22: Gregory Cireddu | C22: 42 | D22: 0 | E22: =IF(G22="Cadeau",0,C22*$L$6+D22*$L$7) -> 672 | F22: 44187 | G22: Payé | H22: Livrée | I22: cheque
A23: 18 | B23: Jac/dan Bouilot | C23: 6 | D23: 6 | E23: =IF(G23="Cadeau",0,C23*$L$6+D23*$L$7) -> 204 | F23: 44191 | G23: Payé | H23: Livrée | I23: cheque
A24: 19 | B24: Eric Soulhac | C24: 4 | D24: 2 | E24: =IF(G24="Cadeau",0,C24*$L$6+D24*$L$7) -> 100 | F24: 44191 | G24: Payé | H24: Livrée | I24: cheque
A25: 20 | B25: Pascal Fassaert | C25: 6 | E25: =IF(G25="Cadeau",0,C25*$L$6+D25*$L$7) -> 96 | F25: 44191 | G25: Payé | H25: Livrée | I25: cheque
A26: 21 | B26: Gintrand | C26: 3 | D26: 3 | E26: =IF(G26="Cadeau",0,C26*$L$6+D26*$L$7) -> 102 | F26: 44191 | G26: Facturé | H26: Livrée | I26: EN attente | J26: REGLE AVEC PHILIPPE 26/05
A27: 22 | B27: ZACHARIE Fassaert | C27: 6 | E27: =IF(G27="Cadeau",0,C27*$L$6+D27*$L$7) -> 96 | F27: 44191 | G27: Facturé | H27: Livrée | I27: Virement
A28: 23 | B28: Dubois Jean-Louis | C28: 6 | D28: 6 | E28: =IF(G28="Cadeau",0,C28*$L$6+D28*$L$7) -> 204 | F28: 44193 | G28: Facturé | H28: Livrée | I28: Chèque
A29: 24 | B29: Jacques Morel | C29: 12 | E29: =IF(G29="Cadeau",0,C29*$L$6+D29*$L$7) -> 192 | F29: 44191 | G29: Payé | H29: Livrée | I29: cheque
A30: 25 | B30: cireddu camille | C30: 3 | E30: =IF(G30="Cadeau",0,C30*$L$6+D30*$L$7) -> 48 | F30: 44187 | G30: Payé | H30: Livrée | I30: espece
A31: 26 | B31: Aymeric Chataigner | C31: 12 | D31: 3 | E31: =IF(G31="Cadeau",0,C31*$L$6+D31*$L$7) -> 246 | F31: 44193 | G31: Facturé | H31: Livrée | I31: Virement
A32: 27 | B32: Philippe Gintrand | C32: 3 | D32: 1 | E32: =IF(G32="Cadeau",0,C32*$L$6+D32*$L$7) -> 0 | F32: 44193 | G32: Cadeau | H32: Livrée | I32: Cxxxxxx | J32: 1 rose
A33: 28 | B33: Léo Carouge | C33: 3 | E33: =IF(G33="Cadeau",0,C33*$L$6+D33*$L$7) -> 0 | F33: 44193 | G33: Cadeau | H33: Livrée | I33: Xxxxxxxxx | J33: sans capsule anniversaire
A34: 29 | B34: Jacques Morel | C34: 18 | D34: 1 | E34: =IF(G34="Cadeau",0,C34*$L$6+D34*$L$7) -> 306 | F34: 44193 | H34: Livrée | I34: Cxxxxxxxx | J34: 1 rose
A35: 30 | B35: Benoit Meon | C35: 18 | D35: 6 | E35: =IF(G35="Cadeau",0,C35*$L$6+D35*$L$7) -> 396 | F35: 44193 | G35: Facturé | H35: Livrée | I35: Virement | J35: Colegue Leo : 3cartons blancs et 1cartons rosés CARTONS
A36: 31 | B36: Carouge Valerie | C36: 6 | E36: =IF(G36="Cadeau",0,C36*$L$6+D36*$L$7) -> 96 | F36: 44193 | G36: Payé | H36: Livrée | I36: espece
A37: 32 | B37: cireddu camille | C37: 12 | D37: 6 | E37: =IF(G37="Cadeau",0,C37*$L$6+D37*$L$7) -> 300 | F37: 44193 | G37: A facturer | H37: Livrée | I37: Virement
A38: 33 | B38: Nino Carouge | C38: 3 | D38: 4 | E38: =IF(G38="Cadeau",0,C38*$L$6+D38*$L$7) -> 0 | F38: 44193 | G38: Cadeau | H38: Livrée | I38: Xxxxxxxx
A39: 34 | B39: JOELLE DUBARBIER | C39: 4 | D39: 4 | E39: =IF(G39="Cadeau",0,C39*$L$6+D39*$L$7) -> 136 | F39: 44193 | G39: Payé | H39: Livrée | I39: VIREMENT
A40: 35 | B40: Fassaert Jeff | C40: 18 | E40: =IF(G40="Cadeau",0,C40*$L$6+D40*$L$7) -> 288 | F40: 44193 | G40: Payé | H40: Livrée | I40: Virement
A41: 36 | B41: cedric jaunet | C41: 12 | E41: =IF(G41="Cadeau",0,C41*$L$6+D41*$L$7) -> 192 | F41: 44193 | G41: A facturer | H41: Habillée
A42: 37 | B42: Léo Carouge | C42: 24 | E42: =IF(G42="Cadeau",0,C42*$L$6+D42*$L$7) -> 384 | F42: 44193 | G42: A facturer | H42: Habillée
A43: 38 | E43: =IF(G43="Cadeau",0,C43*$L$6+D43*$L$7) -> 0
E44: =IF(G44="Cadeau",0,C44*$L$6+D44*$L$7) -> 0
E45: =IF(G45="Cadeau",0,C45*$L$6+D45*$L$7) -> 0
E46: =IF(G46="Cadeau",0,C46*$L$6+D46*$L$7) -> 0
E47: =IF(G47="Cadeau",0,C47*$L$6+D47*$L$7) -> 0
E48: =IF(G48="Cadeau",0,C48*$L$6+D48*$L$7) -> 0
E49: =IF(G49="Cadeau",0,C49*$L$6+D49*$L$7) -> 0
E50: =IF(G50="Cadeau",0,C50*$L$6+D50*$L$7) -> 0
E51: =IF(G51="Cadeau",0,C51*$L$6+D51*$L$7) -> 0
A52: Léo Carouge | E52: =IF(G52="Cadeau",0,C52*$L$6+D52*$L$7) -> 0
E53: =IF(G53="Cadeau",0,C53*$L$6+D53*$L$7) -> 0
E54: =IF(G54="Cadeau",0,C54*$L$6+D54*$L$7) -> 0
E55: =IF(G55="Cadeau",0,C55*$L$6+D55*$L$7) -> 0
E56: =IF(G56="Cadeau",0,C56*$L$6+D56*$L$7) -> 0
E57: =IF(G57="Cadeau",0,C57*$L$6+D57*$L$7) -> 0
E58: =IF(G58="Cadeau",0,C58*$L$6+D58*$L$7) -> 0
E59: =IF(G59="Cadeau",0,C59*$L$6+D59*$L$7) -> 0
E60: =IF(G60="Cadeau",0,C60*$L$6+D60*$L$7) -> 0
E61: =IF(G61="Cadeau",0,C61*$L$6+D61*$L$7) -> 0
E64: =IF(G64="Cadeau",0,C64*$L$6+D64*$L$7) -> 0
E65: =IF(G65="Cadeau",0,C65*$L$6+D65*$L$7) -> 0
E66: =IF(G66="Cadeau",0,C66*$L$6+D66*$L$7) -> 0
... E70: =IF(G70="Cadeau",0,C70*$L$6+D70*$L$7) -> 0

Sheet Suivi Facturation 2021
S1: Prix unitaire HT | T1: sortie decembre | U1: Sortie janvier | V1: Sortie fevrier | W1: mars | X1: avril | Y1: mai | Z1: juin | AA1: juillet | AB1: aout
S2: =R4/1.2 -> 13.333333 | T2: 339 | U2: 59 | V2: 154 | W2: 33 | X2: 104 | Y2: 135 | Z2: 218 | AA2: 161 | AB2: 669
A3: Numero de facture | B3: Nom Client | C3: NB Selection | D3: NB Rosé | E3: Nb blanc de blan | F3: Nb Prestige | G3: Remise Exceptionnelle | H3: Montant TTC bouteilles | I3: Montant HT | J3: Date de facturation | K3: Etat paiement | L3: Etat Commande | M3: paiement | N3: commentaire | O3: Prix Transport TTC | Q3: Statistiques | R3: Prix unitaire TTC | S3: =R5/1.2 -> 15
A4: 1 | B4: Nino Carouge | C4: 2 | D4: 1 | E4: 0 | F4: 0 | G4: CONSO | H4: =IF(K4="Cadeau",0,C4*$R$4+D4*$R$5+E4*$R$6+F4*$R$7) -> 0 | I4: =H4/1.2 -> 0 | J4: 24 /01/2021 | K4: Cadeau | L4: Livrée | M4: 0 | N4: nino conso paris | Q4: Sélection | R4: 16 | T4: 288 | U4: 45 | V4: 103 | W4: 19 | X4: 92 | Y4: 75 | Z4: 138 | AA4: 66 | AB4: 605
A5: 2 | B5: Gregory Cireddu | C5: 38 | D5: 12 | G5: DEPOT ISA | H5: =IF(K5="Cadeau",0,C5*$R$4+D5*$R$5+E5*$R$6+F5*$R$7) -> 824 | I5: =H5/1.2 -> 686.66667 | J5: 44223 | K5: En attente de paiement | L5: Livrée | M5: viremrnt | N5: DEPOPT ISA GREG ET 2 CADEAUX | Q5: Rosé | R5: 18 | T5: 48 | U5: 14 | V5: 51 | W5: 14 | X5: 12 | Y5: 50 | Z5: 72 | AA5: 27 | AB5: 25
A6: =IF(K6="CAdeau",0,MAX($A$3:A5)+1) -> 3 | B6: FISHER LEO | C6: 6 | G6: LIVRER | H6: =IF(K6="Cadeau",0,C6*$R$4+D6*$R$5+E6*$R$6+F6*$R$7) -> 96 | I6: =H6/1.2 -> 80 | J6: 44225 | K6: Payé | L6: Livrée | M6: virement | N6: PARIS NINO | Q6: Blanc de blanc | R6: 17.5 | Y6: 27 | Z6: 7 | AA6: 68 | AB6: 38
A7: =IF(K7="CAdeau",0,MAX($A$3:A6)+1) -> 4 | B7: Jac/dan Bouilot | D7: 12 | G7: SORTIE ST VALLIER | H7: =IF(K7="Cadeau",0,C7*$R$4+D7*$R$5+E7*$R$6+F7*$R$7) -> 216 | I7: =H7/1.2 -> 180 | J7: 44247 | K7: Payé | L7: Livrée | M7: Virement | N7: gintrand | Q7: Prestige | R7: 30
A8: =IF(K8="CAdeau",0,MAX($A$3:A7)+1) -> 5 | B8: Pascal Fassaert | C8: 18 | D8: 2 | G8: LIVRER | H8: =IF(K8="Cadeau",0,C8*$R$4+D8*$R$5+E8*$R$6+F8*$R$7) -> 324 | I8: =H8/1.2 -> 270 | J8: 44247 | K8: Payé | L8: Livrée | M8: Virement | N8: Gintrand
A9: =IF(K9="CAdeau",0,MAX($A$3:A8)+1) -> 6 | B9: Léo Carouge | D9: 12 | G9: DEPOT LEO | H9: =IF(K9="Cadeau",0,C9*$R$4+D9*$R$5+E9*$R$6+F9*$R$7) -> 216 | I9: =H9/1.2 -> 180 | J9: 44240 | K9: En attente de paiement | L9: Livrée | N9: depot paris | Q9: Nb bouteilles vendues | R9: =SUM(C4:D1203) -> 1934
A10: =IF(K10="CAdeau",0,MAX($A$3:A9)+1) -> 7 | B10: VICTOIRE SCHMITT | C10: 6 | G10: SORTIE DEPOT LEO | H10: =IF(K10="Cadeau",0,C10*$R$4+D10*$R$5+E10*$R$6+F10*$R$7) -> 96 | I10: =H10/1.2 -> 80 | J10: 44226 | K10: Payé | L10: Livrée | M10: virement | N10: LIVRE PAR LEO
A11: =IF(K11="CAdeau",0,MAX($A$3:A10)+1) -> 8 | B11: Pascal Ville | C11: 6 | G11: LIVRER | H11: =IF(K11="Cadeau",0,C11*$R$4+D11*$R$5+E11*$R$6+F11*$R$7) -> 96 | I11: =H11/1.2 -> 80 | J11: 44247 | K11: Payé | L11: Livrée | M11: Virement | N11: GINTRAND | Q11: Chiffre d'affaire | R11: =SUM(H4:H1218) -> 35293.5
A12: =IF(K12="CAdeau",0,MAX($A$3:A11)+1) -> 9 | B12: JEAN MARTIN | C12: 12 | G12: LIVRER | H12: =IF(K12="Cadeau",0,C12*$R$4+D12*$R$5+E12*$R$6+F12*$R$7) -> 192 | I12: =H12/1.2 -> 160 | J12: 44247 | K12: Payé | L12: Livrée | M12: virement | N12: GINTRAND
A13: =IF(K13="CAdeau",0,MAX($A$3:A12)+1) -> 10 | B13: MICHELLE Fassaert | C13: 12 | G13: LIVRER | H13: =IF(K13="Cadeau",0,C13*$R$4+D13*$R$5+E13*$R$6+F13*$R$7) -> 192 | I13: =H13/1.2 -> 160 | J13: 44247 | K13: Payé | L13: Livrée | M13: cheque | N13: GINTRAND
A14: =IF(K14="CAdeau",0,MAX($A$3:A13)+1) -> 11 | B14: Jacques Morel | C14: 12 | G14: LIVRER | H14: =IF(K14="Cadeau",0,C14*$R$4+D14*$R$5+E14*$R$6+F14*$R$7) -> 192 | I14: =H14/1.2 -> 160 | J14: 44247 | K14: Payé | L14: Livrée | M14: virement | N14: Gintrand
A15: =IF(K15="CAdeau",0,MAX($A$3:A14)+1) -> 12 | B15: Philippe Gintrand | C15: 18 | D15: 12 | G15: DEPOT ST VALLIER | H15: =IF(K15="Cadeau",0,C15*$R$4+D15*$R$5+E15*$R$6+F15*$R$7) -> 504 | I15: =H15/1.2 -> 420 | J15: 44247 | K15: En attente de paiement | L15: Livrée | N15: Dépôt St vallier
A16: =IF(K16="CAdeau",0,MAX($A$3:A15)+1) -> 13 | B16: XANTI BILBAO | C16: 24 | D16: 12 | G16: DEPOT DUBARBIER | H16: =IF(K16="Cadeau",0,C16*$R$4+D16*$R$5+E16*$R$6+F16*$R$7) -> 600 | I16: =H16/1.2 -> 500 | J16: 44252 | K16: En attente de paiement | L16: Livrée | N16: depot st jean dubarbier
A17: =IF(K17="CAdeau",0,MAX($A$3:A16)+1) -> 14 | B17: Nino Carouge | C17: 1 | D17: 1 | G17: CONSO | H17: =IF(K17="Cadeau",0,C17*$R$4+D17*$R$5+E17*$R$6+F17*$R$7) -> 34 | I17: =H17/1.2 -> 28.333333 | J17: 44254 | L17: Livrée | N17: CONSO PARIS
A18: =IF(K18="CAdeau",0,MAX($A$3:A17)+1) -> 15 | B18: Stanislas BOUTMY | C18: 13 | G18: DEPOT LEO | H18: =IF(K18="Cadeau",0,C18*$R$4+D18*$R$5+E18*$R$6+F18*$R$7) -> 208 | I18: =H18/1.2 -> 173.33333 | J18: 44264 | K18: Payé | L18: Livrée | M18: Virement | N18: leo collegue
A19: =IF(K19="CAdeau",0,MAX($A$3:A18)+1) -> 16 | B19: Benoit Meon | C19: 0 | D19: 24 | G19: DEPOT LEO | H19: =IF(K19="Cadeau",0,C19*$R$4+D19*$R$5+E19*$R$6+F19*$R$7) -> 432 | I19: =H19/1.2 -> 360 | J19: 44308 | K19: Payé | L19: Livrée | M19: Virement | N19: Depot Leo 4 caisses roses
A20: =IF(K20="CAdeau",0,MAX($A$3:A19)+1) -> 17 | H20: =IF(K20="Cadeau",0,C20*$R$4+D20*$R$5+E20*$R$6+F20*$R$7) -> 0 | I20: =H20/1.2 -> 0 | L20: Livrée
A21: =IF(K21="CAdeau",0,MAX($A$3:A20)+1) -> 18 | B21: Léo Carouge | C21: 12 | D21: 12 | G21: DEPOT LEO | H21: =IF(K21="Cadeau",0,C21*$R$4+D21*$R$5+E21*$R$6+F21*$R$7) -> 408 | I21: =H21/1.2 -> 340 | J21: 44263 | K21: En attente de paiement | L21: Livrée | N21: Dépôt paris leo
A22: =IF(K22="CAdeau",0,MAX($A$3:A21)+1) -> 19 | B22: CADEAU | C22: 3 | G22: CADEAUX | H22: =IF(K22="Cadeau",0,C22*$R$4+D22*$R$5+E22*$R$6+F22*$R$7) -> 48 | I22: =H22/1.2 -> 40 | J22: 44263 | L22: Livrée | N22: PLUS 1maison
A23: =IF(K23="CAdeau",0,MAX($A$3:A22)+1) -> 20 | B23: Valerie Franck Gautier | C23: 4 | D23: 2 | G23: LIVRER | H23: =IF(K23="Cadeau",0,C23*$R$4+D23*$R$5+E23*$R$6+F23*$R$7) -> 100 | I23: =H23/1.2 -> 83.333333 | J23: 44264 | K23: Payé | L23: Livrée | M23: espece | N23: reprise maison
A24: =IF(K24="CAdeau",0,MAX($A$3:A23)+1) -> 21 | B24: Philippe Gintrand | C24: 54 | D24: 30 | E24: 18 | G24: DEPOT ST VALLIER | H24: =IF(K24="Cadeau",0,C24*$R$4+D24*$R$5+E24*$R$6+F24*$R$7) -> 1719 | I24: =H24/1.2 -> 1432.5 | J24: 44334 | K24: En attente de paiement | L24: Livrer | N24: DEPOT ST VALLIER
A25: =IF(K25="CAdeau",0,MAX($A$3:A24)+1) -> 22 | H25: =IF(K25="Cadeau",0,C25*$R$4+D25*$R$5+E25*$R$6+F25*$R$7) -> 0 | I25: =H25/1.2 -> 0 | J25: 44423 | L25: Livrer
A26: =IF(K26="CAdeau",0,MAX($A$3:A25)+1) -> 23 | H26: =IF(K26="Cadeau",0,C26*$R$4+D26*$R$5+E26*$R$6+F26*$R$7) -> 0 | I26: =H26/1.2 -> 0
A27: =IF(K27="CAdeau",0,MAX($A$3:A26)+1) -> 24 | B27: CHARLOTTE COUDRET | C27: 3 | D27: 3 | G27: DEPOT DUBARBIER | H27: =IF(K27="Cadeau",0,C27*$R$4+D27*$R$5+E27*$R$6+F27*$R$7) -> 102 | I27: =H27/1.2 -> 85 | J27: 44252 | K27: Payé | M27: virement | N27: DEPOT DUBARBIER
A28: =IF(K28="CAdeau",0,MAX($A$3:A27)+1) -> 25 | B28: amie dubarbier Farancoise | C28: 1 | D28: 2 | G28: DEPOT DUBARBIER | H28: =IF(K28="Cadeau",0,C28*$R$4+D28*$R$5+E28*$R$6+F28*$R$7) -> 52 | I28: =H28/1.2 -> 43.333333 | J28: 44252 | K28: Payé | M28: Espece
A29: =IF(K29="CAdeau",0,MAX($A$3:A28)+1) -> 26 | B29: JOELLE DUBARBIER | C29: 6 | G29: DEPOT DUBARBIER | H29: =IF(K29="Cadeau",0,C29*$R$4+D29*$R$5+E29*$R$6+F29*$R$7) -> 96 | I29: =H29/1.2 -> 80 | J29: 44561 | K29: Payé | L29: Livrer | M29: VIREMENT 80 EUROS
A30: =IF(K30="CAdeau",0,MAX($A$3:A29)+1) -> 27 | H30: =IF(K30="Cadeau",0,C30*$R$4+D30*$R$5+E30*$R$6+F30*$R$7) -> 0 | I30: =H30/1.2 -> 0
A31: =IF(K31="CAdeau",0,MAX($A$3:A30)+1) -> 28 | B31: Eric Soulhac | C31: 6 | D31: 6 | G31: DEPOT ST VALLIER | H31: =IF(K31="Cadeau",0,C31*$R$4+D31*$R$5+E31*$R$6+F31*$R$7) -> 204 | I31: =H31/1.2 -> 170 | J31: 44247 | K31: Payé | M31: virement | N31: depot gintrand
A32: =IF(K32="CAdeau",0,MAX($A$3:A31)+1) -> 29 | B32: LOVERGNE Sandre | C32: 6 | G32: DEPOT LEO | H32: =IF(K32="Cadeau",0,C32*$R$4+D32*$R$5+E32*$R$6+F32*$R$7) -> 96 | I32: =H32/1.2 -> 80 | J32: 44287 | K32: Payé | M32: Virement | N32: Dépôt leo
A33: =IF(K33="CAdeau",0,MAX($A$3:A32)+1) -> 30 | H33: =IF(K33="Cadeau",0,C33*$R$4+D33*$R$5+E33*$R$6+F33*$R$7) -> 0 | I33: =H33/1.2 -> 0
A34: =IF(K34="CAdeau",0,MAX($A$3:A33)+1) -> 31 | H34: =IF(K34="Cadeau",0,C34*$R$4+D34*$R$5+E34*$R$6+F34*$R$7) -> 0 | I34: =H34/1.2 -> 0
A35: =IF(K35="CAdeau",0,MAX($A$3:A34)+1) -> 32 | B35: Gauchet Lucile | C35: 4 | D35: 2 | G35: DEPOT LEO | H35: =IF(K35="Cadeau",0,C35*$R$4+D35*$R$5+E35*$R$6+F35*$R$7) -> 100 | I35: =H35/1.2 -> 83.333333 | J35: 44290 | K35: Payé | M35: virement | N35: DEPOT LEO
B36: Nino Carouge | C36: 2 | D36: 3 | G36: CADEAUX | H36: =IF(K36="Cadeau",0,C36*$R$4+D36*$R$5+E36*$R$6+F36*$R$7) -> 0 | I36: =H36/1.2 -> 0 | J36: 44289 | K36: Cadeau | M36: Conso | N36: nino conso
A37: =IF(K37="CAdeau",0,MAX($A$3:A36)+1) -> 33 | B37: VICTOIRE SCHMITT | C37: 60 | G37: LIVRER | H37: =IF(K37="Cadeau",0,C37*$R$4+D37*$R$5+E37*$R$6+F37*$R$7) -> 960 | I37: =H37/1.2 -> 800 | J37: 14/04/0201 | K37: Payé | M37: Virement | N37: PARIS
A38: =IF(K38="CAdeau",0,MAX($A$3:A37)+1) -> 34 | B38: Philémon Parent | C38: 6 | G38: LIVRER | H38: =IF(K38="Cadeau",0,C38*$R$4+D38*$R$5+E38*$R$6+F38*$R$7) -> 96 | I38: =H38/1.2 -> 80 | J38: 44304 | K38: Payé | M38: Cheque | N38: Germaine
A39: =IF(K39="CAdeau",0,MAX($A$3:A38)+1) -> 35 | B39: Paul Briest | D39: 6 | G39: LIVRER | H39: =IF(K39="Cadeau",0,C39*$R$4+D39*$R$5+E39*$R$6+F39*$R$7) -> 108 | I39: =H39/1.2 -> 90 | K39: Payé | L39: Livrer | M39: Virement 10/09/2021
A40: =IF(K40="CAdeau",0,MAX($A$3:A39)+1) -> 36 | B40: James Carouge | C40: 6 | G40: CONSO | J40: 44308 | K40: Payé | M40: CONSO | N40: CONSO
A41: =IF(K41="CAdeau",0,MAX($A$3:A40)+1) -> 37 | B41: ZACHARIE Fassaert | C41: 6 | G41: DEPOT LEO | H41: =IF(K41="Cadeau",0,C41*$R$4+D41*$R$5+E41*$R$6+F41*$R$7) -> 96 | I41: =H41/1.2 -> 80 | J41: 44316 | K41: Payé | M41: Virement | N41: ,apporter par nino
A42: =IF(K42="CAdeau",0,MAX($A$3:A41)+1) -> 38 | B42: Léo Carouge | C42: 6 | G42: DEPOT LEO | H42: =IF(K42="Cadeau",0,C42*$R$4+D42*$R$5+E42*$R$6+F42*$R$7) -> 96 | I42: =H42/1.2 -> 80 | J42: 44316 | K42: En attente de paiement | M42: DEPOT | N42: Dépôt Léo
A43: K | B43: Nino Carouge | C43: 1 | E43: 1 | G43: CONSO | H43: 0 | I43: =H43/1.2 -> 0 | K43: Payé | M43: CONSO | N43: Conso
A44: =IF(K44="CAdeau",0,MAX($A$3:A43)+1) -> 0 | B44: James Carouge | C44: 2 | D44: 2 | E44: 1 | G44: CADEAU | H44: =IF(K44="Cadeau",0,C44*$R$4+D44*$R$5+E44*$R$6+F44*$R$7) -> 0 | I44: =H44/1.2 -> 0 | J44: 44334 | K44: Cadeau | N44: Conso maison
A45: =IF(K45="CAdeau",0,MAX($A$3:A44)+1) -> 39 | B45: Léo Carouge | C45: 6 | D45: 2 | E45: 6 | G45: DEPOT LEO | H45: =IF(K45="Cadeau",0,C45*$R$4+D45*$R$5+E45*$R$6+F45*$R$7) -> 237 | I45: =H45/1.2 -> 197.5 | J45: 44329 | N45: depot// plus 1 Conso
A46: =IF(K46="CAdeau",0,MAX($A$3:A45)+1) -> 40 | B46: Regis Paquin | C46: 12 | G46: LIVRER | H46: =IF(K46="Cadeau",0,C46*$R$4+D46*$R$5+E46*$R$6+F46*$R$7) -> 192 | I46: =H46/1.2 -> 160 | J46: 44340 | K46: Payé | L46: Livrer | M46: VIREMENT
A47: 5 | B47: Aurelien Tracol | C47: 6 | G47: LIVRER GERMAINE | H47: =IF(K47="Cadeau",0,C47*$R$4+D47*$R$5+E47*$R$6+F47*$R$7) -> 96 | I47: =H47/1.2 -> 80 | J47: 44335 | K47: Payé | L47: Livrer | M47: CHEQUE | N47: DEPOT GINTRAND MAI
H48: =IF(K48="Cadeau",0,C48*$R$4+D48*$R$5+E48*$R$6+F48*$R$7) -> 0
A49: =IF(K49="CAdeau",0,MAX($A$3:A47)+1) -> 41 | B49: Philippe Gintrand | C49: 6 | G49: DEPOT ST VALLIER | H49: =IF(K49="Cadeau",0,C49*$R$4+D49*$R$5+E49*$R$6+F49*$R$7) -> 96 | I49: =H49/1.2 -> 80 | J49: 44248 | K49: Payé | L49: Livrer | M49: virement | N49: depot GINTRAND fevrier
A50: =IF(K50="CAdeau",0,MAX($A$3:A49)+1) -> 42 | B50: Pascal Fassaert | C50: 18 | G50: LIVRER | H50: =IF(K50="Cadeau",0,C50*$R$4+D50*$R$5+E50*$R$6+F50*$R$7) -> 288 | I50: =H50/1.2 -> 240 | J50: 44351 | K50: Payé | L50: Livrer | M50: Virement
A51: =IF(K51="CAdeau",0,MAX($A$3:A50)+1) -> 43 | B51: Fassaert Jeff | C51: 24 | G51: LIVRER | H51: =IF(K51="Cadeau",0,C51*$R$4+D51*$R$5+E51*$R$6+F51*$R$7) -> 384 | I51: =H51/1.2 -> 320 | J51: 44352 | K51: Payé | L51: Livrer | M51: VIREMENT
A52: =IF(K52="CAdeau",0,MAX($A$3:A51)+1) -> 44 | B52: JEAN MARTIN | C52: 6 | G52: LIVRER | H52: =IF(K52="Cadeau",0,C52*$R$4+D52*$R$5+E52*$R$6+F52*$R$7) -> 96 | I52: =H52/1.2 -> 80 | J52: 44352 | K52: Payé | L52: Livrer | M52: VIREMEnt
A53: =IF(K53="CAdeau",0,MAX($A$3:A52)+1) -> 45 | B53: Jacques Morel | C53: 60 | E53: 6 | G53: DEPOT BEA MERY | H53: =IF(K53="Cadeau",0,C53*$R$4+D53*$R$5+E53*$R$6+F53*$R$7) -> 1065 | I53: =H53/1.2 -> 887.5 | J53: 44352 | K53: Payé | L53: Livrer | M53: VIREMENT | N53: 12 SELEC /6BLC DE BLCS
A54: =IF(K54="CAdeau",0,MAX($A$3:A53)+1) -> 46 | B54: Yannick Fassaert | C54: 12 | G54: LIVRER | H54: =IF(K54="Cadeau",0,C54*$R$4+D54*$R$5+E54*$R$6+F54*$R$7) -> 192 | I54: =H54/1.2 -> 160 | J54: 44352 | K54: Payé | L54: Livrer | M54: CHEQUE
A55: =IF(K55="CAdeau",0,MAX($A$3:A54)+1) -> 47 | B55: François Meon | D55: 72 | H55: =IF(K55="Cadeau",0,C55*$R$4+D55*$R$5+E55*$R$6+F55*$R$7) -> 1296 | I55: =H55/1.2 -> 1080 | J55: 44361 | K55: Payé | L55: Livrer | M55: VIREMENT | N55: Par transporteur | O55: 70
A56: =IF(K56="CAdeau",0,MAX($A$3:A55)+1) -> 48 | B56: Xantie | C56: 18 | G56: LIVRER | H56: =IF(K56="Cadeau",0,C56*$R$4+D56*$R$5+E56*$R$6+F56*$R$7) -> 288 | I56: =H56/1.2 -> 240 | J56: 44353 | K56: Payé | L56: Livrer | M56: VIREMENT | N56: /140 EUROS EN ESPECE
A57: =IF(K57="CAdeau",0,MAX($A$3:A56)+1) -> 49 | B57: Jacques Morel | C57: 12 | E57: 6 | G57: LIVRER | H57: =IF(K57="Cadeau",0,C57*$R$4+D57*$R$5+E57*$R$6+F57*$R$7) -> 297 | I57: =H57/1.2 -> 247.5 | J57: 44353 | K57: Payé | L57: Livrer | M57: virement | N57: Dépôt mery
A58: =IF(K58="CAdeau",0,MAX($A$3:A57)+1) -> 50 | B58: Jacques Girard | C58: 6 | E58: 6 | G58: DEPOT ST VALLIER | H58: =IF(K58="Cadeau",0,C58*$R$4+D58*$R$5+E58*$R$6+F58*$R$7) -> 201 | I58: =H58/1.2 -> 167.5 | J58: 44357 | K58: Payé | L58: Livrer | M58: Cheque | N58: Dépôt st vallier mai
A59: =IF(K59="CAdeau",0,MAX($A$3:A58)+1) -> 51 | B59: Zimmermann Camille | C59: 6 | E59: 6 | G59: DEPOT LEO | H59: =IF(K59="Cadeau",0,C59*$R$4+D59*$R$5+E59*$R$6+F59*$R$7) -> 201 | I59: =H59/1.2 -> 167.5 | J59: 44381 | K59: Payé | M59: VIREMENT | N59: DEPOT LEO
A60: =IF(K60="CAdeau",0,MAX($A$3:A59)+1) -> 52 | B60: Garval /Amaral | C60: 1 | E60: 51 | G60: LIVRER | H60: =IF(K60="Cadeau",0,C60*$R$4+D60*$R$5+E60*$R$6+F60*$R$7) -> 908.5 | I60: =H60/1.2 -> 757.08333 | J60: 44381 | K60: Payé | L60: Livrer | M60: CHEQUE
A61: =IF(K61="CAdeau",0,MAX($A$3:A60)+1) -> 53 | B61: Sarha | E61: 1 | G61: LIVRER | H61: =IF(K61="Cadeau",0,C61*$R$4+D61*$R$5+E61*$R$6+F61*$R$7) -> 17.5 | I61: =H61/1.2 -> 14.583333 | J61: 44381 | K61: Payé | L61: Livrer
A62: =IF(K62="CAdeau",0,MAX($A$3:A61)+1) -> 0 | B62: James Carouge | C62: 2 | E62: 1 | G62: CONSO CADEAUX | H62: =IF(K62="Cadeau",0,C62*$R$4+D62*$R$5+E62*$R$6+F62*$R$7) -> 0 | I62: =H62/1.2 -> 0 | K62: Cadeau | M62: /CADEAU
A63: =IF(K63="CAdeau",0,MAX($A$3:A62)+1) -> 54 | B63: Léo Carouge | C63: 60 | D63: 24 | E63: 12 | G63: DEPOT LEO | H63: =IF(K63="Cadeau",0,C63*$R$4+D63*$R$5+E63*$R$6+F63*$R$7) -> 1602 | I63: =H63/1.2 -> 1335 | J63: 44383 | K63: En attente de paiement | M63: DEPOT | N63: LEO
A64: =IF(K64="CAdeau",0,MAX($A$3:A63)+1) -> 0 | B64: James Carouge | C64: 3 | D64: 3 | E64: 3 | G64: CADEAU CONSO | H64: =IF(K64="Cadeau",0,C64*$R$4+D64*$R$5+E64*$R$6+F64*$R$7) -> 0 | I64: =H64/1.2 -> 0 | J64: 44389 | K64: Cadeau | M64: CONSO | N64: SARDAIGNE
A65: =IF(K65="CAdeau",0,MAX($A$3:A64)+1) -> 55 | B65: Stanislas BOUTMY | C65: 6 | D65: 6 | G65: DEPOT LEO | H65: =IF(K65="Cadeau",0,C65*$R$4+D65*$R$5+E65*$R$6+F65*$R$7) -> 204 | I65: =H65/1.2 -> 170 | J65: 44397 | L65: Livrer | N65: LEO DEPOT
A66: =IF(K66="CAdeau",0,MAX($A$3:A65)+1) -> 56 | B66: Benjamin Straubhaar | C66: 24 | G66: DEPOT LEO | H66: =IF(K66="Cadeau",0,C66*$R$4+D66*$R$5+E66*$R$6+F66*$R$7) -> 384 | I66: =H66/1.2 -> 320 | J66: 44397 | K66: Payé | L66: Livrer | M66: VIREMENT | N66: LEO DEPOT
A67: =IF(K67="CAdeau",0,MAX($A$3:A66)+1) -> 57 | B67: Philémon Parent | C67: 6 | G67: LIVRER | H67: =IF(K67="Cadeau",0,C67*$R$4+D67*$R$5+E67*$R$6+F67*$R$7) -> 96 | I67: =H67/1.2 -> 80 | J67: 44410 | K67: Payé | L67: Livrer | M67: CHEQUE | N67: LIVRE JAMES GERMAINE
A68: =IF(K68="CAdeau",0,MAX($A$3:A67)+1) -> 58 | B68: Karine GATE | D68: 6 | G68: DEPOT LEO | H68: =IF(K68="Cadeau",0,C68*$R$4+D68*$R$5+E68*$R$6+F68*$R$7) -> 108 | I68: =H68/1.2 -> 90 | J68: 44413 | K68: Payé | L68: Livrer | M68: VIREMENT | N68: DEPOT LEO
A69: =IF(K69="CAdeau",0,MAX($A$3:A68)+1) -> 0 | H69: =IF(K69="Cadeau",0,C69*$R$4+D69*$R$5+E69*$R$6+F69*$R$7) -> 0 | K69: Cadeau
A70: =IF(K70="CAdeau",0,MAX($A$3:A69)+1) -> 59 | B70: Aymeric Chataigner | G70: 0 | H70: =IF(K70="Cadeau",0,C70*$R$4+D70*$R$5+E70*$R$6+F70*$R$7) -> 0 | I70: =H70/1.2 -> 0 | J70: 44420 | L70: Livrer | M70: virement | N70: LIVRE A BORDEAUX
A71: =IF(K71="CAdeau",0,MAX($A$3:A70)+1) -> 60 | B71: VICTOIRE SCHMITT | C71: 300 | G71: LIVRER | H71: =IF(K71="Cadeau",0,C71*$R$4+D71*$R$5+E71*$R$6+F71*$R$7) -> 4800 | I71: =H71/1.2 -> 4000 | J71: 44420 | K71: Payé | L71: Livrer | M71: virement | N71: livrer bordeaux 4500 EUROS
A72: =IF(K72="CAdeau",0,MAX($A$3:A71)+1) -> 61 | B72: Alice Dubourdieu | C72: 2 | D72: 2 | E72: 2 | G72: LIVRER | H72: =IF(K72="Cadeau",0,C72*$R$4+D72*$R$5+E72*$R$6+F72*$R$7) -> 103 | I72: =H72/1.2 -> 85.833333 | J72: 44420 | K72: Payé | L72: Livrer | M72: Virement
A73: =IF(K73="CAdeau",0,MAX($A$3:A72)+1) -> 62 | B73: Fanny Surman | C73: 2 | D73: 2 | E73: 8 | G73: LIVRER | H73: =IF(K73="Cadeau",0,C73*$R$4+D73*$R$5+E73*$R$6+F73*$R$7) -> 208 | I73: =H73/1.2 -> 173.33333 | J73: 44420 | K73: Payé | L73: Livrer | M73: Virement
A74: =IF(K74="CAdeau",0,MAX($A$3:A73)+1) -> 63 | B74: Daphne Morvan | C74: 6 | D74: 12 | E74: 6 | G74: LIVRER | H74: =IF(K74="Cadeau",0,C74*$R$4+D74*$R$5+E74*$R$6+F74*$R$7) -> 417 | I74: =H74/1.2 -> 347.5 | J74: 44420 | K74: Payé | L74: Livrer | M74: VIREMENT | N74: REGLE LE 28/10/2022
A75: =IF(K75="CAdeau",0,MAX($A$3:A74)+1) -> 64 | B75: cireddu camille | C75: 30 | G75: LIVRER | H75: =IF(K75="Cadeau",0,C75*$R$4+D75*$R$5+E75*$R$6+F75*$R$7) -> 480 | I75: =H75/1.2 -> 400 | J75: 44420 | K75: En attente de paiement | L75: Livrer | M75: VIR CHEQUE | N75: /SEYDOU 12 JUST ARNAUD 6
A76: =IF(K76="CAdeau",0,MAX($A$3:A75)+1) -> 65 | B76: Manon Juste Aguer | C76: 6 | G76: LIVRER | H76: =IF(K76="Cadeau",0,C76*$R$4+D76*$R$5+E76*$R$6+F76*$R$7) -> 96 | I76: =H76/1.2 -> 80 | J76: 44421 | K76: Payé | L76: Livrer
A77: =IF(K77="CAdeau",0,MAX($A$3:A76)+1) -> 66 | B77: CLAVERY ISABELLE | C77: 6 | G77: LIVREER | H77: =IF(K77="Cadeau",0,C77*$R$4+D77*$R$5+E77*$R$6+F77*$R$7) -> 96 | I77: =H77/1.2 -> 80 | J77: 44421 | K77: En attente de paiement | L77: Livrer
A78: =IF(K78="CAdeau",0,MAX($A$3:A77)+1) -> 67 | B78: JULIETTE | C78: 1 | D78: 1 | E78: 1 | G78: LIVRER | H78: =IF(K78="Cadeau",0,C78*$R$4+D78*$R$5+E78*$R$6+F78*$R$7) -> 51.5 | I78: =H78/1.2 -> 42.916667 | J78: 44421 | K78: Payé | L78: Livrer | M78: ESPECE | N78: CABANNE LEGE CAP FERRET
A79: =IF(K79="CAdeau",0,MAX($A$3:A78)+1) -> 68 | B79: Léo Carouge | C79: 18 | D79: 12 | E79: 6 | G79: DEPOT BORDEAUX | H79: =IF(K79="Cadeau",0,C79*$R$4+D79*$R$5+E79*$R$6+F79*$R$7) -> 609 | I79: =H79/1.2 -> 507.5 | J79: 44423 | L79: Livrer | N79: PICHOU 12 SEL/ ISA 12 ROSE ESPECE
A80: =IF(K80="CAdeau",0,MAX($A$3:A79)+1) -> 69 | B80: James Carouge | C80: 1 | D80: 2 | E80: 7 | F80: 1 | G80: CONSO | H80: 0 | I80: 0 | K80: En attente de paiement | M80: 0 | N80: CONSO CADEAUX
A81: =IF(K81="CAdeau",0,MAX($A$3:A80)+1) -> 70 | B81: ANNE KAES | C81: 3 | G81: DEPOT ISA | H81: =IF(K81="Cadeau",0,C81*$R$4+D81*$R$5+E81*$R$6+F81*$R$7) -> 48 | I81: =H81/1.2 -> 40 | J81: 44421 | K81: Payé | L81: Livrer | M81: VIREMENT | N81: SUR DEPOT ISA GREG
A82: =IF(K82="CAdeau",0,MAX($A$3:A81)+1) -> 71 | B82: PATRICK ABRY | C82: 5 | E82: 2 | G82: LIVRER | H82: =IF(K82="Cadeau",0,C82*$R$4+D82*$R$5+E82*$R$6+F82*$R$7) -> 115 | I82: =H82/1.2 -> 95.833333 | J82: 44439 | K82: Payé | L82: Livrer | M82: cheque | N82: BRETAGNE
A83: =IF(K83="CAdeau",0,MAX($A$3:A82)+1) -> 72 | B83: MARILYN SUIRE | C83: 6 | G83: LIVRER | H83: =IF(K83="Cadeau",0,C83*$R$4+D83*$R$5+E83*$R$6+F83*$R$7) -> 96 | I83: =H83/1.2 -> 80 | J83: 44435 | K83: Payé | L83: Livrer | M83: Cheque | N83: BRETAGNE
A84: =IF(K84="CAdeau",0,MAX($A$3:A83)+1) -> 73 | B84: MARIE CLAIRE LE CHAT PEAN | C84: 6 | G84: LIVRER | H84: =IF(K84="Cadeau",0,C84*$R$4+D84*$R$5+E84*$R$6+F84*$R$7) -> 96 | I84: =H84/1.2 -> 80 | J84: 44435 | K84: Payé | L84: Livrer | M84: Chèque | N84: BRETAGNE
A85: =IF(K85="CAdeau",0,MAX($A$3:A84)+1) -> 74 | B85: MARIE ANGE PARENTON | C85: 6 | G85: LIVRER | H85: =IF(K85="Cadeau",0,C85*$R$4+D85*$R$5+E85*$R$6+F85*$R$7) -> 96 | I85: =H85/1.2 -> 80 | J85: 44435 | K85: Payé | L85: Livrer | M85: Chèque | N85: BRETAGNE
A86: =IF(K86="CAdeau",0,MAX($A$3:A85)+1) -> 75 | B86: ANNE LE DOZE | C86: 6 | G86: LIVRER | H86: =IF(K86="Cadeau",0,C86*$R$4+D86*$R$5+E86*$R$6+F86*$R$7) -> 96 | I86: =H86/1.2 -> 80 | J86: 44435 | K86: Payé | L86: Livrer | M86: Chèque | N86: BRETAGNE
A87: =IF(K87="CAdeau",0,MAX($A$3:A86)+1) -> 76 | B87: Philippe Gintrand | C87: 6 | E87: 6 | G87: DEPOT ST VALLIER | H87: =IF(K87="Cadeau",0,C87*$R$4+D87*$R$5+E87*$R$6+F87*$R$7) -> 201 | I87: =H87/1.2 -> 167.5 | J87: 44439 | K87: Payé | L87: Livrer | M87: VIREMENT | N87: DEPOT ST VALLIER Simon Lea
A88: =IF(K88="CAdeau",0,MAX($A$3:A87)+1) -> 77 | B88: Aymeric Chataigner | C88: 198 | G88: 2 | H88: =IF(K88="Cadeau",0,C88*$R$4+D88*$R$5+E88*$R$6+F88*$R$7)-G88*SUM(C88:F88) -> 2772 | I88: =H88/1.2 -> 2310 | J88: 44423 | K88: Payé | L88: Livrer | M88: Virement | N88: RESTE EN ESPECE REMISE A 14 euros
A89: =IF(K89="CAdeau",0,MAX($A$3:A88)+1) -> 0 | B89: Denis Coutant | C89: 2 | G89: CADEAUX | H89: 0 | I89: =H89/1.2 -> 0 | K89: Cadeau | L89: Livrer | M89: CADEAU | N89: CADEAU
A90: =IF(K90="CAdeau",0,MAX($A$3:A89)+1) -> 78 | B90: Hugo Thomas | C90: 6 | G90: DEPOT LEO | H90: =IF(K90="Cadeau",0,C90*$R$4+D90*$R$5+E90*$R$6+F90*$R$7) -> 96 | I90: =H90/1.2 -> 80 | J90: 44462 | L90: Livrer | N90: STOCK LEO
A91: =IF(K91="CAdeau",0,MAX($A$3:A90)+1) -> 79 | B91: AGENCE LAGUILLON | C91: 24 | D91: 10 | E91: 48 | G91: LIVRERE EN PARTIE | H91: =IF(K91="Cadeau",0,C91*$R$4+D91*$R$5+E91*$R$6+F91*$R$7) -> 1404 | I91: =H91/1.2 -> 1170 | J91: 44470 | K91: Payé | L91: Livrer | M91: VIREMENT | N91: RESTE ALIVRER 32BLC 6 ROSE 6 SELEC
A92: =IF(K92="CAdeau",0,MAX($A$3:A91)+1) -> 0 | B92: Cadeau Vendages | C92: 6 | G92: CADEAUX VENDANGEURS | H92: =IF(K92="Cadeau",0,C92*$R$4+D92*$R$5+E92*$R$6+F92*$R$7) -> 0 | I92: =H92/1.2 -> 0 | J92: 44465 | K92: Cadeau | M92: Cadeau Vendangeurs | N92: REPRISE MAISON
A93: =IF(K93="CAdeau",0,MAX($A$3:A92)+1) -> 80 | B93: Léo Carouge | C93: 12 | G93: DEPOT LEO | H93: =IF(K93="Cadeau",0,C93*$R$4+D93*$R$5+E93*$R$6+F93*$R$7) -> 192 | I93: =H93/1.2 -> 160 | J93: 44472 | K93: En attente de paiement | L93: Livrer | N93: DEPOT LEO
A94: =IF(K94="CAdeau",0,MAX($A$3:A93)+1) -> 81 | B94: Stanislas BOUTMY | C94: 12 | D94: 6 | G94: DEPOT LEO | H94: =IF(K94="Cadeau",0,C94*$R$4+D94*$R$5+E94*$R$6+F94*$R$7) -> 300 | I94: =H94/1.2 -> 250 | J94: 44485 | K94: Payé | L94: Livrer | M94: Sortie de depot leo | N94: DEPOT LEO
A95: =IF(K95="CAdeau",0,MAX($A$3:A94)+1) -> 0 | B95: James Carouge | C95: 3 | D95: 3 | E95: 3 | G95: CONSO SARDAIGNE | H95: 0 | I95: =H95/1.2 -> 0 | J95: 44484 | K95: Cadeau | L95: Livrer | M95: CONSO | N95: SARDAIGNE
A96: =IF(K96="CAdeau",0,MAX($A$3:A95)+1) -> 82 | B96: Denis Coutant | C96: 12 | G96: DEPOT BEA | H96: =IF(K96="Cadeau",0,C96*$R$4+D96*$R$5+E96*$R$6+F96*$R$7) -> 192 | I96: =H96/1.2 -> 160 | J96: 44486 | K96: Payé | L96: LIVRER | M96: SORTI DE DEPOT BEA | N96: STOCK BEA TROYES
A97: =IF(K97="CAdeau",0,MAX($A$3:A96)+1) -> 83 | B97: Jacques Morel | C97: 36 | G97: DEPOT BEA | H97: =IF(K97="Cadeau",0,C97*$R$4+D97*$R$5+E97*$R$6+F97*$R$7) -> 576 | I97: =H97/1.2 -> 480 | J97: 44487 | K97: Payé | L97: Livrer | M97: SORTI DE DEPOT BEA | N97: SOLDE STOCK
A98: =IF(K98="CAdeau",0,MAX($A$3:A97)+1) -> 84 | B98: amie dubarbier Francoise | C98: 3 | D98: 1 | G98: DEPOT DUBARBIER | H98: =IF(K98="Cadeau",0,C98*$R$4+D98*$R$5+E98*$R$6+F98*$R$7) -> 66 | I98: =H98/1.2 -> 55 | J98: 44449 | K98: En attente de paiement | L98: Livrer | M98: VIREMENT 68 | N98: STOCK DUBARBIER
A99: =IF(K99="CAdeau",0,MAX($A$3:A98)+1) -> 85 | B99: Philippe Gintrand | C99: 6 | G99: DEPOT ST VALLIER | H99: =IF(K99="Cadeau",0,C99*$R$4+D99*$R$5+E99*$R$6+F99*$R$7) -> 96 | I99: =H99/1.2 -> 80 | J99: 44470 | K99: Payé | L99: Livrer | M99: VIREMENT | N99: STOCK ST VALLIER
A100: =IF(K100="CAdeau",0,MAX($A$3:A99)+1) -> 0 | B100: James Carouge | C100: 2 | E100: 2 | G100: CONSO | H100: 0 | I100: 0 | J100: 44492 | K100: Cadeau | L100: Livrer | M100: CONSO | N100: CRETE
...

Sheet LISTE DEROULANTE
A1: Cadeau | B1: A habiller
A2: A facturer | B2: Habillé
A3: Payé | B3: Livrer
A4: En attente de paiement
A5: Dégustation-Livraison

Sheet stocks
A2: SELECTION | H2: ROSE | N2: BLANC BLANC | T2: PRESTIGE | Z2: CRD
A3: mois | B3: entree | C3: sortie | D3: stock civc | E3: conso | F3: stock maison | H3: mois | I3: entree | J3: sortie | K3: stock civc | L3: conso | M3: stock maison | N3: mois | O3: entree | P3: sortie | Q3: stock civc | R3: conso | S3: stock maison | T3: mois | U3: entree | V3: sortie | W3: stock civc | X3: conso | Y3: stock maison | Z3: mois | AA3: entree | AB3: sortie | AC3: conso | AD3: stock
A4: 44136 | B4: 200 | D4: =B4-C4 -> 200 | F4: =D4-E4 -> 200 | H4: 44136 | I4: 50 | K4: =I4-J4 -> 50 | M4: =K4-L4 -> 50 | N4: 44136 | T4: 44136 | Z4: 44136 | AD4: =AA4-AB4-AC4 -> 0
A5: 44166 | B5: 150 | C5: 288 | D5: =D4+B5-C5 -> 62 | E5: 3 | F5: =D5-E5 -> 59 | H5: 44166 | J5: 48 | K5: =K4+I5-J5 -> 2 | M5: =K5-L5 -> 2 | N5: 44166 | T5: 44166 | Z5: 44166 | AA5: 550 | AB5: =C5+J5 -> 336 | AD5: =AD4+AA5-AB5-AC5 -> 214
A6: 44197 | B6: 100 | C6: 45 | D6: =D5+B6-C6 -> 117 | F6: =D6-E6 -> 117 | H6: 44197 | I6: 100 | J6: 14 | K6: =K5+I6-J6 -> 88 | M6: =K6-L6 -> 88 | N6: 44197 | T6: 44197 | Z6: 44197 | AB6: =C6+J6 -> 59 | AD6: =AD5+AA6-AB6-AC6 -> 155
A7: 44228 | C7: 103 | D7: =D6+B7-C7 -> 14 | F7: =D7-E7 -> 14 | H7: 44228 | J7: 51 | K7: =K6+I7-J7 -> 37 | M7: =K7-L7 -> 37 | N7: 44228 | T7: 44228 | Z7: 44228 | AA7: 300 | AB7: =C7+J7 -> 154 | AD7: =AD6+AA7-AB7-AC7 -> 301
A8: 44256 | B8: 100 | C8: 19 | D8: =D7+B8-C8 -> 95 | F8: =D8-E8 -> 95 | H8: 44256 | I8: 50 | J8: 14 | K8: =K7+I8-J8 -> 73 | M8: =K8-L8 -> 73 | N8: 44256 | T8: 44256 | Z8: 44256 | AB8: =C8+J8 -> 33 | AD8: =AD7+AA8-AB8-AC8 -> 268
A9: 44287 | B9: 100 | C9: 92 | D9: =D8+B9-C9 -> 103 | F9: =D9-E9 -> 103 | H9: 44287 | J9: 12 | K9: =K8+I9-J9 -> 61 | M9: =K9-L9 -> 61 | N9: 44287 | O9: 50 | T9: 44287 | U9: 50 | Z9: 44287 | AA9: 150 | AB9: =C9+J9 -> 104 | AD9: =AD8+AA9-AB9-AC9 -> 314
A10: 44317 | B10: 150 | C10: 75 | D10: =D9+B10-C10 -> 178 | F10: =D10-E10 -> 178 | H10: 44317 | I10: 50 | J10: 33 | K10: =K9+I10-J10 -> 78 | M10: =K10-L10 -> 78 | N10: 44317 | O10: 100 | P10: 27 | Q10: =O9-P10 -> 23 | S10: =Q10-R10 -> 23 | T10: 44317 | Z10: 44317 | AA10: 400 | AB10: =C10+J10+P10+V10 -> 135 | AD10: =AD9+AA10-AB10-AC10 -> 579
A11: 44348 | B11: 150 | C11: 138 | D11: =D10+B11-C11 -> 190 | F11: =D11-E11 -> 190 | H11: 44348 | I11: 50 | J11: 72 | K11: =K10+I11-J11 -> 56 | M11: =K11-L11 -> 56 | N11: 44348 | P11: 7 | R11: 1 | T11: 44348 | Z11: 44348 | AB11: 218 | AD11: =AD10+AA11-AB11-AC11 -> 361
A12: 44378 | B12: 250 | C12: 66 | D12: =D11+B12-C12 -> 374 | F12: =D12-E12 -> 374 | H12: 44378 | J12: 27 | K12: =K11+I12-J12 -> 29 | M12: =K12-L12 -> 29 | N12: 44378 | P12: 68 | S12: 34 | T12: 44378 | Z12: 44378 | AA12: 1000 | AB12: 161 | AD12: =AD11+AA12-AB12-AC12 -> 1200
A13: 44409 | B13: 300 | C13: 605 | D13: =D12+B13-C13 -> 69 | F13: =D13-E13 -> 69 | H13: 44409 | J13: 25 | K13: =K12+I13-J13 -> 4 | M13: =K13-L13 -> 4 | N13: 44409 | P13: 38 | R13: 1 | T13: 44409 | X13: 1 | Z13: 44409 | AB13: 669 | AD13: =AD12+AA13-AB13-AC13 -> 531
A14: 44440 | B14: 100 | C14: 26 | D14: =D13+B14-C14 -> 143 | F14: =D14-E14 -> 143 | H14: 44440 | I14: 50 | J14: 4 | K14: =K13+I14-J14 -> 50 | M14: =K14-L14 -> 50 | N14: 44440 | O14: 100 | P14: 16 | S14: 100 | T14: 44440 | Z14: 44440 | AB14: 47 | AD14: =AD13+AA14-AB14-AC14 -> 484
A15: 44470 | C15: 5 | D15: =D14+B15-C15 -> 138 | F15: =D15-E15 -> 138 | H15: 44470 | J15: 3 | K15: =K14+I15-J15 -> 47 | M15: =K15-L15 -> 47 | N15: 44470 | P15: 5 | T15: 44470 | Z15: 44470 | AB15: =C15+J15 -> 8 | AD15: =AD14+AA15-AB15-AC15 -> 476
A16: 44501 | C16: 36 | D16: =D15+B16-C16 -> 102 | F16: =D16-E16 -> 102 | H16: 44501 | K16: =K15+I16-J16 -> 47 | M16: =K16-L16 -> 47 | N16: 44501 | P16: 20 | T16: 44501 | Z16: 44501 | AB16: 56 | AD16: =AD15+AA16-AB16-AC16 -> 420
A17: 44531 | C17: 81 | D17: =D16+B17-C17 -> 21 | F17: =D17-E17 -> 21 | H17: 44531 | J17: 37 | K17: =K16+I17-J17 -> 10 | M17: =K17-L17 -> 10 | N17: 44531 | O17: 100 | P17: 75 | T17: 44531 | X17: 8 | Z17: 44531 | AB17: 201 | AD17: =AD16+AA17-AB17-AC17 -> 219
A18: 44562 | B18: 100 | C18: 6 | D18: =D17+B18-C18 -> 115 | F18: =D18-E18 -> 115 | H18: 44562 | I18: 50 | J18: 6 | K18: =K17+I18-J18 -> 54 | M18: =K18-L18 -> 54 | N18: 44562 | P18: 32 | T18: 44562 | Z18: 44562 | AA18: 50 | AB18: 44 | AD18: =AD17+AA18-AB18-AC18 -> 225
B20: ROSE | E20: SELEC | H20: BB | K20: PRESTIGE | O20: CONSO PERSO | P20: ROSE | Q20: SELEC | R20: BB | S20: PRESTIGE
A21: LIEU DE STOCK | B21: STOCK | C21: entre | D21: sorti | E21: STOCK | F21: entre | G21: sorti | H21: STOCK | I21: entre | J21: sorti | K21: STOCK | L21: entre | M21: sorti | O21: 44136
A22: DUBARBIER | B22: =C22-D22 -> 8 | C22: 12 | D22: 4 | E22: =F22-G22 -> 20 | F22: 24 | G22: 4 | H22: =I22-J22 -> 0 | K22: =L22-M22 -> 0 | O22: 44166
A23: FASSAERT | B23: =C23-D23 -> 0 | E23: =F23-G23 -> 0 | H23: =I23-J23 -> 0 | K23: =L23-M23 -> 0 | O23: 44197
A24: GINTRAND | B24: =C24-D24 -> 30 | C24: 30 | E24: =F24-G24 -> 36 | F24: 54 | G24: 18 | H24: =I24-J24 -> 0 | I24: 18 | J24: 18 | K24: =L24-M24 -> 0 | O24: 44228
A25: LEO | B25: =C25-D25 -> 6 | C25: 6 | E25: =F25-G25 -> 6 | F25: 6 | H25: =I25-J25 -> 6 | I25: 6 | K25: =L25-M25 -> 0 | O25: 44256
A26: GREGORY | B26: =C26-D26 -> 12 | C26: 12 | E26: =F26-G26 -> 33 | F26: 36 | G26: 3 | H26: =I26-J26 -> 0 | K26: =L26-M26 -> 0 | O26: 44287
A27: ,Morel Bea | B27: 48 | G27: 48 | O27: 44317 | Q27: 6
O28: 44348 | R28: 1
O29: 44378 | P29: 4 | Q29: 4 | R29: 3
O30: 44409 | P30: 2 | Q30: 1 | R30: 7 | S30: 1
O31: 44440
O32: 44470
O33: 44501
O34: 44531 | P34: 4 | Q34: 9 | R34: 14 | S34: 8
O35: 44562
